Workbook

Sheet Apr'25  H2
B1: Fe 500
A2: Region / Date | B2: Ex-Ahmedabad | C2: Ex-Bangalore | D2: Ex-Chennai | E2: Ex-Delhi/NCR | F2: Ex-Durgapur | G2: Ex-Goa | H2: Ex-Hyderabad | I2: Ex-Jaipur | J2: Ex-Jalna | K2: Ex-Mandi Gobindgarh | L2: Ex-Mumbai | M2: Ex-Muzaffarnagar | N2: Ex-Patna | O2: Ex-Raigarh | P2: Ex-Raipur | Q2: Ex-Rourkela
A3: 45763 | E3: 48700 | I3: =_xlfn.XLOOKUP(A3,'steel Mint data'!A:A,'steel Mint data'!I:I) -> 47500 | K3: 48700 | P3: 45800 | Q3: 46000
A4: =A3+1 -> 45764 | E4: 48600 | I4: =_xlfn.XLOOKUP(A4,'steel Mint data'!A:A,'steel Mint data'!I:I) -> 47200 | K4: 48400 | P4: 45400 | Q4: 45800
A5: =A4+1 -> 45765 | E5: 48600 | I5: =_xlfn.XLOOKUP(A5,'steel Mint data'!A:A,'steel Mint data'!I:I) -> 47000 | K5: 48300 | P5: 45200 | Q5: 45700
A6: =A5+1 -> 45766 | E6: 48400 | I6: =_xlfn.XLOOKUP(A6,'steel Mint data'!A:A,'steel Mint data'!I:I) -> 46800 | K6: 48100 | P6: 44800 | Q6: 45600
A7: =A6+1 -> 45767 | I7: =_xlfn.XLOOKUP(A7,'steel Mint data'!A:A,'steel Mint data'!I:I) -> H
A8: =A7+1 -> 45768 | E8: 47900 | I8: =_xlfn.XLOOKUP(A8,'steel Mint data'!A:A,'steel Mint data'!I:I) -> 46800 | K8: 48000 | P8: 44700 | Q8: 45500
A9: =A8+1 -> 45769 | E9: 48600 | I9: =_xlfn.XLOOKUP(A9,'steel Mint data'!A:A,'steel Mint data'!I:I) -> 47500 | K9: 49000 | P9: 45600 | Q9: 46300
A10: =A9+1 -> 45770 | E10: 48600 | I10: =_xlfn.XLOOKUP(A10,'steel Mint data'!A:A,'steel Mint data'!I:I) -> 47300 | K10: 48900 | P10: 45200 | Q10: 45700
A11: =A10+1 -> 45771 | E11: =_xlfn.XLOOKUP(A11,'steel Mint data'!A:A,'steel Mint data'!D:D,"",0) -> 48400 | I11: =_xlfn.XLOOKUP(A11,'steel Mint data'!A:A,'steel Mint data'!I:I) -> 47300 | K11: =_xlfn.XLOOKUP(A11,'steel Mint data'!A:A,'steel Mint data'!L:L,"",0) -> 48900 | P11: =_xlfn.XLOOKUP(A11,'steel Mint data'!A:A,'steel Mint data'!Q:Q,"",0) -> 45200 | Q11: =_xlfn.XLOOKUP(A11,'steel Mint data'!A:A,'steel Mint data'!R:R,"",0) -> 45500
A12: =A11+1 -> 45772 | E12: =_xlfn.XLOOKUP(A12,'steel Mint data'!A:A,'steel Mint data'!D:D,"",0) -> 48300 | I12: =_xlfn.XLOOKUP(A12,'steel Mint data'!A:A,'steel Mint data'!I:I) -> 47000 | K12: =_xlfn.XLOOKUP(A12,'steel Mint data'!A:A,'steel Mint data'!L:L,"",0) -> 48700 | P12: =_xlfn.XLOOKUP(A12,'steel Mint data'!A:A,'steel Mint data'!Q:Q,"",0) -> 45000 | Q12: =_xlfn.XLOOKUP(A12,'steel Mint data'!A:A,'steel Mint data'!R:R,"",0) -> 45500
A13: =A12+1 -> 45773 | E13: =_xlfn.XLOOKUP(A13,'steel Mint data'!A:A,'steel Mint data'!D:D,"",0) -> 48100 | I13: =_xlfn.XLOOKUP(A13,'steel Mint data'!A:A,'steel Mint data'!I:I) -> 47000 | K13: =_xlfn.XLOOKUP(A13,'steel Mint data'!A:A,'steel Mint data'!L:L,"",0) -> 48500 | P13: =_xlfn.XLOOKUP(A13,'steel Mint data'!A:A,'steel Mint data'!Q:Q,"",0) -> 45000 | Q13: =_xlfn.XLOOKUP(A13,'steel Mint data'!A:A,'steel Mint data'!R:R,"",0) -> 45300
A14: =A13+1 -> 45774 | E14: =_xlfn.XLOOKUP(A14,'steel Mint data'!A:A,'steel Mint data'!D:D,"",0) -> H | I14: =_xlfn.XLOOKUP(A14,'steel Mint data'!A:A,'steel Mint data'!I:I) -> H | K14: =_xlfn.XLOOKUP(A14,'steel Mint data'!A:A,'steel Mint data'!L:L,"",0) -> H | P14: =_xlfn.XLOOKUP(A14,'steel Mint data'!A:A,'steel Mint data'!Q:Q,"",0) -> H | Q14: =_xlfn.XLOOKUP(A14,'steel Mint data'!A:A,'steel Mint data'!R:R,"",0) -> H
A15: =A14+1 -> 45775 | E15: =_xlfn.XLOOKUP(A15,'steel Mint data'!A:A,'steel Mint data'!D:D,"",0) -> 47800 | I15: =_xlfn.XLOOKUP(A15,'steel Mint data'!A:A,'steel Mint data'!I:I) -> 46500 | K15: =_xlfn.XLOOKUP(A15,'steel Mint data'!A:A,'steel Mint data'!L:L,"",0) -> 48300 | P15: =_xlfn.XLOOKUP(A15,'steel Mint data'!A:A,'steel Mint data'!Q:Q,"",0) -> 45000 | Q15: =_xlfn.XLOOKUP(A15,'steel Mint data'!A:A,'steel Mint data'!R:R,"",0) -> 44900
A16: =A15+1 -> 45776 | E16: =_xlfn.XLOOKUP(A16,'steel Mint data'!A:A,'steel Mint data'!D:D,"",0) -> 47800 | I16: =_xlfn.XLOOKUP(A16,'steel Mint data'!A:A,'steel Mint data'!I:I) -> 46500 | K16: =_xlfn.XLOOKUP(A16,'steel Mint data'!A:A,'steel Mint data'!L:L,"",0) -> 48200 | P16: =_xlfn.XLOOKUP(A16,'steel Mint data'!A:A,'steel Mint data'!Q:Q,"",0) -> 44800 | Q16: =_xlfn.XLOOKUP(A16,'steel Mint data'!A:A,'steel Mint data'!R:R,"",0) -> 44900
A17: =A16+1 -> 45777 | E17: =_xlfn.XLOOKUP(A17,'steel Mint data'!A:A,'steel Mint data'!D:D,"",0) -> 47300 | I17: =_xlfn.XLOOKUP(A17,'steel Mint data'!A:A,'steel Mint data'!I:I) -> 46200 | K17: =_xlfn.XLOOKUP(A17,'steel Mint data'!A:A,'steel Mint data'!L:L,"",0) -> 48200 | P17: =_xlfn.XLOOKUP(A17,'steel Mint data'!A:A,'steel Mint data'!Q:Q,"",0) -> 44500 | Q17: =_xlfn.XLOOKUP(A17,'steel Mint data'!A:A,'steel Mint data'!R:R,"",0) -> 44700
E19: =SUM(E3:E18) -> 627100 | K19: =SUM(K3:K18) -> 630200 | P19: =SUM(P3:P18) -> 586200 | Q19: =SUM(Q3:Q18) -> 591400
B20: Amba Shakti (NCR) | C20: API (Raipur) | D20: Aditya Industries (Mandi) | E20: Shree Ganesh (Rourkela) | F20: SKA Raipur | G20: Amba Gwalior | H20: SKA
A21: Avg Price - Divided by no of days steel mint price is available | B21: =E19/O21 -> 48238.462 | C21: =P19/O21 -> 45092.308 | D21: =K19/O21 -> 48476.923 | E21: =Q19/O21 -> 45492.308 | F21: =C21 -> 45092.308 | G21: =B21-800 -> 47438.462 | O21: =COUNT(P3:P18) -> 13
A22: BIS | B22: 1200 | C22: 2150 | D22: 400 | E22: 2200 | F22: 1800 | G22: 1200
A23: Loading Charges | B23: 200 | C23: 265 | D23: 250 | E23: 275 | F23: 275 | G23: 200
A24: Actual PO Price (base dia): A | B24: =SUM(B21:B23) -> 49638.462 | C24: =SUM(C21:C23) -> 47507.308 | D24: =SUM(D21:D23) -> 49126.923 | E24: =SUM(E21:E23) -> 47967.308 | F24: =SUM(F21:F23) -> 47167.308 | G24: =SUM(G21:G23) -> 48838.462 | H24: 47217 | K24: =52150-C24-1250 -> 3392.6923
A25: Notional PO: B | B25: 50900 | C25: 48415 | D25: 49550 | E25: 48575 | F25: 48575 | G25: 50300 | H25: 46875
A26: Change (A-B) | B26: =B24-B25 -> -1261.5385 | C26: =C24-C25 -> -907.69231 | D26: =D24-D25 -> -423.07692 | E26: =E24-E25 -> -607.69231 | F26: =F24-F25 -> -1407.6923 | G26: =G24-G25 -> -1461.5385
J27: =52500-C24-1250 -> 3742.6923
A28: Current PL | B28: 56400 | C28: 53650 | D28: 56900 | E28: 53650 | F28: 53650 | G28: =B28-800 -> 55600
A29: Current ex plant NR | B29: =B28-2300 -> 54100 | C29: =C28-2300 -> 51350 | D29: =D28-2300 -> 54600 | E29: =E28-2300 -> 51350 | F29: =F28-2300 -> 51350 | G29: =G28-2300 -> 53300
A30: Current GM: C | B30: =B29-B24 -> 4461.5385 | C30: =C29-C24 -> 3842.6923 | D30: =D29-D24 -> 5473.0769 | E30: =E29-E24 -> 3382.6923 | F30: =F29-F24 -> 4182.6923 | G30: =G29-G24 -> 4461.5385 | I30: =54500-G24-1000 -> 4661.5385
F31: as per H1
E32: Notional PO | F32: 46875

Sheet May'25 H1
B1: Fe 500
A2: Region / Date | B2: Ex-Ahmedabad | C2: Ex-Bangalore | D2: Ex-Chennai | E2: Ex-Delhi/NCR | F2: Ex-Durgapur | G2: Ex-Goa | H2: Ex-Hyderabad | I2: Ex-Jaipur | J2: Ex-Jalna | K2: Ex-Mandi Gobindgarh | L2: Ex-Mumbai | M2: Ex-Muzaffarnagar | N2: Ex-Patna | O2: Ex-Raigarh | P2: Ex-Raipur | Q2: Ex-Rourkela
A3: 45778 | E3: =_xlfn.XLOOKUP(A3,'steel Mint data'!A:A,'steel Mint data'!D:D,"",0) -> 47500 | I3: =_xlfn.XLOOKUP(A3,'steel Mint data'!A:A,'steel Mint data'!I:I,"",0) -> 46200 | K3: =_xlfn.XLOOKUP(A3,'steel Mint data'!A:A,'steel Mint data'!L:L,"",0) -> 48100 | P3: =_xlfn.XLOOKUP(A3,'steel Mint data'!A:A,'steel Mint data'!Q:Q,"",0) -> 44500 | Q3: =_xlfn.XLOOKUP(A3,'steel Mint data'!A:A,'steel Mint data'!R:R,"",0) -> 44600
A4: =A3+1 -> 45779 | E4: =_xlfn.XLOOKUP(A4,'steel Mint data'!A:A,'steel Mint data'!D:D,"",0) -> 47500 | I4: =_xlfn.XLOOKUP(A4,'steel Mint data'!A:A,'steel Mint data'!I:I,"",0) -> 46200 | K4: =_xlfn.XLOOKUP(A4,'steel Mint data'!A:A,'steel Mint data'!L:L,"",0) -> 48000 | P4: =_xlfn.XLOOKUP(A4,'steel Mint data'!A:A,'steel Mint data'!Q:Q,"",0) -> 44500 | Q4: =_xlfn.XLOOKUP(A4,'steel Mint data'!A:A,'steel Mint data'!R:R,"",0) -> 44300
A5: =A4+1 -> 45780 | E5: =_xlfn.XLOOKUP(A5,'steel Mint data'!A:A,'steel Mint data'!D:D,"",0) -> 47300 | I5: =_xlfn.XLOOKUP(A5,'steel Mint data'!A:A,'steel Mint data'!I:I,"",0) -> 46300 | K5: =_xlfn.XLOOKUP(A5,'steel Mint data'!A:A,'steel Mint data'!L:L,"",0) -> 48000 | P5: =_xlfn.XLOOKUP(A5,'steel Mint data'!A:A,'steel Mint data'!Q:Q,"",0) -> 44300 | Q5: =_xlfn.XLOOKUP(A5,'steel Mint data'!A:A,'steel Mint data'!R:R,"",0) -> 44500
A6: =A5+1 -> 45781 | E6: =_xlfn.XLOOKUP(A6,'steel Mint data'!A:A,'steel Mint data'!D:D,"",0) -> H | I6: =_xlfn.XLOOKUP(A6,'steel Mint data'!A:A,'steel Mint data'!I:I,"",0) -> H | K6: =_xlfn.XLOOKUP(A6,'steel Mint data'!A:A,'steel Mint data'!L:L,"",0) -> H | P6: =_xlfn.XLOOKUP(A6,'steel Mint data'!A:A,'steel Mint data'!Q:Q,"",0) -> H | Q6: =_xlfn.XLOOKUP(A6,'steel Mint data'!A:A,'steel Mint data'!R:R,"",0) -> H
A7: =A6+1 -> 45782 | E7: =_xlfn.XLOOKUP(A7,'steel Mint data'!A:A,'steel Mint data'!D:D,"",0) -> 47300 | I7: =_xlfn.XLOOKUP(A7,'steel Mint data'!A:A,'steel Mint data'!I:I,"",0) -> 46400 | K7: =_xlfn.XLOOKUP(A7,'steel Mint data'!A:A,'steel Mint data'!L:L,"",0) -> 48000 | P7: =_xlfn.XLOOKUP(A7,'steel Mint data'!A:A,'steel Mint data'!Q:Q,"",0) -> 44400 | Q7: =_xlfn.XLOOKUP(A7,'steel Mint data'!A:A,'steel Mint data'!R:R,"",0) -> 44500
A8: =A7+1 -> 45783 | E8: =_xlfn.XLOOKUP(A8,'steel Mint data'!A:A,'steel Mint data'!D:D,"",0) -> 47200 | I8: =_xlfn.XLOOKUP(A8,'steel Mint data'!A:A,'steel Mint data'!I:I,"",0) -> 46300 | K8: =_xlfn.XLOOKUP(A8,'steel Mint data'!A:A,'steel Mint data'!L:L,"",0) -> 48000 | P8: =_xlfn.XLOOKUP(A8,'steel Mint data'!A:A,'steel Mint data'!Q:Q,"",0) -> 44300 | Q8: =_xlfn.XLOOKUP(A8,'steel Mint data'!A:A,'steel Mint data'!R:R,"",0) -> 44300
A9: =A8+1 -> 45784 | E9: =_xlfn.XLOOKUP(A9,'steel Mint data'!A:A,'steel Mint data'!D:D,"",0) -> 47000 | I9: =_xlfn.XLOOKUP(A9,'steel Mint data'!A:A,'steel Mint data'!I:I,"",0) -> 46000 | K9: =_xlfn.XLOOKUP(A9,'steel Mint data'!A:A,'steel Mint data'!L:L,"",0) -> 47700 | P9: =_xlfn.XLOOKUP(A9,'steel Mint data'!A:A,'steel Mint data'!Q:Q,"",0) -> 44200 | Q9: =_xlfn.XLOOKUP(A9,'steel Mint data'!A:A,'steel Mint data'!R:R,"",0) -> 44200
A10: =A9+1 -> 45785 | E10: =_xlfn.XLOOKUP(A10,'steel Mint data'!A:A,'steel Mint data'!D:D,"",0) -> 47000 | I10: =_xlfn.XLOOKUP(A10,'steel Mint data'!A:A,'steel Mint data'!I:I,"",0) -> 46000 | K10: =_xlfn.XLOOKUP(A10,'steel Mint data'!A:A,'steel Mint data'!L:L,"",0) -> 47700 | P10: =_xlfn.XLOOKUP(A10,'steel Mint data'!A:A,'steel Mint data'!Q:Q,"",0) -> 44100 | Q10: =_xlfn.XLOOKUP(A10,'steel Mint data'!A:A,'steel Mint data'!R:R,"",0) -> 44000
A11: =A10+1 -> 45786 | E11: =_xlfn.XLOOKUP(A11,'steel Mint data'!A:A,'steel Mint data'!D:D,"",0) -> 47000 | I11: =_xlfn.XLOOKUP(A11,'steel Mint data'!A:A,'steel Mint data'!I:I,"",0) -> 46000 | K11: =_xlfn.XLOOKUP(A11,'steel Mint data'!A:A,'steel Mint data'!L:L,"",0) -> 47700 | P11: =_xlfn.XLOOKUP(A11,'steel Mint data'!A:A,'steel Mint data'!Q:Q,"",0) -> 43900 | Q11: =_xlfn.XLOOKUP(A11,'steel Mint data'!A:A,'steel Mint data'!R:R,"",0) -> 44000
A12: =A11+1 -> 45787 | E12: =_xlfn.XLOOKUP(A12,'steel Mint data'!A:A,'steel Mint data'!D:D,"",0) -> 47000 | I12: =_xlfn.XLOOKUP(A12,'steel Mint data'!A:A,'steel Mint data'!I:I,"",0) -> 45900 | K12: =_xlfn.XLOOKUP(A12,'steel Mint data'!A:A,'steel Mint data'!L:L,"",0) -> 47600 | P12: =_xlfn.XLOOKUP(A12,'steel Mint data'!A:A,'steel Mint data'!Q:Q,"",0) -> 43800 | Q12: =_xlfn.XLOOKUP(A12,'steel Mint data'!A:A,'steel Mint data'!R:R,"",0) -> 43800
A13: =A12+1 -> 45788 | E13: =_xlfn.XLOOKUP(A13,'steel Mint data'!A:A,'steel Mint data'!D:D,"",0) -> H | I13: =_xlfn.XLOOKUP(A13,'steel Mint data'!A:A,'steel Mint data'!I:I,"",0) -> H | K13: =_xlfn.XLOOKUP(A13,'steel Mint data'!A:A,'steel Mint data'!L:L,"",0) -> H | P13: =_xlfn.XLOOKUP(A13,'steel Mint data'!A:A,'steel Mint data'!Q:Q,"",0) -> H | Q13: =_xlfn.XLOOKUP(A13,'steel Mint data'!A:A,'steel Mint data'!R:R,"",0) -> H
A14: =A13+1 -> 45789 | E14: =_xlfn.XLOOKUP(A14,'steel Mint data'!A:A,'steel Mint data'!D:D,"",0) -> 47300 | I14: =_xlfn.XLOOKUP(A14,'steel Mint data'!A:A,'steel Mint data'!I:I,"",0) -> 46100 | K14: =_xlfn.XLOOKUP(A14,'steel Mint data'!A:A,'steel Mint data'!L:L,"",0) -> 47800 | P14: =_xlfn.XLOOKUP(A14,'steel Mint data'!A:A,'steel Mint data'!Q:Q,"",0) -> 44100 | Q14: =_xlfn.XLOOKUP(A14,'steel Mint data'!A:A,'steel Mint data'!R:R,"",0) -> 44100
A15: =A14+1 -> 45790 | E15: =_xlfn.XLOOKUP(A15,'steel Mint data'!A:A,'steel Mint data'!D:D,"",0) -> 47400 | I15: =_xlfn.XLOOKUP(A15,'steel Mint data'!A:A,'steel Mint data'!I:I,"",0) -> 45800 | K15: =_xlfn.XLOOKUP(A15,'steel Mint data'!A:A,'steel Mint data'!L:L,"",0) -> 47700 | P15: =_xlfn.XLOOKUP(A15,'steel Mint data'!A:A,'steel Mint data'!Q:Q,"",0) -> 43900 | Q15: =_xlfn.XLOOKUP(A15,'steel Mint data'!A:A,'steel Mint data'!R:R,"",0) -> 43800
... A17: =A16+1 -> 45792 | E17: =_xlfn.XLOOKUP(A17,'steel Mint data'!A:A,'steel Mint data'!D:D,"",0) -> 47200 | I17: =_xlfn.XLOOKUP(A17,'steel Mint data'!A:A,'steel Mint data'!I:I,"",0) -> 45600 | K17: =_xlfn.XLOOKUP(A17,'steel Mint data'!A:A,'steel Mint data'!L:L,"",0) -> 47500 | P17: =_xlfn.XLOOKUP(A17,'steel Mint data'!A:A,'steel Mint data'!Q:Q,"",0) -> 43500 | Q17: =_xlfn.XLOOKUP(A17,'steel Mint data'!A:A,'steel Mint data'!R:R,"",0) -> 43700
E19: =SUM(E3:E18) -> 614100 | K19: =SUM(K3:K18) -> 621300 | P19: =SUM(P3:P18) -> 573200 | Q19: =SUM(Q3:Q18) -> 573500
B20: Amba Shakti (NCR) | C20: API (Raipur) | D20: Aditya Industries (Mandi) | E20: Shree Ganesh (Rourkela) | F20: SKA Raipur | G20: Amba Gwalior
A21: Avg Price - Divided by no of days steel mint price is available | B21: =E19/O21 -> 47238.462 | C21: =P19/O21 -> 44092.308 | D21: =K19/O21 -> 47792.308 | E21: =Q19/O21 -> 44115.385 | F21: =C21 -> 44092.308 | G21: =B21-800 -> 46438.462 | O21: =COUNT(P3:P17) -> 13
A22: BIS | B22: 1200 | C22: 2150 | D22: 400 | E22: 2200 | F22: 1800 | G22: 1200 | I22: =55000-1500-1000-G24 -> 4661.5385 | L22: =54500-3500-C24 -> 4492.6923
A23: Loading Charges | B23: 200 | C23: 265 | D23: 250 | E23: 275 | F23: 275 | G23: 200 | J23: =C24-G24 -> -1331.1538 | K23: =53500-G24-1000 -> 4661.5385
A24: Actual PO Price (base dia): A | B24: =SUM(B21:B23) -> 48638.462 | C24: =SUM(C21:C23) -> 46507.308 | D24: =SUM(D21:D23) -> 48442.308 | E24: =SUM(E21:E23) -> 46590.385 | F24: =SUM(F21:F23) -> 46167.308 | G24: =SUM(G21:G23) -> 47838.462 | H24: =54500-2000-1000-G24 -> 3661.5385 | I24: 13 | K24: =53500-G25-1000 -> 4100 | M24: =52300-B24 -> 3661.5385 | O24: =G24+3500+1000 -> 52338.462 | P24: =52900-B24 -> 4261.5385
A25: Notional PO: B | B25: 49200 | C25: 47415 | D25: 48950 | E25: 47375 | F25: 47075 | G25: 48400 | H25: 32 | I25: 22 | J25: =I25/45 -> 0.48888889 | K25: =1500*J25 -> 733.33333 | M25: =52300-B25 -> 3100 | P25: =52900-B25 -> 3700
A26: Change (A-B) | B26: =B24-B25 -> -561.53846 | C26: =C24-C25 -> -907.69231 | D26: =D24-D25 -> -507.69231 | E26: =E24-E25 -> -784.61538 | F26: =F24-F25 -> -907.69231 | G26: =G24-G25 -> -561.53846
L27: =53500 -> 53500 | N27: 53750
A28: Current PL | B28: 56400 | C28: 53650 | D28: 56900 | E28: 53650 | F28: 53650 | G28: =B28-800 -> 55600 | L28: 1315 | N28: =53750-B24 -> 5111.5385
A29: Current ex plant NR | B29: =B28-2300 -> 54100 | C29: =C28-2300 -> 51350 | D29: =D28-2300 -> 54600 | E29: =E28-2300 -> 51350 | F29: =F28-2300 -> 51350 | G29: =G28-2300 -> 53300 | J29: =55500 -> 55500 | L29: 52500 | N29: =53750-B25 -> 4550
A30: Current GM: C | B30: =B29-B24 -> 5461.5385 | C30: =C29-C24 -> 4842.6923 | D30: =D29-D24 -> 6157.6923 | E30: =E29-E24 -> 4759.6154 | F30: =F29-F24 -> 5182.6923 | G30: =G29-G24 -> 5461.5385 | I30: =C24+1250+2500 -> 50257.308 | J30: 800 | L30: =L29-B24 -> 3861.5385
F31: as per H1 | L31: =L29-B25 -> 3300
B32: =54400-D24-1000 -> 4957.6923 | E32: Notional PO | F32: 46875 | J32: 52500 | P32: =53700-1050-D24 -> 4207.6923
J33: =J32-D24-1000 -> 3057.6923
D34: 51300 | H34: =53500-1250 -> 52250 | J34: =J32-D25-1000 -> 2550 | K34: =54500-2000-1000-G24 -> 3661.5385 | M34: =53000-1200 -> 51800
D35: =D34-C24-1250 -> 3542.6923 | F35: =51800-B24 -> 3161.5385 | H35: =52250-1000-G24 -> 3411.5385
A36: Kala Amb | B36: =D24+1000+3000 -> 52442.308 | D36: =51300-C25-1250 -> 2635 | F36: =51800-B25 -> 2600 | H36: =52250-1000-G25 -> 2850
A37: Gwalior | B37: =G24+1000+3000 -> 51838.462 | K37: =54000-1100-1000-G24 -> 4061.5385
G38: =5440 -> 5440
L39: =54400-D24-1000 -> 4957.6923
H40: 32mm | I40: 0.35 | J40: =I40*2000 -> 700
H41: =G24+1000 -> 48838.462

Sheet May'25 H2
B1: Fe 500
A2: Region / Date | B2: Ex-Ahmedabad | C2: Ex-Bangalore | D2: Ex-Chennai | E2: Ex-Delhi/NCR | F2: Ex-Durgapur | G2: Ex-Goa | H2: Ex-Hyderabad | I2: Ex-Jaipur | J2: Ex-Jalna | K2: Ex-Mandi Gobindgarh | L2: Ex-Mumbai | M2: Ex-Muzaffarnagar | N2: Ex-Patna | O2: Ex-Raigarh | P2: Ex-Raipur | Q2: Ex-Rourkela
A3: 45793 | E3: =_xlfn.XLOOKUP(A3,'steel Mint data'!A:A,'steel Mint data'!D:D,"",0) -> 47000 | I3: =_xlfn.XLOOKUP(A3,'steel Mint data'!A:A,'steel Mint data'!I:I,"",0) -> 45700 | K3: =_xlfn.XLOOKUP(A3,'steel Mint data'!A:A,'steel Mint data'!L:L,"",0) -> 47500 | P3: =_xlfn.XLOOKUP(A3,'steel Mint data'!A:A,'steel Mint data'!Q:Q,"",0) -> 43500 | Q3: =_xlfn.XLOOKUP(A3,'steel Mint data'!A:A,'steel Mint data'!R:R,"",0) -> 44000
A4: =A3+1 -> 45794 | E4: =_xlfn.XLOOKUP(A4,'steel Mint data'!A:A,'steel Mint data'!D:D,"",0) -> 46900 | I4: =_xlfn.XLOOKUP(A4,'steel Mint data'!A:A,'steel Mint data'!I:I,"",0) -> 45700 | K4: =_xlfn.XLOOKUP(A4,'steel Mint data'!A:A,'steel Mint data'!L:L,"",0) -> 47500 | P4: =_xlfn.XLOOKUP(A4,'steel Mint data'!A:A,'steel Mint data'!Q:Q,"",0) -> 43600 | Q4: =_xlfn.XLOOKUP(A4,'steel Mint data'!A:A,'steel Mint data'!R:R,"",0) -> 43800
A5: =A4+1 -> 45795 | E5: =_xlfn.XLOOKUP(A5,'steel Mint data'!A:A,'steel Mint data'!D:D,"",0) -> H | I5: =_xlfn.XLOOKUP(A5,'steel Mint data'!A:A,'steel Mint data'!I:I,"",0) -> H | K5: =_xlfn.XLOOKUP(A5,'steel Mint data'!A:A,'steel Mint data'!L:L,"",0) -> H | P5: =_xlfn.XLOOKUP(A5,'steel Mint data'!A:A,'steel Mint data'!Q:Q,"",0) -> H | Q5: =_xlfn.XLOOKUP(A5,'steel Mint data'!A:A,'steel Mint data'!R:R,"",0) -> H
A6: =A5+1 -> 45796 | E6: =_xlfn.XLOOKUP(A6,'steel Mint data'!A:A,'steel Mint data'!D:D,"",0) -> 46800 | I6: =_xlfn.XLOOKUP(A6,'steel Mint data'!A:A,'steel Mint data'!I:I,"",0) -> 45700 | K6: =_xlfn.XLOOKUP(A6,'steel Mint data'!A:A,'steel Mint data'!L:L,"",0) -> 47500 | P6: =_xlfn.XLOOKUP(A6,'steel Mint data'!A:A,'steel Mint data'!Q:Q,"",0) -> 43500 | Q6: =_xlfn.XLOOKUP(A6,'steel Mint data'!A:A,'steel Mint data'!R:R,"",0) -> 43700
A7: =A6+1 -> 45797 | E7: =_xlfn.XLOOKUP(A7,'steel Mint data'!A:A,'steel Mint data'!D:D,"",0) -> 46700 | I7: =_xlfn.XLOOKUP(A7,'steel Mint data'!A:A,'steel Mint data'!I:I,"",0) -> 45800 | K7: =_xlfn.XLOOKUP(A7,'steel Mint data'!A:A,'steel Mint data'!L:L,"",0) -> 47600 | P7: =_xlfn.XLOOKUP(A7,'steel Mint data'!A:A,'steel Mint data'!Q:Q,"",0) -> 43500 | Q7: =_xlfn.XLOOKUP(A7,'steel Mint data'!A:A,'steel Mint data'!R:R,"",0) -> 43900
A8: =A7+1 -> 45798 | E8: =_xlfn.XLOOKUP(A8,'steel Mint data'!A:A,'steel Mint data'!D:D,"",0) -> 46700 | I8: =_xlfn.XLOOKUP(A8,'steel Mint data'!A:A,'steel Mint data'!I:I,"",0) -> 45900 | K8: =_xlfn.XLOOKUP(A8,'steel Mint data'!A:A,'steel Mint data'!L:L,"",0) -> 47600 | P8: =_xlfn.XLOOKUP(A8,'steel Mint data'!A:A,'steel Mint data'!Q:Q,"",0) -> 43500 | Q8: =_xlfn.XLOOKUP(A8,'steel Mint data'!A:A,'steel Mint data'!R:R,"",0) -> 44100
A9: =A8+1 -> 45799 | E9: =_xlfn.XLOOKUP(A9,'steel Mint data'!A:A,'steel Mint data'!D:D,"",0) -> 46700 | I9: =_xlfn.XLOOKUP(A9,'steel Mint data'!A:A,'steel Mint data'!I:I,"",0) -> 45800 | K9: =_xlfn.XLOOKUP(A9,'steel Mint data'!A:A,'steel Mint data'!L:L,"",0) -> 47600 | P9: =_xlfn.XLOOKUP(A9,'steel Mint data'!A:A,'steel Mint data'!Q:Q,"",0) -> 43400 | Q9: =_xlfn.XLOOKUP(A9,'steel Mint data'!A:A,'steel Mint data'!R:R,"",0) -> 43900
A10: =A9+1 -> 45800 | E10: =_xlfn.XLOOKUP(A10,'steel Mint data'!A:A,'steel Mint data'!D:D,"",0) -> 46400 | I10: =_xlfn.XLOOKUP(A10,'steel Mint data'!A:A,'steel Mint data'!I:I,"",0) -> 45600 | K10: =_xlfn.XLOOKUP(A10,'steel Mint data'!A:A,'steel Mint data'!L:L,"",0) -> 47500 | P10: =_xlfn.XLOOKUP(A10,'steel Mint data'!A:A,'steel Mint data'!Q:Q,"",0) -> 43300 | Q10: =_xlfn.XLOOKUP(A10,'steel Mint data'!A:A,'steel Mint data'!R:R,"",0) -> 43300
A11: =A10+1 -> 45801 | E11: =_xlfn.XLOOKUP(A11,'steel Mint data'!A:A,'steel Mint data'!D:D,"",0) -> 46600 | I11: =_xlfn.XLOOKUP(A11,'steel Mint data'!A:A,'steel Mint data'!I:I,"",0) -> 45600 | K11: =_xlfn.XLOOKUP(A11,'steel Mint data'!A:A,'steel Mint data'!L:L,"",0) -> 47500 | P11: =_xlfn.XLOOKUP(A11,'steel Mint data'!A:A,'steel Mint data'!Q:Q,"",0) -> 43200 | Q11: =_xlfn.XLOOKUP(A11,'steel Mint data'!A:A,'steel Mint data'!R:R,"",0) -> 43100
A12: =A11+1 -> 45802 | E12: =_xlfn.XLOOKUP(A12,'steel Mint data'!A:A,'steel Mint data'!D:D,"",0) -> H | I12: =_xlfn.XLOOKUP(A12,'steel Mint data'!A:A,'steel Mint data'!I:I,"",0) -> H | K12: =_xlfn.XLOOKUP(A12,'steel Mint data'!A:A,'steel Mint data'!L:L,"",0) -> H | P12: =_xlfn.XLOOKUP(A12,'steel Mint data'!A:A,'steel Mint data'!Q:Q,"",0) -> H | Q12: =_xlfn.XLOOKUP(A12,'steel Mint data'!A:A,'steel Mint data'!R:R,"",0) -> H
A13: =A12+1 -> 45803 | E13: =_xlfn.XLOOKUP(A13,'steel Mint data'!A:A,'steel Mint data'!D:D,"",0) -> 46200 | I13: =_xlfn.XLOOKUP(A13,'steel Mint data'!A:A,'steel Mint data'!I:I,"",0) -> 45400 | K13: =_xlfn.XLOOKUP(A13,'steel Mint data'!A:A,'steel Mint data'!L:L,"",0) -> 47200 | P13: =_xlfn.XLOOKUP(A13,'steel Mint data'!A:A,'steel Mint data'!Q:Q,"",0) -> 43100 | Q13: =_xlfn.XLOOKUP(A13,'steel Mint data'!A:A,'steel Mint data'!R:R,"",0) -> 43100
A14: =A13+1 -> 45804 | E14: =_xlfn.XLOOKUP(A14,'steel Mint data'!A:A,'steel Mint data'!D:D,"",0) -> 46000 | I14: =_xlfn.XLOOKUP(A14,'steel Mint data'!A:A,'steel Mint data'!I:I,"",0) -> 45200 | K14: =_xlfn.XLOOKUP(A14,'steel Mint data'!A:A,'steel Mint data'!L:L,"",0) -> 47100 | P14: =_xlfn.XLOOKUP(A14,'steel Mint data'!A:A,'steel Mint data'!Q:Q,"",0) -> 42900 | Q14: =_xlfn.XLOOKUP(A14,'steel Mint data'!A:A,'steel Mint data'!R:R,"",0) -> 43000
A15: =A14+1 -> 45805 | E15: =_xlfn.XLOOKUP(A15,'steel Mint data'!A:A,'steel Mint data'!D:D,"",0) -> 45800 | I15: =_xlfn.XLOOKUP(A15,'steel Mint data'!A:A,'steel Mint data'!I:I,"",0) -> 45100 | K15: =_xlfn.XLOOKUP(A15,'steel Mint data'!A:A,'steel Mint data'!L:L,"",0) -> 47100 | P15: =_xlfn.XLOOKUP(A15,'steel Mint data'!A:A,'steel Mint data'!Q:Q,"",0) -> 42800 | Q15: =_xlfn.XLOOKUP(A15,'steel Mint data'!A:A,'steel Mint data'!R:R,"",0) -> 43000
... A18: =A17+1 -> 45808 | E18: =_xlfn.XLOOKUP(A18,'steel Mint data'!A:A,'steel Mint data'!D:D,"",0) -> 45800 | I18: =_xlfn.XLOOKUP(A18,'steel Mint data'!A:A,'steel Mint data'!I:I,"",0) -> 44900 | K18: =_xlfn.XLOOKUP(A18,'steel Mint data'!A:A,'steel Mint data'!L:L,"",0) -> 46800 | P18: =_xlfn.XLOOKUP(A18,'steel Mint data'!A:A,'steel Mint data'!Q:Q,"",0) -> 42400 | Q18: =_xlfn.XLOOKUP(A18,'steel Mint data'!A:A,'steel Mint data'!R:R,"",0) -> 42500
E19: =SUM(E3:E18) -> 649200 | I19: =SUM(I3:I18) -> 636200 | K19: =SUM(K3:K18) -> 662300 | P19: =SUM(P3:P18) -> 603600 | Q19: =SUM(Q3:Q18) -> 607400
B20: Amba Shakti (NCR) | C20: API (Raipur) | D20: Aditya Industries (Mandi) | E20: Shree Ganesh (Rourkela) | F20: SKA Raipur | G20: Amba Gwalior | H20: Rajasthan
A21: Avg Price - Divided by no of days steel mint price is available | B21: =E19/O21 -> 46371.429 | C21: =P19/O21 -> 43114.286 | D21: =K19/O21 -> 47307.143 | E21: =Q19/O21 -> 43385.714 | F21: =C21 -> 43114.286 | G21: =B21-800 -> 45571.429 | H21: =I19/O21 -> 45442.857 | J21: =I19/O21 -> 45442.857 | L21: =G24+1000+2700+4000 -> 54671.429 | O21: =COUNT(P3:P18) -> 14
A22: BIS | B22: 1200 | C22: 2150 | D22: 400 | E22: 2200 | F22: 1800 | G22: 1200 | H22: 800
A23: Loading Charges | B23: 200 | C23: 265 | D23: 250 | E23: 275 | F23: 275 | G23: 200 | H23: 270 | K23: =D24+800 -> 48757.143 | L23: =G24+1000 -> 47971.429
A24: Actual PO Price (base dia): A | B24: =SUM(B21:B23) -> 47771.429 | C24: =SUM(C21:C23) -> 45529.286 | D24: =SUM(D21:D23) -> 47957.143 | E24: =SUM(E21:E23) -> 45860.714 | F24: =SUM(F21:F23) -> 45189.286 | G24: =SUM(G21:G23) -> 46971.429 | H24: =SUM(H21:H23) -> 46512.857 | K24: =K23+1500 -> 50257.143
A25: Notional PO: B | B25: 48700 | C25: 46515 | D25: 48450 | F25: 46175 | G25: =B25-800 -> 47900 | H25: 47116 | I25: =H25-H23-H22 -> 46046 | K25: =53500-K24 -> 3242.8571 | M25: =48650-C25 -> 2135
A26: Change (A-B) | B26: =B24-B25 -> -928.57143 | C26: =C24-C25 -> -985.71429 | D26: =D24-D25 -> -492.85714 | E26: =E24-E25 -> 45860.714 | F26: =F24-F25 -> -985.71429 | G26: =G24-G25 -> -928.57143 | H26: =H24-H25 -> -603.14286 | O26: =52250-2600-C24 -> 4120.7143
K27: =53000-1300-1000 -> 50700 | M27: =52700-1500 -> 51200
A28: Current PL | B28: 55300 | C28: 52550 | D28: 55800 | E28: 53650 | F28: 52550 | G28: =B28-800 -> 54500 | H28: =B28-500 -> 54800 | K28: =K27-G24 -> 3728.5714 | M28: =M27-D25-800 -> 1950 | O28: =M27-D25-800 -> 1950
A29: Current ex plant NR | B29: =B28-2300 -> 53000 | C29: =C28-2300 -> 50250 | D29: =D28-2300 -> 53500 | E29: =E28-2300 -> 51350 | F29: =F28-2300 -> 50250 | G29: =G28-2300 -> 52200 | O29: =52700-D24-800-1500 -> 2442.8571 | P29: =O29-O28 -> 492.85714
A30: Current GM: C | B30: =B29-B24 -> 5228.5714 | C30: =C29-C24 -> 4720.7143 | D30: =D29-D24 -> 5542.8571 | E30: =E29-E24 -> 5489.2857 | F30: =F29-F24 -> 5060.7143 | G30: =G29-G24 -> 5228.5714
K31: =52250-2600-C24 -> 4120.7143
I35: =51700-1000-G24 -> 3728.5714
I36: =51700-1000-G25 -> 2800 | O36: =48900-C24 -> 3370.7143

Sheet Jun'25 H1
B1: Fe 500
A2: Region / Date | B2: Ex-Ahmedabad | C2: Ex-Bangalore | D2: Ex-Chennai | E2: Ex-Delhi/NCR | F2: Ex-Durgapur | G2: Ex-Goa | H2: Ex-Hyderabad | I2: Ex-Jaipur | J2: Ex-Jalna | K2: Ex-Mandi Gobindgarh | L2: Ex-Mumbai | M2: Ex-Muzaffarnagar | N2: Ex-Patna | O2: Ex-Raigarh | P2: Ex-Raipur | Q2: Ex-Rourkela
A3: 45809 | E3: =_xlfn.XLOOKUP(A3,'steel Mint data'!A:A,'steel Mint data'!D:D,"",0) -> H | I3: =_xlfn.XLOOKUP(A3,'steel Mint data'!A:A,'steel Mint data'!I:I,"",0) -> H | K3: =_xlfn.XLOOKUP(A3,'steel Mint data'!A:A,'steel Mint data'!L:L,"",0) -> H | P3: =_xlfn.XLOOKUP(A3,'steel Mint data'!A:A,'steel Mint data'!Q:Q,"",0) -> H | Q3: =_xlfn.XLOOKUP(A3,'steel Mint data'!A:A,'steel Mint data'!R:R,"",0) -> H
A4: =A3+1 -> 45810 | E4: =_xlfn.XLOOKUP(A4,'steel Mint data'!A:A,'steel Mint data'!D:D,"",0) -> 46000 | I4: =_xlfn.XLOOKUP(A4,'steel Mint data'!A:A,'steel Mint data'!I:I,"",0) -> 45300 | K4: =_xlfn.XLOOKUP(A4,'steel Mint data'!A:A,'steel Mint data'!L:L,"",0) -> 46800 | P4: =_xlfn.XLOOKUP(A4,'steel Mint data'!A:A,'steel Mint data'!Q:Q,"",0) -> 42500 | Q4: =_xlfn.XLOOKUP(A4,'steel Mint data'!A:A,'steel Mint data'!R:R,"",0) -> 42400
A5: =A4+1 -> 45811 | E5: =_xlfn.XLOOKUP(A5,'steel Mint data'!A:A,'steel Mint data'!D:D,"",0) -> 46000 | I5: =_xlfn.XLOOKUP(A5,'steel Mint data'!A:A,'steel Mint data'!I:I,"",0) -> 45100 | K5: =_xlfn.XLOOKUP(A5,'steel Mint data'!A:A,'steel Mint data'!L:L,"",0) -> 47100 | P5: =_xlfn.XLOOKUP(A5,'steel Mint data'!A:A,'steel Mint data'!Q:Q,"",0) -> 42200 | Q5: =_xlfn.XLOOKUP(A5,'steel Mint data'!A:A,'steel Mint data'!R:R,"",0) -> 42300
A6: =A5+1 -> 45812 | E6: =_xlfn.XLOOKUP(A6,'steel Mint data'!A:A,'steel Mint data'!D:D,"",0) -> 46100 | I6: =_xlfn.XLOOKUP(A6,'steel Mint data'!A:A,'steel Mint data'!I:I,"",0) -> 45100 | K6: =_xlfn.XLOOKUP(A6,'steel Mint data'!A:A,'steel Mint data'!L:L,"",0) -> 47100 | P6: =_xlfn.XLOOKUP(A6,'steel Mint data'!A:A,'steel Mint data'!Q:Q,"",0) -> 42000 | Q6: =_xlfn.XLOOKUP(A6,'steel Mint data'!A:A,'steel Mint data'!R:R,"",0) -> 42200
A7: =A6+1 -> 45813 | E7: =_xlfn.XLOOKUP(A7,'steel Mint data'!A:A,'steel Mint data'!D:D,"",0) -> 45800 | I7: =_xlfn.XLOOKUP(A7,'steel Mint data'!A:A,'steel Mint data'!I:I,"",0) -> 45000 | K7: =_xlfn.XLOOKUP(A7,'steel Mint data'!A:A,'steel Mint data'!L:L,"",0) -> 47200 | P7: =_xlfn.XLOOKUP(A7,'steel Mint data'!A:A,'steel Mint data'!Q:Q,"",0) -> 42000 | Q7: =_xlfn.XLOOKUP(A7,'steel Mint data'!A:A,'steel Mint data'!R:R,"",0) -> 42000
A8: =A7+1 -> 45814 | E8: =_xlfn.XLOOKUP(A8,'steel Mint data'!A:A,'steel Mint data'!D:D,"",0) -> 45800 | I8: =_xlfn.XLOOKUP(A8,'steel Mint data'!A:A,'steel Mint data'!I:I,"",0) -> 44800 | K8: =_xlfn.XLOOKUP(A8,'steel Mint data'!A:A,'steel Mint data'!L:L,"",0) -> 47100 | P8: =_xlfn.XLOOKUP(A8,'steel Mint data'!A:A,'steel Mint data'!Q:Q,"",0) -> 41900 | Q8: =_xlfn.XLOOKUP(A8,'steel Mint data'!A:A,'steel Mint data'!R:R,"",0) -> 41900
A9: =A8+1 -> 45815 | E9: =_xlfn.XLOOKUP(A9,'steel Mint data'!A:A,'steel Mint data'!D:D,"",0) -> 45700 | I9: =_xlfn.XLOOKUP(A9,'steel Mint data'!A:A,'steel Mint data'!I:I,"",0) -> 44600 | K9: =_xlfn.XLOOKUP(A9,'steel Mint data'!A:A,'steel Mint data'!L:L,"",0) -> 47000 | P9: =_xlfn.XLOOKUP(A9,'steel Mint data'!A:A,'steel Mint data'!Q:Q,"",0) -> 41700 | Q9: =_xlfn.XLOOKUP(A9,'steel Mint data'!A:A,'steel Mint data'!R:R,"",0) -> 41800
A10: =A9+1 -> 45816 | E10: =_xlfn.XLOOKUP(A10,'steel Mint data'!A:A,'steel Mint data'!D:D,"",0) -> H | I10: =_xlfn.XLOOKUP(A10,'steel Mint data'!A:A,'steel Mint data'!I:I,"",0) -> H | K10: =_xlfn.XLOOKUP(A10,'steel Mint data'!A:A,'steel Mint data'!L:L,"",0) -> H | P10: =_xlfn.XLOOKUP(A10,'steel Mint data'!A:A,'steel Mint data'!Q:Q,"",0) -> H | Q10: =_xlfn.XLOOKUP(A10,'steel Mint data'!A:A,'steel Mint data'!R:R,"",0) -> H
A11: =A10+1 -> 45817 | E11: =_xlfn.XLOOKUP(A11,'steel Mint data'!A:A,'steel Mint data'!D:D,"",0) -> 45500 | I11: =_xlfn.XLOOKUP(A11,'steel Mint data'!A:A,'steel Mint data'!I:I,"",0) -> 44600 | K11: =_xlfn.XLOOKUP(A11,'steel Mint data'!A:A,'steel Mint data'!L:L,"",0) -> 46900 | P11: =_xlfn.XLOOKUP(A11,'steel Mint data'!A:A,'steel Mint data'!Q:Q,"",0) -> 41500 | Q11: =_xlfn.XLOOKUP(A11,'steel Mint data'!A:A,'steel Mint data'!R:R,"",0) -> 41600
A12: =A11+1 -> 45818 | E12: =_xlfn.XLOOKUP(A12,'steel Mint data'!A:A,'steel Mint data'!D:D,"",0) -> 45600 | I12: =_xlfn.XLOOKUP(A12,'steel Mint data'!A:A,'steel Mint data'!I:I,"",0) -> 44600 | K12: =_xlfn.XLOOKUP(A12,'steel Mint data'!A:A,'steel Mint data'!L:L,"",0) -> 46900 | P12: =_xlfn.XLOOKUP(A12,'steel Mint data'!A:A,'steel Mint data'!Q:Q,"",0) -> 41400 | Q12: =_xlfn.XLOOKUP(A12,'steel Mint data'!A:A,'steel Mint data'!R:R,"",0) -> 41500
A13: =A12+1 -> 45819 | E13: =_xlfn.XLOOKUP(A13,'steel Mint data'!A:A,'steel Mint data'!D:D,"",0) -> 45600 | I13: =_xlfn.XLOOKUP(A13,'steel Mint data'!A:A,'steel Mint data'!I:I,"",0) -> 44400 | K13: =_xlfn.XLOOKUP(A13,'steel Mint data'!A:A,'steel Mint data'!L:L,"",0) -> 46900 | P13: =_xlfn.XLOOKUP(A13,'steel Mint data'!A:A,'steel Mint data'!Q:Q,"",0) -> 41400 | Q13: =_xlfn.XLOOKUP(A13,'steel Mint data'!A:A,'steel Mint data'!R:R,"",0) -> 41700
A14: =A13+1 -> 45820 | E14: =_xlfn.XLOOKUP(A14,'steel Mint data'!A:A,'steel Mint data'!D:D,"",0) -> 45500 | I14: =_xlfn.XLOOKUP(A14,'steel Mint data'!A:A,'steel Mint data'!I:I,"",0) -> 44300 | K14: =_xlfn.XLOOKUP(A14,'steel Mint data'!A:A,'steel Mint data'!L:L,"",0) -> 46800 | P14: =_xlfn.XLOOKUP(A14,'steel Mint data'!A:A,'steel Mint data'!Q:Q,"",0) -> 41400 | Q14: =_xlfn.XLOOKUP(A14,'steel Mint data'!A:A,'steel Mint data'!R:R,"",0) -> 41700
A15: =A14+1 -> 45821 | E15: =_xlfn.XLOOKUP(A15,'steel Mint data'!A:A,'steel Mint data'!D:D,"",0) -> 45400 | I15: =_xlfn.XLOOKUP(A15,'steel Mint data'!A:A,'steel Mint data'!I:I,"",0) -> 44300 | K15: =_xlfn.XLOOKUP(A15,'steel Mint data'!A:A,'steel Mint data'!L:L,"",0) -> 46600 | P15: =_xlfn.XLOOKUP(A15,'steel Mint data'!A:A,'steel Mint data'!Q:Q,"",0) -> 41300 | Q15: =_xlfn.XLOOKUP(A15,'steel Mint data'!A:A,'steel Mint data'!R:R,"",0) -> 41600
... A18: =A17+1 -> 45824 | E18: =_xlfn.XLOOKUP(A18,'steel Mint data'!A:A,'steel Mint data'!D:D,"",0) -> 45300 | I18: =_xlfn.XLOOKUP(A18,'steel Mint data'!A:A,'steel Mint data'!I:I,"",0) -> 44200 | K18: =_xlfn.XLOOKUP(A18,'steel Mint data'!A:A,'steel Mint data'!L:L,"",0) -> 46600 | P18: =_xlfn.XLOOKUP(A18,'steel Mint data'!A:A,'steel Mint data'!Q:Q,"",0) -> 41200 | Q18: =_xlfn.XLOOKUP(A18,'steel Mint data'!A:A,'steel Mint data'!R:R,"",0) -> 41500
E19: =SUM(E3:E18) -> 593600 | I19: =SUM(I3:I18) -> 580500 | K19: =SUM(K3:K18) -> 609600 | P19: =SUM(P3:P18) -> 541700 | Q19: =SUM(Q3:Q18) -> 543700
B20: Amba Shakti (NCR) | C20: API (Raipur) | D20: Aditya Industries (Mandi) | E20: Shree Ganesh (Rourkela) | F20: SKA Raipur | G20: Amba Gwalior | H20: Rajasthan
A21: Avg Price - Divided by no of days steel mint price is available | B21: =E19/O21 -> 45661.538 | C21: =P19/O21 -> 41669.231 | D21: =K19/O21 -> 46892.308 | E21: =Q19/O21 -> 41823.077 | F21: =C21 -> 41669.231 | G21: =B21-800 -> 44861.538 | H21: =I19/O21 -> 44653.846 | O21: =COUNT(P1:P18) -> 13
A22: BIS | B22: 1200 | C22: 2150 | D22: 400 | E22: 2200 | F22: 1800 | G22: 1200 | H22: 800 | Q22: =50300-800-47650 -> 1850
A23: Loading Charges | B23: 200 | C23: 265 | D23: 250 | E23: 275 | F23: 275 | G23: 200 | H23: 270 | J23: =C24+1250+3000 -> 48334.231 | K23: =50500-G24-1000-1000 -> 2238.4615
A24: Actual PO Price (base dia): A | B24: =SUM(B21:B23) -> 47061.538 | C24: =SUM(C21:C23) -> 44084.231 | D24: =SUM(D21:D23) -> 47542.308 | E24: =SUM(E21:E23) -> 44298.077 | F24: =SUM(F21:F23) -> 43744.231 | G24: =SUM(G21:G23) -> 46261.538 | H24: =SUM(H21:H23) -> 45723.846 | J24: =D24-B24 -> 480.76923 | K24: =J24-150 -> 330.76923 | M24: =50500-G24-1000-1000 -> 2238.4615 | O24: =52700-3700 -> 49000 | P24: =O24-1000-1000-G24 -> 738.46154
A25: Notional PO: B | B25: 47200 | C25: 44915 | D25: 47550 | F25: 44575 | G25: 46400 | H25: 45970 | J25: =55500-51800 -> 3700
A26: Change (A-B) | B26: =B24-B25 -> -138.46154 | C26: =C24-C25 -> -830.76923 | D26: =D24-D25 -> -7.6923077 | E26: =E24-E25 -> 44298.077 | F26: =F24-F25 -> -830.76923 | G26: =G24-G25 -> -138.46154 | H26: =H24-H25 -> -246.15385 | N26: =52700-4000 -> 48700
L27: =50600-B24 -> 3538.4615 | S27: =52100*45 -> 2344500
A28: Current PL | B28: 51300 | C28: 48550 | D28: 51800 | E28: 49650 | F28: 48550 | G28: 50500 | H28: 50800 | K28: =49600-2900-400-C24 -> 2215.7692 | L28: =50600-B25 -> 3400 | O28: =52700-4000 -> 48700 | P28: =50300-D24 -> 2757.6923
A29: Current ex plant NR | B29: =B28-500-(200+300+300)-250-400 -> 49350 | C29: =C28-500-(200+300+300)-250-400 -> 46600 | D29: =D28-500-(200+300+300)-250-400 -> 49850 | E29: =E28-500-(200+300+300)-250-400 -> 47700 | F29: =F28-500-(200+300+300)-250-400 -> 46600 | G29: =G28-500-(200+300+300)-250-400 -> 48550 | H29: =H28-500-(200+300+300)-250-400 -> 48850 | K29: =49600-2900-400-C25 -> 1385 | P29: =50300-D25 -> 2750
A30: Current GM: C | B30: =B29-B24 -> 2288.4615 | C30: =C29-C24 -> 2515.7692 | D30: =D29-D24 -> 2307.6923 | E30: =E29-E24 -> 3401.9231 | F30: =F29-F24 -> 2855.7692 | G30: =G29-G24 -> 2288.4615 | H30: =H29-H24 -> 3126.1538 | K30: =K28-K29 -> 830.76923 | M30: =50500-2200-300-1250-C24 -> 2665.7692
M31: =50500-2200-300-1250-C25 -> 1835 | N31: =M30-M31 -> 830.76923 | R31: =50600-550-D24 -> 2507.6923
B32: =B28-B24-2000 -> 2238.4615 | C32: =C28-C24-2000 -> 2465.7692 | D32: =D28-D24-2000 -> 2257.6923 | E32: =E28-E24-2000 -> 3351.9231 | F32: =F28-F24-2000 -> 2805.7692 | G32: =G28-G24-2000 -> 2238.4615 | H32: =H28-H24-2000 -> 3076.1538 | K32: =52100-2600-1250-C24 -> 4165.7692 | R32: =50600-550-D25 -> 2500
C33: =C24+3500+1250 -> 48834.231 | K33: =52100-2600-1250-C25 -> 3335 | L33: =51200-1200-B24 -> 2938.4615
C34: =50000-C33 -> 1165.7692 | J34: =50600-1200-B24 -> 2338.4615 | K34: =K32-K33 -> 830.76923 | L34: =51200-1000-D24 -> 2657.6923 | P34: =52100-2600-1250-C24 -> 4165.7692
A35: Plant | B35: Jun H1 notional | C35: =50000-C24-1250-3400 -> 1265.7692 | E35: =50000-D24-1000 -> 1457.6923 | J35: =50600-550-D24 -> 2507.6923 | P35: =52100-2600-1250-C25 -> 3335
A36: Sikandarabad | B36: 47200
A37: API, Raipur | B37: 44915
A38: SKA, Raipur | B38: 44575
A39: Kala Amb | B39: 47550
A40: Gwalior | B40: =B36-800 -> 46400 | D40: =53000-1800-B40-1000 -> 3800
A41: Jaipur | B41: 45970

Sheet Jun'25 H2
B1: Fe 500
A2: Region / Date | B2: Ex-Ahmedabad | C2: Ex-Bangalore | D2: Ex-Chennai | E2: Ex-Delhi/NCR | F2: Ex-Durgapur | G2: Ex-Goa | H2: Ex-Hyderabad | I2: Ex-Jaipur | J2: Ex-Jalna | K2: Ex-Mandi Gobindgarh | L2: Ex-Mumbai | M2: Ex-Muzaffarnagar | N2: Ex-Patna | O2: Ex-Raigarh | P2: Ex-Raipur | Q2: Ex-Rourkela
A3: 45824 | E3: =_xlfn.XLOOKUP(A3,'steel Mint data'!A:A,'steel Mint data'!D:D,"",0) -> 45300 | I3: =_xlfn.XLOOKUP(A3,'steel Mint data'!A:A,'steel Mint data'!I:I,"",0) -> 44200 | K3: =_xlfn.XLOOKUP(A3,'steel Mint data'!A:A,'steel Mint data'!L:L,"",0) -> 46600 | P3: =_xlfn.XLOOKUP(A3,'steel Mint data'!A:A,'steel Mint data'!Q:Q,"",0) -> 41200 | Q3: =_xlfn.XLOOKUP(A3,'steel Mint data'!A:A,'steel Mint data'!R:R,"",0) -> 41500
A4: =A3+1 -> 45825 | E4: =_xlfn.XLOOKUP(A4,'steel Mint data'!A:A,'steel Mint data'!D:D,"",0) -> 45400 | I4: =_xlfn.XLOOKUP(A4,'steel Mint data'!A:A,'steel Mint data'!I:I,"",0) -> 44200 | K4: =_xlfn.XLOOKUP(A4,'steel Mint data'!A:A,'steel Mint data'!L:L,"",0) -> 46600 | P4: =_xlfn.XLOOKUP(A4,'steel Mint data'!A:A,'steel Mint data'!Q:Q,"",0) -> 41200 | Q4: =_xlfn.XLOOKUP(A4,'steel Mint data'!A:A,'steel Mint data'!R:R,"",0) -> 41500
A5: =A4+1 -> 45826 | E5: =_xlfn.XLOOKUP(A5,'steel Mint data'!A:A,'steel Mint data'!D:D,"",0) -> 45400 | I5: =_xlfn.XLOOKUP(A5,'steel Mint data'!A:A,'steel Mint data'!I:I,"",0) -> 44200 | K5: =_xlfn.XLOOKUP(A5,'steel Mint data'!A:A,'steel Mint data'!L:L,"",0) -> 46600 | P5: =_xlfn.XLOOKUP(A5,'steel Mint data'!A:A,'steel Mint data'!Q:Q,"",0) -> 41000 | Q5: =_xlfn.XLOOKUP(A5,'steel Mint data'!A:A,'steel Mint data'!R:R,"",0) -> 41300
A6: =A5+1 -> 45827 | E6: =_xlfn.XLOOKUP(A6,'steel Mint data'!A:A,'steel Mint data'!D:D,"",0) -> 45300 | I6: =_xlfn.XLOOKUP(A6,'steel Mint data'!A:A,'steel Mint data'!I:I,"",0) -> 44000 | K6: =_xlfn.XLOOKUP(A6,'steel Mint data'!A:A,'steel Mint data'!L:L,"",0) -> 46500 | P6: =_xlfn.XLOOKUP(A6,'steel Mint data'!A:A,'steel Mint data'!Q:Q,"",0) -> 41000 | Q6: =_xlfn.XLOOKUP(A6,'steel Mint data'!A:A,'steel Mint data'!R:R,"",0) -> 41300
A7: =A6+1 -> 45828 | E7: =_xlfn.XLOOKUP(A7,'steel Mint data'!A:A,'steel Mint data'!D:D,"",0) -> 45000 | I7: =_xlfn.XLOOKUP(A7,'steel Mint data'!A:A,'steel Mint data'!I:I,"",0) -> 43800 | K7: =_xlfn.XLOOKUP(A7,'steel Mint data'!A:A,'steel Mint data'!L:L,"",0) -> 46400 | P7: =_xlfn.XLOOKUP(A7,'steel Mint data'!A:A,'steel Mint data'!Q:Q,"",0) -> 41000 | Q7: =_xlfn.XLOOKUP(A7,'steel Mint data'!A:A,'steel Mint data'!R:R,"",0) -> 41100
A8: =A7+1 -> 45829 | E8: =_xlfn.XLOOKUP(A8,'steel Mint data'!A:A,'steel Mint data'!D:D,"",0) -> 44800 | I8: =_xlfn.XLOOKUP(A8,'steel Mint data'!A:A,'steel Mint data'!I:I,"",0) -> 43800 | K8: =_xlfn.XLOOKUP(A8,'steel Mint data'!A:A,'steel Mint data'!L:L,"",0) -> 46300 | P8: =_xlfn.XLOOKUP(A8,'steel Mint data'!A:A,'steel Mint data'!Q:Q,"",0) -> 41000 | Q8: =_xlfn.XLOOKUP(A8,'steel Mint data'!A:A,'steel Mint data'!R:R,"",0) -> 41100
A9: =A8+1 -> 45830 | E9: =_xlfn.XLOOKUP(A9,'steel Mint data'!A:A,'steel Mint data'!D:D,"",0) -> H | I9: =_xlfn.XLOOKUP(A9,'steel Mint data'!A:A,'steel Mint data'!I:I,"",0) -> H | K9: =_xlfn.XLOOKUP(A9,'steel Mint data'!A:A,'steel Mint data'!L:L,"",0) -> H | P9: =_xlfn.XLOOKUP(A9,'steel Mint data'!A:A,'steel Mint data'!Q:Q,"",0) -> H | Q9: =_xlfn.XLOOKUP(A9,'steel Mint data'!A:A,'steel Mint data'!R:R,"",0) -> H
A10: =A9+1 -> 45831 | E10: =_xlfn.XLOOKUP(A10,'steel Mint data'!A:A,'steel Mint data'!D:D,"",0) -> 44500 | I10: =_xlfn.XLOOKUP(A10,'steel Mint data'!A:A,'steel Mint data'!I:I,"",0) -> 43600 | K10: =_xlfn.XLOOKUP(A10,'steel Mint data'!A:A,'steel Mint data'!L:L,"",0) -> 45700 | P10: =_xlfn.XLOOKUP(A10,'steel Mint data'!A:A,'steel Mint data'!Q:Q,"",0) -> 40800 | Q10: =_xlfn.XLOOKUP(A10,'steel Mint data'!A:A,'steel Mint data'!R:R,"",0) -> 41000
A11: =A10+1 -> 45832 | E11: =_xlfn.XLOOKUP(A11,'steel Mint data'!A:A,'steel Mint data'!D:D,"",0) -> 44400 | I11: =_xlfn.XLOOKUP(A11,'steel Mint data'!A:A,'steel Mint data'!I:I,"",0) -> 43300 | K11: =_xlfn.XLOOKUP(A11,'steel Mint data'!A:A,'steel Mint data'!L:L,"",0) -> 45700 | P11: =_xlfn.XLOOKUP(A11,'steel Mint data'!A:A,'steel Mint data'!Q:Q,"",0) -> 40400 | Q11: =_xlfn.XLOOKUP(A11,'steel Mint data'!A:A,'steel Mint data'!R:R,"",0) -> 41000
A12: =A11+1 -> 45833 | E12: =_xlfn.XLOOKUP(A12,'steel Mint data'!A:A,'steel Mint data'!D:D,"",0) -> 44400 | I12: =_xlfn.XLOOKUP(A12,'steel Mint data'!A:A,'steel Mint data'!I:I,"",0) -> 43500 | K12: =_xlfn.XLOOKUP(A12,'steel Mint data'!A:A,'steel Mint data'!L:L,"",0) -> 45800 | P12: =_xlfn.XLOOKUP(A12,'steel Mint data'!A:A,'steel Mint data'!Q:Q,"",0) -> 40500 | Q12: =_xlfn.XLOOKUP(A12,'steel Mint data'!A:A,'steel Mint data'!R:R,"",0) -> 41000
A13: =A12+1 -> 45834 | E13: =_xlfn.XLOOKUP(A13,'steel Mint data'!A:A,'steel Mint data'!D:D,"",0) -> 44500 | I13: =_xlfn.XLOOKUP(A13,'steel Mint data'!A:A,'steel Mint data'!I:I,"",0) -> 43600 | K13: =_xlfn.XLOOKUP(A13,'steel Mint data'!A:A,'steel Mint data'!L:L,"",0) -> 45900 | P13: =_xlfn.XLOOKUP(A13,'steel Mint data'!A:A,'steel Mint data'!Q:Q,"",0) -> 40500 | Q13: =_xlfn.XLOOKUP(A13,'steel Mint data'!A:A,'steel Mint data'!R:R,"",0) -> 41200
A14: =A13+1 -> 45835 | E14: =_xlfn.XLOOKUP(A14,'steel Mint data'!A:A,'steel Mint data'!D:D,"",0) -> 44700 | I14: =_xlfn.XLOOKUP(A14,'steel Mint data'!A:A,'steel Mint data'!I:I,"",0) -> 43400 | K14: =_xlfn.XLOOKUP(A14,'steel Mint data'!A:A,'steel Mint data'!L:L,"",0) -> 45900 | P14: =_xlfn.XLOOKUP(A14,'steel Mint data'!A:A,'steel Mint data'!Q:Q,"",0) -> 40400 | Q14: =_xlfn.XLOOKUP(A14,'steel Mint data'!A:A,'steel Mint data'!R:R,"",0) -> 41200 | S14: =49000-3450-1250-C24 -> 1185 | T14: =49000-1000-3450-F24 -> 1775
A15: =A14+1 -> 45836 | E15: =_xlfn.XLOOKUP(A15,'steel Mint data'!A:A,'steel Mint data'!D:D,"",0) -> 44600 | I15: =_xlfn.XLOOKUP(A15,'steel Mint data'!A:A,'steel Mint data'!I:I,"",0) -> 43400 | K15: =_xlfn.XLOOKUP(A15,'steel Mint data'!A:A,'steel Mint data'!L:L,"",0) -> 45800 | P15: =_xlfn.XLOOKUP(A15,'steel Mint data'!A:A,'steel Mint data'!Q:Q,"",0) -> 40200 | Q15: =_xlfn.XLOOKUP(A15,'steel Mint data'!A:A,'steel Mint data'!R:R,"",0) -> 41000
A16: =A15+1 -> 45837 | E16: =_xlfn.XLOOKUP(A16,'steel Mint data'!A:A,'steel Mint data'!D:D,"",0) -> H | I16: =_xlfn.XLOOKUP(A16,'steel Mint data'!A:A,'steel Mint data'!I:I,"",0) -> H | K16: =_xlfn.XLOOKUP(A16,'steel Mint data'!A:A,'steel Mint data'!L:L,"",0) -> H | P16: =_xlfn.XLOOKUP(A16,'steel Mint data'!A:A,'steel Mint data'!Q:Q,"",0) -> H | Q16: =_xlfn.XLOOKUP(A16,'steel Mint data'!A:A,'steel Mint data'!R:R,"",0) -> H
A17: =A16+1 -> 45838 | E17: =_xlfn.XLOOKUP(A17,'steel Mint data'!A:A,'steel Mint data'!D:D,"",0) -> 44500 | I17: =_xlfn.XLOOKUP(A17,'steel Mint data'!A:A,'steel Mint data'!I:I,"",0) -> 43300 | K17: =_xlfn.XLOOKUP(A17,'steel Mint data'!A:A,'steel Mint data'!L:L,"",0) -> 45800 | P17: =_xlfn.XLOOKUP(A17,'steel Mint data'!A:A,'steel Mint data'!Q:Q,"",0) -> 39900 | Q17: =_xlfn.XLOOKUP(A17,'steel Mint data'!A:A,'steel Mint data'!R:R,"",0) -> 41000
E18: =_xlfn.XLOOKUP(A18,'steel Mint data'!A:A,'steel Mint data'!D:D,"",0) | I18: =_xlfn.XLOOKUP(A18,'steel Mint data'!A:A,'steel Mint data'!I:I,"",0) | K18: =_xlfn.XLOOKUP(A18,'steel Mint data'!A:A,'steel Mint data'!L:L,"",0) | Q18: =_xlfn.XLOOKUP(A18,'steel Mint data'!A:A,'steel Mint data'!R:R,"",0)
E19: =SUM(E3:E18) -> 582800 | I19: =SUM(I3:I18) -> 568300 | K19: =SUM(K3:K18) -> 599600 | P19: =SUM(P3:P18) -> 529100 | Q19: =SUM(Q3:Q18) -> 535200 | S19: =49000-3450-1250-C24 -> 1185 | T19: =49000-3450-1000-F24 -> 1775
B20: Amba Shakti (NCR) | C20: API (Raipur) | D20: Aditya Industries (Mandi) | E20: Shree Ganesh (Rourkela) | F20: SKA Raipur | G20: Amba Gwalior | H20: Rajasthan | S20: =49000-3450-1250-C25 -> 685 | T20: =49000-3450-1000-F25 -> 1275
A21: Avg Price - Divided by no of days steel mint price is available | B21: =E19/O21 -> 44830.769 | C21: =P19/O21 -> 40700 | D21: =K19/O21 -> 46123.077 | E21: =Q19/O21 -> 41169.231 | F21: =C21 -> 40700 | G21: =B21-800 -> 44030.769 | H21: =I19/O21 -> 43715.385 | K21: =C24+1250+3500+2000 -> 49865 | M21: =D24+1000+1200+2500 -> 51473.077 | O21: =COUNT(P3:P18) -> 13 | R21: =53500-1350-1000-G24 -> 5719.2308 | S21: =S19-S20 -> 500 | T21: =T19-T20 -> 500
A22: BIS | B22: 1200 | C22: 2150 | D22: 400 | E22: 2200 | F22: 1800 | G22: 1200 | H22: 800 | J22: =49500-1000-1000-G24 -> 2069.2308 | R22: =53500-1350-1000-G25 -> 5350
A23: Loading Charges | B23: 200 | C23: 265 | D23: 250 | E23: 275 | F23: 275 | G23: 200 | H23: 270 | J23: =C24+1250+3000 -> 47365 | K23: =50500-G24-1000-1000 -> 3069.2308 | R23: =50000-1000-1000-G24 -> 2569.2308
A24: Actual PO Price (base dia): A | B24: =SUM(B21:B23) -> 46230.769 | C24: =SUM(C21:C23) -> 43115 | D24: =SUM(D21:D23) -> 46773.077 | E24: =SUM(E21:E23) -> 43644.231 | F24: =SUM(F21:F23) -> 42775 | G24: =SUM(G21:G23) -> 45430.769 | H24: =SUM(H21:H23) -> 44785.385 | I24: =C24+3500 -> 46615 | J24: =D24-B24 -> 542.30769 | K24: =J24-150 -> 392.30769 | M24: =50500-G24-1000-1000 -> 3069.2308 | O24: =52700-3700 -> 49000 | P24: =O24-1000-1000-G24 -> 1569.2308 | R24: =50000-1000-1000-G25 -> 2200 | S24: =R23-R24 -> 369.23077
A25: Notional PO: B | B25: 46700 | C25: 43615 | D25: 47250 | F25: 43275 | G25: 45800 | H25: 45275 | I25: =B24+500 -> 46730.769 | J25: =55500-51800 -> 3700
A26: Change (A-B) | B26: =B24-B25 -> -469.23077 | C26: =C24-C25 -> -500 | D26: =D24-D25 -> -476.92308 | E26: =E24-E25 -> 43644.231 | F26: =F24-F25 -> -500 | G26: =G24-G25 -> -369.23077 | H26: =H24-H25 -> -489.61538 | N26: =52700-4000 -> 48700 | R26: =49700-1200-B24 -> 2269.2308
L27: =50600-B24 -> 4369.2308 | Q27: =49800-600-D24 -> 2426.9231 | R27: =49700-1200-B25 -> 1800 | S27: =R26-R27 -> 469.23077
A28: Current PL | B28: 51300 | C28: 48550 | D28: 51800 | E28: 49650 | F28: 48550 | G28: 50500 | H28: 50800 | K28: =49600-2900-400-C24 -> 3185 | L28: =50600-B25 -> 3900 | O28: =52700-4000 -> 48700 | Q28: =49800-600-D25 -> 1950
A29: Current ex plant NR | B29: =B28-500-(200+300+300)-250-400 -> 49350 | C29: =C28-500-(200+300+300)-250-400 -> 46600 | D29: =D28-500-(200+300+300)-250-400 -> 49850 | E29: =E28-500-(200+300+300)-250-400 -> 47700 | F29: =F28-500-(200+300+300)-250-400 -> 46600 | G29: =G28-500-(200+300+300)-250-400 -> 48550 | H29: =H28-500-(200+300+300)-250-400 -> 48850 | J29: =50000-B24 -> 3769.2308 | K29: =49600-2900-400-C25 -> 2685 | M29: =53150-3600-C24 -> 6435 | O29: =52550-4000-C24 -> 5435
A30: Current GM: C | B30: =B29-B24 -> 3119.2308 | C30: =C29-C24 -> 3485 | D30: =D29-D24 -> 3076.9231 | E30: =E29-E24 -> 4055.7692 | F30: =F29-F24 -> 3825 | G30: =G29-G24 -> 3119.2308 | H30: =H29-H24 -> 4064.6154 | K30: =K28-K29 -> 500 | M30: =53150-3600-C25 -> 5935 | N30: =M29-M30 -> 500 | O30: =52550-4000-C25 -> 4935 | S30: =49000-3550-1250-C24 -> 1085 | T30: =49000-1000-1000-G24 -> 1569.2308 | U30: =49000-3450-1000-F24 -> 1775
Q31: =49000-1000-1000-G24 -> 1569.2308 | R31: =49700-1050-D24 -> 1876.9231 | S31: =49000-3550-1250-C25 -> 585 | T31: =49000-1000-1000-G25 -> 1200 | U31: =49000-3450-1000-F25 -> 1275
B32: =B24+1100+1800 -> 49130.769 | D32: =C24+1250+3500+2000 -> 49865 | G32: =50000-1500-G24-1000 -> 2069.2308 | K32: 5 | L32: 9 | M32: =K32-L32 -> -4 | Q32: =49000-1000-1000-G25 -> 1200 | R32: =49700-1050-D25 -> 1400
D33: =50000-3500-1250-C24 -> 2135 | F33: =D24-B24 -> 542.30769 | L33: =51200-1200-B24 -> 3769.2308
G34: =G24+1000+1000+2000 -> 49430.769 | H34: =49000+3500 -> 52500 | J34: =50600-1200-B24 -> 3169.2308 | L34: =51200-1000-D24 -> 3426.9231 | O34: =50200-200-2500 -> 47500 | P34: =47000+2500+200 -> 49700
A35: Plant | B35: Jun H1 notional | D35: =49000-700-B24 -> 2069.2308 | E35: =C24+1250+3500+2000 -> 49865 | J35: =50600-550-D24 -> 3276.9231 | R35: =C24+1250+2000 -> 46365 | S35: =51000-1440-500-800-D24 -> 1486.9231
A36: Sikandarabad | B36: 47200 | S36: =51000-1440-500-800-D25 -> 1010
A37: API, Raipur | B37: 44915 | F37: =49500-G24-1000-2000 -> 1069.2308 | G37: =49700-1050-800-D24 -> 1076.9231 | H37: =G24+1000+1000+2000 -> 49430.769 | R37: =46000 -> 46000
A38: SKA, Raipur | B38: 44575 | G38: =49700-1050-800-D25 -> 600 | K38: =49700-800-1050-D24 -> 1076.9231 | O38: =50600-2600-200-C24-1250 -> 3435 | R38: =R37-C24 -> 2885
A39: Kala Amb | B39: 47550 | H39: =48000-G24-1000 -> 1569.2308 | K39: =49700-1200-B24 -> 2269.2308 | L39: =(K39*42+K38*126)/168 -> 1375 | O39: =50600-2600-200-C25-1250 -> 2935 | P39: =O38-O39 -> 500
A40: Gwalior | B40: =B36-800 -> 46400 | D40: =53000-1800-B40-1000 -> 3800
A41: Jaipur | B41: 45970 | F41: =G24-C24 -> 2315.7692

Sheet Jul'25 H1 temp
B1: Fe 500
A2: Region / Date | B2: Ex-Ahmedabad | C2: Ex-Bangalore | D2: Ex-Chennai | E2: Ex-Delhi/NCR | F2: Ex-Durgapur | G2: Ex-Goa | H2: Ex-Hyderabad | I2: Ex-Jaipur | J2: Ex-Jalna | K2: Ex-Mandi Gobindgarh | L2: Ex-Mumbai | M2: Ex-Muzaffarnagar | N2: Ex-Patna | O2: Ex-Raigarh | P2: Ex-Raipur | Q2: Ex-Rourkela
A3: 45839 | B3: =_xlfn.XLOOKUP(A3,'steel Mint data'!A:A,'steel Mint data'!B:B,"",0) -> 43200 | E3: =_xlfn.XLOOKUP(A3,'steel Mint data'!A:A,'steel Mint data'!D:D,"",0) -> 44500 | I3: =_xlfn.XLOOKUP(A3,'steel Mint data'!A:A,'steel Mint data'!I:I,"",0) -> 43300 | K3: =_xlfn.XLOOKUP(A3,'steel Mint data'!A:A,'steel Mint data'!L:L,"",0) -> 45800 | P3: =_xlfn.XLOOKUP(A3,'steel Mint data'!A:A,'steel Mint data'!Q:Q,"",0) -> 39800 | Q3: =_xlfn.XLOOKUP(A3,'steel Mint data'!A:A,'steel Mint data'!R:R,"",0) -> 40900
A4: 45840
A5: 45841
A6: 45842
A7: 45843
A8: 45844
A9: 45845
A10: 45846 | B10: =_xlfn.XLOOKUP(A10,'steel Mint data'!A:A,'steel Mint data'!B:B,"",0) -> 42800 | E10: =_xlfn.XLOOKUP(A10,'steel Mint data'!A:A,'steel Mint data'!D:D,"",0) -> 43900 | I10: =_xlfn.XLOOKUP(A10,'steel Mint data'!A:A,'steel Mint data'!I:I,"",0) -> 43000 | K10: =_xlfn.XLOOKUP(A10,'steel Mint data'!A:A,'steel Mint data'!L:L,"",0) -> 45400 | P10: =_xlfn.XLOOKUP(A10,'steel Mint data'!A:A,'steel Mint data'!Q:Q,"",0) -> 39500 | Q10: =_xlfn.XLOOKUP(A10,'steel Mint data'!A:A,'steel Mint data'!R:R,"",0) -> 41000
A11: 45847 | B11: =_xlfn.XLOOKUP(A11,'steel Mint data'!A:A,'steel Mint data'!B:B,"",0) -> 43200 | E11: =_xlfn.XLOOKUP(A11,'steel Mint data'!A:A,'steel Mint data'!D:D,"",0) -> 44400 | I11: =_xlfn.XLOOKUP(A11,'steel Mint data'!A:A,'steel Mint data'!I:I,"",0) -> 43200 | K11: =_xlfn.XLOOKUP(A11,'steel Mint data'!A:A,'steel Mint data'!L:L,"",0) -> 45500 | P11: =_xlfn.XLOOKUP(A11,'steel Mint data'!A:A,'steel Mint data'!Q:Q,"",0) -> 39700 | Q11: =_xlfn.XLOOKUP(A11,'steel Mint data'!A:A,'steel Mint data'!R:R,"",0) -> 41000
A12: 45848 | B12: =_xlfn.XLOOKUP(A12,'steel Mint data'!A:A,'steel Mint data'!B:B,"",0) -> 43200 | E12: =_xlfn.XLOOKUP(A12,'steel Mint data'!A:A,'steel Mint data'!D:D,"",0) -> 44400 | I12: =_xlfn.XLOOKUP(A12,'steel Mint data'!A:A,'steel Mint data'!I:I,"",0) -> 43200 | K12: =_xlfn.XLOOKUP(A12,'steel Mint data'!A:A,'steel Mint data'!L:L,"",0) -> 45500 | P12: =_xlfn.XLOOKUP(A12,'steel Mint data'!A:A,'steel Mint data'!Q:Q,"",0) -> 39700 | Q12: =_xlfn.XLOOKUP(A12,'steel Mint data'!A:A,'steel Mint data'!R:R,"",0) -> 40800
A13: 45849 | B13: =_xlfn.XLOOKUP(A13,'steel Mint data'!A:A,'steel Mint data'!B:B,"",0) -> 43200 | E13: =_xlfn.XLOOKUP(A13,'steel Mint data'!A:A,'steel Mint data'!D:D,"",0) -> 44300 | I13: =_xlfn.XLOOKUP(A13,'steel Mint data'!A:A,'steel Mint data'!I:I,"",0) -> 43000 | K13: =_xlfn.XLOOKUP(A13,'steel Mint data'!A:A,'steel Mint data'!L:L,"",0) -> 45500 | P13: =_xlfn.XLOOKUP(A13,'steel Mint data'!A:A,'steel Mint data'!Q:Q,"",0) -> 39500 | Q13: =_xlfn.XLOOKUP(A13,'steel Mint data'!A:A,'steel Mint data'!R:R,"",0) -> 40700
A14: 45850 | B14: =_xlfn.XLOOKUP(A14,'steel Mint data'!A:A,'steel Mint data'!B:B,"",0) -> 43200 | E14: =_xlfn.XLOOKUP(A14,'steel Mint data'!A:A,'steel Mint data'!D:D,"",0) -> 44000 | I14: =_xlfn.XLOOKUP(A14,'steel Mint data'!A:A,'steel Mint data'!I:I,"",0) -> 43000 | K14: =_xlfn.XLOOKUP(A14,'steel Mint data'!A:A,'steel Mint data'!L:L,"",0) -> 45300 | P14: =_xlfn.XLOOKUP(A14,'steel Mint data'!A:A,'steel Mint data'!Q:Q,"",0) -> 39300 | Q14: =_xlfn.XLOOKUP(A14,'steel Mint data'!A:A,'steel Mint data'!R:R,"",0) -> 40600
A15: 45851 | B15: =_xlfn.XLOOKUP(A15,'steel Mint data'!A:A,'steel Mint data'!B:B,"",0) -> H | E15: =_xlfn.XLOOKUP(A15,'steel Mint data'!A:A,'steel Mint data'!D:D,"",0) -> H | I15: =_xlfn.XLOOKUP(A15,'steel Mint data'!A:A,'steel Mint data'!I:I,"",0) -> H | K15: =_xlfn.XLOOKUP(A15,'steel Mint data'!A:A,'steel Mint data'!L:L,"",0) -> H | P15: =_xlfn.XLOOKUP(A15,'steel Mint data'!A:A,'steel Mint data'!Q:Q,"",0) -> H | Q15: =_xlfn.XLOOKUP(A15,'steel Mint data'!A:A,'steel Mint data'!R:R,"",0) -> H
A16: 45852 | B16: =_xlfn.XLOOKUP(A16,'steel Mint data'!A:A,'steel Mint data'!B:B,"",0) -> 42800 | E16: =_xlfn.XLOOKUP(A16,'steel Mint data'!A:A,'steel Mint data'!D:D,"",0) -> 43900 | I16: =_xlfn.XLOOKUP(A16,'steel Mint data'!A:A,'steel Mint data'!I:I,"",0) -> 42700 | K16: =_xlfn.XLOOKUP(A16,'steel Mint data'!A:A,'steel Mint data'!L:L,"",0) -> 45200 | P16: =_xlfn.XLOOKUP(A16,'steel Mint data'!A:A,'steel Mint data'!Q:Q,"",0) -> 39200 | Q16: =_xlfn.XLOOKUP(A16,'steel Mint data'!A:A,'steel Mint data'!R:R,"",0) -> 40200
A17: 45853 | B17: =_xlfn.XLOOKUP(A17,'steel Mint data'!A:A,'steel Mint data'!B:B,"",0) -> 42600 | E17: =_xlfn.XLOOKUP(A17,'steel Mint data'!A:A,'steel Mint data'!D:D,"",0) -> 43800 | I17: =_xlfn.XLOOKUP(A17,'steel Mint data'!A:A,'steel Mint data'!I:I,"",0) -> 42400 | K17: =_xlfn.XLOOKUP(A17,'steel Mint data'!A:A,'steel Mint data'!L:L,"",0) -> 45000 | P17: =_xlfn.XLOOKUP(A17,'steel Mint data'!A:A,'steel Mint data'!Q:Q,"",0) -> 39000 | Q17: =_xlfn.XLOOKUP(A17,'steel Mint data'!A:A,'steel Mint data'!R:R,"",0) -> 40200
B18: =_xlfn.XLOOKUP(A18,'steel Mint data'!A:A,'steel Mint data'!B:B,"",0) | S18: =49000-2500-F24 -> 4962.5 | T18: =47500-2500-F24 -> 3462.5
B19: =SUM(B3:B18) -> 344200 | E19: =SUM(E3:E18) -> 353200 | I19: =SUM(I3:I18) -> 343800 | K19: =SUM(K3:K18) -> 363200 | P19: =SUM(P3:P18) -> 315700 | Q19: =SUM(Q3:Q18) -> 325400 | S19: =49000-2500-F25 -> 4225 | T19: =47500-2500-F25 -> 2725
B20: Amba Shakti (NCR) | C20: API (Raipur) | D20: Aditya Industries (Mandi) | E20: Shree Ganesh (Rourkela) | F20: SKA Raipur | G20: Amba Gwalior | H20: Rajasthan | I20: Gujarat
A21: Avg Price - Divided by no of days steel mint price is available | B21: =E19/O21 -> 44150 | C21: =P19/O21 -> 39462.5 | D21: =K19/O21 -> 45400 | E21: =Q19/O21 -> 40675 | F21: =C21 -> 39462.5 | G21: =B21-800 -> 43350 | H21: =I19/O21 -> 42975 | I21: =B19/O21 -> 43025 | O21: =COUNT(P3:P18) -> 8 | T21: =(S18*40+T18*302)/342 -> 3637.9386
A22: BIS | B22: 1200 | C22: 2150 | D22: 400 | E22: 2200 | F22: 1800 | G22: 1200 | H22: 800 | I22: 0 | J22: 1000 | K22: =G24+2200+1000+2000 -> 49950 | M22: =G24+1000+2000 -> 47750 | Q22: =48000-1000-G24 -> 2250 | T22: =(S19*40+T19*302)/342 -> 2900.4386
A23: Loading Charges | B23: 200 | C23: 265 | D23: 250 | E23: 275 | F23: 275 | G23: 200 | H23: 270 | I23: 200 | K23: =C24+1250+1500 -> 44627.5 | L23: =K23+3500 -> 48127.5 | Q23: =49450-1450-1000-G24 -> 2250
A24: Actual PO Price (base dia): A | B24: =SUM(B21:B23) -> 45550 | C24: =SUM(C21:C23) -> 41877.5 | D24: =SUM(D21:D23) -> 46050 | E24: =SUM(E21:E23) -> 43150 | F24: =SUM(F21:F23) -> 41537.5 | G24: =SUM(G21:G23) -> 44750 | H24: =SUM(H21:H23) -> 44045 | I24: =SUM(I21:I23) -> 43225 | J24: =I24+1000+2000+2500 -> 48725
A25: Notional PO: B | B25: =B36 -> 46000 | C25: =B37 -> 42615 | D25: =B39 -> 46450 | E25: =B42 -> 43675 | F25: =B38 -> 42275 | G25: =B40 -> 45200 | H25: =B41 -> 44470 | I25: 43500 | K25: =G25-C25 -> 2585 | L25: =K25-1000 -> 1585 | O25: =48500-C25-3600-1250 -> 1035
A26: Change (A-B) | B26: =B24-B25 -> -450 | C26: =C24-C25 -> -737.5 | D26: =D24-D25 -> -400 | E26: =E24-E25 -> -525 | F26: =F24-F25 -> -737.5 | G26: =G24-G25 -> -450 | H26: =H24-H25 -> -425 | I26: =I24-I25 -> -275 | K26: 48550 | S26: =45800-3100-F24 -> 1162.5 | T26: =45800 -> 45800
K27: =C25+3000 -> 45615 | N27: =46000-3350-F24 -> 1112.5 | O27: =46000-3600-F24 -> 862.5 | Q27: =48000-1250-C24 -> 4872.5 | S27: =45800-3100-F25 -> 425
A28: Current PL | B28: 49300 | C28: 46550 | D28: 49800 | E28: 47650 | F28: 46550 | G28: 48500 | H28: 48800 | I28: 48800 | K28: =K26-K27 -> 2935 | N28: =46000-3350-F25 -> 375 | O28: =46000-3600-F25 -> 125 | Q28: =48000-1000-G24 -> 2250 | R28: =Q27-Q28 -> 2622.5
A29: Current ex plant NR | B29: =B28-500-(200+300+300)-250-400 -> 47350 | C29: =C28-500-(200+300+300)-250-400 -> 44600 | D29: =D28-500-(200+300+300)-250-400 -> 47850 | E29: =E28-500-(200+300+300)-250-400 -> 45700 | F29: =F28-500-(200+300+300)-250-400 -> 44600 | G29: =G28-500-(200+300+300)-250-400 -> 46550 | H29: =H28-500-(200+300+300)-250-400 -> 46850 | I29: =I28-500-(200+300+300)-250-400 -> 46850 | K29: =K26-3000-C25 -> 2935 | M29: =47300-1100-D24 -> 150
A30: Current GM: C | B30: =B29-B24 -> 1800 | C30: =C29-C24 -> 2722.5 | D30: =D29-D24 -> 1800 | E30: =E29-E24 -> 2550 | F30: =F29-F24 -> 3062.5 | G30: =G29-G24 -> 1800 | H30: =H29-H24 -> 2805 | I30: =I29-I24 -> 3625 | Q30: =48000-1250-C24 -> 4872.5
O31: =46000-1250-C24 -> 2872.5 | P31: =O31-O32 -> 737.5 | R31: Gwalior | S31: SKA | T31: API
B32: =B28-B24 -> 3750 | C32: =C28-C24 -> 4672.5 | D32: =D28-D24 -> 3750 | E32: =E28-E24 -> 4500 | F32: =F28-F24 -> 5012.5 | G32: =G28-G24 -> 3750 | H32: =H28-H24 -> 4755 | I32: =I28-I24 -> 5575 | N32: =46000-1000-F24 -> 3462.5 | O32: =46000-1250-C25 -> 2135 | R32: =G24+1500+1000+500 -> 47750 | S32: =F24+1000+500+3000 -> 46037.5
B33: =B28-800-300 -> 48200 | R33: =G25+1500+1000+500 -> 48200
B34: Fe 500 | C34: Fe 550D | D34: =C24+3000+1200 -> 46077.5 | L34: =3600+700 -> 4300
A35: Plant | B35: Jul H1 notional | D35: =46500-C24 -> 4622.5 | E35: =D24+800+1200 -> 48050 | F35: =B24+1500 -> 47050 | H35: =F24+500+1000+3000 -> 46037.5 | L35: =C24+1250+2000+L34 -> 49427.5 | P35: =46400-3300-1000-F24 -> 562.5
A36: Sikandarabad | B36: 46000 | O36: =F24+3000+500 -> 45037.5
A37: API, Raipur | B37: 42615 | C37: =B37+1250 -> 43865 | F37: =F24+500+3000 -> 45037.5 | H37: =45000-1000-F24 -> 2462.5
A38: SKA, Raipur | B38: 42275 | C38: =B38+1000 -> 43275 | J38: =43865+3500+1200 -> 48565 | K38: =48250 -> 48250
A39: Kala Amb | B39: 46450 | C39: =B39+800 -> 47250 | P39: =47300-1300-1000-F24 -> 3462.5
A40: Gwalior | B40: 45200 | C40: =B40+1000 -> 46200 | D40: =C40-C39 -> -1050 | I40: =46200+2000+2000 -> 50200 | P40: =47300-1300-1000-F25 -> 2725
A41: Jaipur | B41: 44470
A42: Roukeral | B42: 43675
A43: Gujarat | B43: =44500-1000 -> 43500 | C43: =B43+1000 -> 44500
B45: =45100-F24-2200 -> 1362.5

Sheet Jul'25 H1
B1: Fe 500
A2: Region / Date | B2: Ex-Ahmedabad | C2: Ex-Bangalore | D2: Ex-Chennai | E2: Ex-Delhi/NCR | F2: Ex-Durgapur | G2: Ex-Goa | H2: Ex-Hyderabad | I2: Ex-Jaipur | J2: Ex-Jalna | K2: Ex-Mandi Gobindgarh | L2: Ex-Mumbai | M2: Ex-Muzaffarnagar | N2: Ex-Patna | O2: Ex-Raigarh | P2: Ex-Raipur | Q2: Ex-Rourkela
A3: 45839 | B3: =_xlfn.XLOOKUP(A3,'steel Mint data'!A:A,'steel Mint data'!B:B,"",0) -> 43200 | E3: =_xlfn.XLOOKUP(A3,'steel Mint data'!A:A,'steel Mint data'!D:D,"",0) -> 44500 | I3: =_xlfn.XLOOKUP(A3,'steel Mint data'!A:A,'steel Mint data'!I:I,"",0) -> 43300 | K3: =_xlfn.XLOOKUP(A3,'steel Mint data'!A:A,'steel Mint data'!L:L,"",0) -> 45800 | P3: =_xlfn.XLOOKUP(A3,'steel Mint data'!A:A,'steel Mint data'!Q:Q,"",0) -> 39800 | Q3: =_xlfn.XLOOKUP(A3,'steel Mint data'!A:A,'steel Mint data'!R:R,"",0) -> 40900
A4: 45840 | B4: =_xlfn.XLOOKUP(A4,'steel Mint data'!A:A,'steel Mint data'!B:B,"",0) -> 43000 | E4: =_xlfn.XLOOKUP(A4,'steel Mint data'!A:A,'steel Mint data'!D:D,"",0) -> 44400 | I4: =_xlfn.XLOOKUP(A4,'steel Mint data'!A:A,'steel Mint data'!I:I,"",0) -> 43300 | K4: =_xlfn.XLOOKUP(A4,'steel Mint data'!A:A,'steel Mint data'!L:L,"",0) -> 45700 | P4: =_xlfn.XLOOKUP(A4,'steel Mint data'!A:A,'steel Mint data'!Q:Q,"",0) -> 39900 | Q4: =_xlfn.XLOOKUP(A4,'steel Mint data'!A:A,'steel Mint data'!R:R,"",0) -> 41000
A5: 45841 | B5: =_xlfn.XLOOKUP(A5,'steel Mint data'!A:A,'steel Mint data'!B:B,"",0) -> 42800 | E5: =_xlfn.XLOOKUP(A5,'steel Mint data'!A:A,'steel Mint data'!D:D,"",0) -> 44200 | I5: =_xlfn.XLOOKUP(A5,'steel Mint data'!A:A,'steel Mint data'!I:I,"",0) -> 43200 | K5: =_xlfn.XLOOKUP(A5,'steel Mint data'!A:A,'steel Mint data'!L:L,"",0) -> 45500 | P5: =_xlfn.XLOOKUP(A5,'steel Mint data'!A:A,'steel Mint data'!Q:Q,"",0) -> 39700 | Q5: =_xlfn.XLOOKUP(A5,'steel Mint data'!A:A,'steel Mint data'!R:R,"",0) -> 40800
A6: 45842 | B6: =_xlfn.XLOOKUP(A6,'steel Mint data'!A:A,'steel Mint data'!B:B,"",0) -> 42800 | E6: =_xlfn.XLOOKUP(A6,'steel Mint data'!A:A,'steel Mint data'!D:D,"",0) -> 44200 | I6: =_xlfn.XLOOKUP(A6,'steel Mint data'!A:A,'steel Mint data'!I:I,"",0) -> 43200 | K6: =_xlfn.XLOOKUP(A6,'steel Mint data'!A:A,'steel Mint data'!L:L,"",0) -> 45500 | P6: =_xlfn.XLOOKUP(A6,'steel Mint data'!A:A,'steel Mint data'!Q:Q,"",0) -> 39400 | Q6: =_xlfn.XLOOKUP(A6,'steel Mint data'!A:A,'steel Mint data'!R:R,"",0) -> 40800
A7: 45843 | B7: =_xlfn.XLOOKUP(A7,'steel Mint data'!A:A,'steel Mint data'!B:B,"",0) -> 42800 | E7: =_xlfn.XLOOKUP(A7,'steel Mint data'!A:A,'steel Mint data'!D:D,"",0) -> 44200 | I7: =_xlfn.XLOOKUP(A7,'steel Mint data'!A:A,'steel Mint data'!I:I,"",0) -> 43200 | K7: =_xlfn.XLOOKUP(A7,'steel Mint data'!A:A,'steel Mint data'!L:L,"",0) -> 45500 | P7: =_xlfn.XLOOKUP(A7,'steel Mint data'!A:A,'steel Mint data'!Q:Q,"",0) -> 39400 | Q7: =_xlfn.XLOOKUP(A7,'steel Mint data'!A:A,'steel Mint data'!R:R,"",0) -> 40800
A8: 45844 | B8: =_xlfn.XLOOKUP(A8,'steel Mint data'!A:A,'steel Mint data'!B:B,"",0) -> H | E8: =_xlfn.XLOOKUP(A8,'steel Mint data'!A:A,'steel Mint data'!D:D,"",0) -> H | I8: =_xlfn.XLOOKUP(A8,'steel Mint data'!A:A,'steel Mint data'!I:I,"",0) -> H | K8: =_xlfn.XLOOKUP(A8,'steel Mint data'!A:A,'steel Mint data'!L:L,"",0) -> H | P8: =_xlfn.XLOOKUP(A8,'steel Mint data'!A:A,'steel Mint data'!Q:Q,"",0) -> H | Q8: =_xlfn.XLOOKUP(A8,'steel Mint data'!A:A,'steel Mint data'!R:R,"",0) -> H
A9: 45845 | B9: =_xlfn.XLOOKUP(A9,'steel Mint data'!A:A,'steel Mint data'!B:B,"",0) -> 42800 | E9: =_xlfn.XLOOKUP(A9,'steel Mint data'!A:A,'steel Mint data'!D:D,"",0) -> 44000 | I9: =_xlfn.XLOOKUP(A9,'steel Mint data'!A:A,'steel Mint data'!I:I,"",0) -> 43200 | K9: =_xlfn.XLOOKUP(A9,'steel Mint data'!A:A,'steel Mint data'!L:L,"",0) -> 45500 | P9: =_xlfn.XLOOKUP(A9,'steel Mint data'!A:A,'steel Mint data'!Q:Q,"",0) -> 39400 | Q9: =_xlfn.XLOOKUP(A9,'steel Mint data'!A:A,'steel Mint data'!R:R,"",0) -> 40800
A10: 45846 | B10: =_xlfn.XLOOKUP(A10,'steel Mint data'!A:A,'steel Mint data'!B:B,"",0) -> 42800 | E10: =_xlfn.XLOOKUP(A10,'steel Mint data'!A:A,'steel Mint data'!D:D,"",0) -> 43900 | I10: =_xlfn.XLOOKUP(A10,'steel Mint data'!A:A,'steel Mint data'!I:I,"",0) -> 43000 | K10: =_xlfn.XLOOKUP(A10,'steel Mint data'!A:A,'steel Mint data'!L:L,"",0) -> 45400 | P10: =_xlfn.XLOOKUP(A10,'steel Mint data'!A:A,'steel Mint data'!Q:Q,"",0) -> 39500 | Q10: =_xlfn.XLOOKUP(A10,'steel Mint data'!A:A,'steel Mint data'!R:R,"",0) -> 41000
A11: 45847 | B11: =_xlfn.XLOOKUP(A11,'steel Mint data'!A:A,'steel Mint data'!B:B,"",0) -> 43200 | E11: =_xlfn.XLOOKUP(A11,'steel Mint data'!A:A,'steel Mint data'!D:D,"",0) -> 44400 | I11: =_xlfn.XLOOKUP(A11,'steel Mint data'!A:A,'steel Mint data'!I:I,"",0) -> 43200 | K11: =_xlfn.XLOOKUP(A11,'steel Mint data'!A:A,'steel Mint data'!L:L,"",0) -> 45500 | P11: =_xlfn.XLOOKUP(A11,'steel Mint data'!A:A,'steel Mint data'!Q:Q,"",0) -> 39700 | Q11: =_xlfn.XLOOKUP(A11,'steel Mint data'!A:A,'steel Mint data'!R:R,"",0) -> 41000
A12: 45848 | B12: =_xlfn.XLOOKUP(A12,'steel Mint data'!A:A,'steel Mint data'!B:B,"",0) -> 43200 | E12: =_xlfn.XLOOKUP(A12,'steel Mint data'!A:A,'steel Mint data'!D:D,"",0) -> 44400 | I12: =_xlfn.XLOOKUP(A12,'steel Mint data'!A:A,'steel Mint data'!I:I,"",0) -> 43200 | K12: =_xlfn.XLOOKUP(A12,'steel Mint data'!A:A,'steel Mint data'!L:L,"",0) -> 45500 | P12: =_xlfn.XLOOKUP(A12,'steel Mint data'!A:A,'steel Mint data'!Q:Q,"",0) -> 39700 | Q12: =_xlfn.XLOOKUP(A12,'steel Mint data'!A:A,'steel Mint data'!R:R,"",0) -> 40800
A13: 45849 | B13: =_xlfn.XLOOKUP(A13,'steel Mint data'!A:A,'steel Mint data'!B:B,"",0) -> 43200 | E13: =_xlfn.XLOOKUP(A13,'steel Mint data'!A:A,'steel Mint data'!D:D,"",0) -> 44300 | I13: =_xlfn.XLOOKUP(A13,'steel Mint data'!A:A,'steel Mint data'!I:I,"",0) -> 43000 | K13: =_xlfn.XLOOKUP(A13,'steel Mint data'!A:A,'steel Mint data'!L:L,"",0) -> 45500 | P13: =_xlfn.XLOOKUP(A13,'steel Mint data'!A:A,'steel Mint data'!Q:Q,"",0) -> 39500 | Q13: =_xlfn.XLOOKUP(A13,'steel Mint data'!A:A,'steel Mint data'!R:R,"",0) -> 40700
A14: 45850 | B14: =_xlfn.XLOOKUP(A14,'steel Mint data'!A:A,'steel Mint data'!B:B,"",0) -> 43200 | E14: =_xlfn.XLOOKUP(A14,'steel Mint data'!A:A,'steel Mint data'!D:D,"",0) -> 44000 | I14: =_xlfn.XLOOKUP(A14,'steel Mint data'!A:A,'steel Mint data'!I:I,"",0) -> 43000 | K14: =_xlfn.XLOOKUP(A14,'steel Mint data'!A:A,'steel Mint data'!L:L,"",0) -> 45300 | P14: =_xlfn.XLOOKUP(A14,'steel Mint data'!A:A,'steel Mint data'!Q:Q,"",0) -> 39300 | Q14: =_xlfn.XLOOKUP(A14,'steel Mint data'!A:A,'steel Mint data'!R:R,"",0) -> 40600
... A17: 45853 | B17: =_xlfn.XLOOKUP(A17,'steel Mint data'!A:A,'steel Mint data'!B:B,"",0) -> 42600 | E17: =_xlfn.XLOOKUP(A17,'steel Mint data'!A:A,'steel Mint data'!D:D,"",0) -> 43800 | I17: =_xlfn.XLOOKUP(A17,'steel Mint data'!A:A,'steel Mint data'!I:I,"",0) -> 42400 | K17: =_xlfn.XLOOKUP(A17,'steel Mint data'!A:A,'steel Mint data'!L:L,"",0) -> 45000 | P17: =_xlfn.XLOOKUP(A17,'steel Mint data'!A:A,'steel Mint data'!Q:Q,"",0) -> 39000 | Q17: =_xlfn.XLOOKUP(A17,'steel Mint data'!A:A,'steel Mint data'!R:R,"",0) -> 40200
B18: =_xlfn.XLOOKUP(A18,'steel Mint data'!A:A,'steel Mint data'!B:B,"",0) | S18: =49000-2500-F24 -> 4925 | T18: =47500-2500-F24 -> 3425
B19: =SUM(B3:B18) -> 558400 | E19: =SUM(E3:E18) -> 574200 | I19: =SUM(I3:I18) -> 559900 | K19: =SUM(K3:K18) -> 590900 | P19: =SUM(P3:P18) -> 513500 | Q19: =SUM(Q3:Q18) -> 529600 | S19: =49000-2500-F25 -> 4225 | T19: =47500-2500-F25 -> 2725
B20: Amba Shakti (NCR) | C20: API (Raipur) | D20: Aditya Industries (Mandi) | E20: Shree Ganesh (Rourkela) | F20: SKA Raipur | G20: Amba Gwalior | H20: Rajasthan | I20: Gujarat
A21: Avg Price - Divided by no of days steel mint price is available | B21: =E19/O21 -> 44169.231 | C21: =P19/O21 -> 39500 | D21: =K19/O21 -> 45453.846 | E21: =Q19/O21 -> 40738.462 | F21: =C21 -> 39500 | G21: =B21-800 -> 43369.231 | H21: =I19/O21 -> 43069.231 | I21: =B19/O21 -> 42953.846 | L21: 1650 | M21: 1250 | N21: 3500 | O21: =COUNT(P3:P18) -> 13 | T21: =(S18*40+T18*302)/342 -> 3600.4386
A22: BIS | B22: 1200 | C22: 2150 | D22: 400 | E22: 2200 | F22: 1800 | G22: 1200 | H22: 800 | I22: 0 | K22: Dashnoor -550D -42 | L22: gwalior | M22: kalaamb | N22: SKA Raipur | T22: =(S19*40+T19*302)/342 -> 2900.4386
A23: Loading Charges | B23: 200 | C23: 265 | D23: 250 | E23: 275 | F23: 275 | G23: 200 | H23: 270 | I23: 200 | K23: 46000 | L23: =$K$23-$L$21-1000-G24 -> -1419.2308 | M23: =46000-1250-800-D24 -> -2153.8462 | N23: =46000-3500-1000-F24 -> -75 | Q23: =47000-3600-F24 -> 1825
A24: Actual PO Price (base dia): A | B24: =SUM(B21:B23) -> 45569.231 | C24: =SUM(C21:C23) -> 41915 | D24: =SUM(D21:D23) -> 46103.846 | E24: =SUM(E21:E23) -> 43213.462 | F24: =SUM(F21:F23) -> 41575 | G24: =SUM(G21:G23) -> 44769.231 | H24: =SUM(H21:H23) -> 44139.231 | I24: =SUM(I21:I23) -> 43153.846 | L24: =$K$23-$L$21-1000-G25 -> -1850 | M24: =46000-1250-800-D25 -> -2500 | N24: =46000-3500-1000-F25 -> -775 | Q24: =47000-3600-F25 -> 1125
A25: Notional PO: B | B25: =B36 -> 46000 | C25: =B37 -> 42615 | D25: =B39 -> 46450 | E25: =B42 -> 43675 | F25: =B38 -> 42275 | G25: =B40 -> 45200 | H25: =B41 -> 44470 | I25: 43500 | R25: DEHRADUN | S25: Punjab
A26: Change (A-B) | B26: =B24-B25 -> -430.76923 | C26: =C24-C25 -> -700 | D26: =D24-D25 -> -346.15385 | E26: =E24-E25 -> -461.53846 | F26: =F24-F25 -> -700 | G26: =G24-G25 -> -430.76923 | H26: =H24-H25 -> -330.76923 | I26: =I24-I25 -> -346.15385 | L26: 850 | M26: 3150 | R26: =46820-1100-D24 -> -383.84615 | S26: =47220-1500-D24 -> -383.84615 | T26: =45800 -> 45800
K27: Shree Tect -120 MT 550 | L27: gwalior | M27: SKA Raipur | R27: =46820-1100-D25 -> -730 | S27: =47220-1500-D25 -> -730
A28: Current PL | B28: 49300 | C28: 46550 | D28: 49800 | E28: 47650 | F28: 46550 | G28: 48500 | H28: 48800 | I28: 48800 | K28: 45000 | L28: =45000-850-G24 -> -619.23077 | M28: =45000-3150-F24 -> 275 | R28: =46820-1100-G24 -> 950.76923
A29: Current ex plant NR | B29: =B28-500-(200+300+300)-250-400 -> 47350 | C29: =C28-500-(200+300+300)-250-400 -> 44600 | D29: =D28-500-(200+300+300)-250-400 -> 47850 | E29: =E28-500-(200+300+300)-250-400 -> 45700 | F29: =F28-500-(200+300+300)-250-400 -> 44600 | G29: =G28-500-(200+300+300)-250-400 -> 46550 | H29: =H28-500-(200+300+300)-250-400 -> 46850 | I29: =I28-500-(200+300+300)-250-400 -> 46850 | L29: =45000-850-G25 -> -1050 | M29: =45000-3150-F25 -> -425 | P29: =47000-3600-F24 -> 1825
A30: Current GM: C | B30: =B29-B24 -> 1780.7692 | C30: =C29-C24 -> 2685 | D30: =D29-D24 -> 1746.1538 | E30: =E29-E24 -> 2486.5385 | F30: =F29-F24 -> 3025 | G30: =G29-G24 -> 1780.7692 | H30: =H29-H24 -> 2710.7692 | I30: =I29-I24 -> 3696.1538 | K30: =45000-1000-I24 -> 846.15385 | P30: =47000-3600-F25 -> 1125
T31: API
B32: =B28-B24 -> 3730.7692 | C32: =C28-C24 -> 4635 | D32: =D28-D24 -> 3696.1538 | E32: =E28-E24 -> 4436.5385 | F32: =F28-F24 -> 4975 | G32: =G28-G24 -> 3730.7692 | H32: =H28-H24 -> 4660.7692 | I32: =I28-I24 -> 5646.1538 | K32: =D24-G24 -> 1334.6154
B33: =B28-800-300 -> 48200
B34: Fe 500 | C34: Fe 550D | D34: =C24+3000+1200 -> 46115
A35: Plant | B35: Jul H1 notional | D35: =46500-C24 -> 4585 | E35: =D24+800+1200 -> 48103.846 | F35: =B24+1500 -> 47069.231 | H35: =F24+500+1000+3000 -> 46075 | K35: =47800-1900 -> 45900
A36: Sikandarabad | B36: 46000
A37: API, Raipur | B37: 42615 | C37: =B37+1250 -> 43865 | F37: =F24+500+3000 -> 45075 | H37: =45000-1000-F24 -> 2425
A38: SKA, Raipur | B38: 42275 | C38: =B38+1000 -> 43275 | E38: =46700-1200 -> 45500
A39: Kala Amb | B39: 46450 | C39: =B39+800 -> 47250
A40: Gwalior | B40: 45200 | C40: =B40+1000 -> 46200 | D40: =C40-C39 -> -1050 | I40: =46200+2000+2000 -> 50200
A41: Jaipur | B41: 44470
A42: Roukeral | B42: 43675
A43: Gujarat | B43: =44500-1000 -> 43500 | C43: =B43+1000 -> 44500
C73: Grade | D73: CM | E73: 8 | F73: 10 | G73: 12 | H73: 16 | I73: 20 | J73: 25 | K73: 32 | L73: Grand Total
C74: Fe 550D | D74: API Ispat | E74: 171 | F74: 179 | G74: 288 | H74: 242 | I74: 393 | J74: 72 | L74: 1345
D75: SKA ISPAT | E75: 156 | F75: 54 | G75: 250 | H75: 250 | I75: 228 | J75: 280 | K75: 110 | L75: 1328
D76: Aditya Industries | E76: 46 | F76: 34 | G76: 195 | H76: 63 | I76: 31 | J76: 25 | L76: 394
D77: ASUL- Gwalior | E77: 89 | F77: 42 | G77: 17 | H77: 32 | I77: 55 | L77: 235
C78: Fe 550D Total | E78: 462 | F78: 309 | G78: 750 | H78: 587 | I78: 707 | J78: 377 | K78: 110 | L78: 3302

Sheet Jul'25 H2
B1: Fe 500
A2: Region / Date | B2: Ex-Ahmedabad | C2: Ex-Bangalore | D2: Ex-Chennai | E2: Ex-Delhi/NCR | F2: Ex-Durgapur | G2: Ex-Goa | H2: Ex-Hyderabad | I2: Ex-Jaipur | J2: Ex-Jalna | K2: Ex-Mandi Gobindgarh | L2: Ex-Mumbai | M2: Ex-Muzaffarnagar | N2: Ex-Patna | O2: Ex-Raigarh | P2: Ex-Raipur | Q2: Ex-Rourkela
A3: 45854 | B3: =_xlfn.XLOOKUP(A3,'steel Mint data'!A:A,'steel Mint data'!B:B,"",0) -> 42500 | E3: =_xlfn.XLOOKUP(A3,'steel Mint data'!A:A,'steel Mint data'!D:D,"",0) -> 43900 | I3: =_xlfn.XLOOKUP(A3,'steel Mint data'!A:A,'steel Mint data'!I:I,"",0) -> 42400 | K3: =_xlfn.XLOOKUP(A3,'steel Mint data'!A:A,'steel Mint data'!L:L,"",0) -> 44900 | P3: =_xlfn.XLOOKUP(A3,'steel Mint data'!A:A,'steel Mint data'!Q:Q,"",0) -> 39000 | Q3: =_xlfn.XLOOKUP(A3,'steel Mint data'!A:A,'steel Mint data'!R:R,"",0) -> 40100
A4: 45855 | B4: =_xlfn.XLOOKUP(A4,'steel Mint data'!A:A,'steel Mint data'!B:B,"",0) -> 43000 | E4: =_xlfn.XLOOKUP(A4,'steel Mint data'!A:A,'steel Mint data'!D:D,"",0) -> 43900 | I4: =_xlfn.XLOOKUP(A4,'steel Mint data'!A:A,'steel Mint data'!I:I,"",0) -> 42600 | K4: =_xlfn.XLOOKUP(A4,'steel Mint data'!A:A,'steel Mint data'!L:L,"",0) -> 45100 | P4: =_xlfn.XLOOKUP(A4,'steel Mint data'!A:A,'steel Mint data'!Q:Q,"",0) -> 39000 | Q4: =_xlfn.XLOOKUP(A4,'steel Mint data'!A:A,'steel Mint data'!R:R,"",0) -> 40200
A5: 45856 | B5: =_xlfn.XLOOKUP(A5,'steel Mint data'!A:A,'steel Mint data'!B:B,"",0) -> 43200 | E5: =_xlfn.XLOOKUP(A5,'steel Mint data'!A:A,'steel Mint data'!D:D,"",0) -> 44000 | I5: =_xlfn.XLOOKUP(A5,'steel Mint data'!A:A,'steel Mint data'!I:I,"",0) -> 42600 | K5: =_xlfn.XLOOKUP(A5,'steel Mint data'!A:A,'steel Mint data'!L:L,"",0) -> 45100 | P5: =_xlfn.XLOOKUP(A5,'steel Mint data'!A:A,'steel Mint data'!Q:Q,"",0) -> 39100 | Q5: =_xlfn.XLOOKUP(A5,'steel Mint data'!A:A,'steel Mint data'!R:R,"",0) -> 40400
A6: 45857 | B6: =_xlfn.XLOOKUP(A6,'steel Mint data'!A:A,'steel Mint data'!B:B,"",0) -> 43200 | E6: =_xlfn.XLOOKUP(A6,'steel Mint data'!A:A,'steel Mint data'!D:D,"",0) -> 44000 | I6: =_xlfn.XLOOKUP(A6,'steel Mint data'!A:A,'steel Mint data'!I:I,"",0) -> 42600 | K6: =_xlfn.XLOOKUP(A6,'steel Mint data'!A:A,'steel Mint data'!L:L,"",0) -> 45100 | P6: =_xlfn.XLOOKUP(A6,'steel Mint data'!A:A,'steel Mint data'!Q:Q,"",0) -> 39000 | Q6: =_xlfn.XLOOKUP(A6,'steel Mint data'!A:A,'steel Mint data'!R:R,"",0) -> 40400
A7: 45858 | B7: =_xlfn.XLOOKUP(A7,'steel Mint data'!A:A,'steel Mint data'!B:B,"",0) -> H | E7: =_xlfn.XLOOKUP(A7,'steel Mint data'!A:A,'steel Mint data'!D:D,"",0) -> H | I7: =_xlfn.XLOOKUP(A7,'steel Mint data'!A:A,'steel Mint data'!I:I,"",0) -> H | K7: =_xlfn.XLOOKUP(A7,'steel Mint data'!A:A,'steel Mint data'!L:L,"",0) -> H | P7: =_xlfn.XLOOKUP(A7,'steel Mint data'!A:A,'steel Mint data'!Q:Q,"",0) -> H | Q7: =_xlfn.XLOOKUP(A7,'steel Mint data'!A:A,'steel Mint data'!R:R,"",0) -> H
A8: 45859 | B8: =_xlfn.XLOOKUP(A8,'steel Mint data'!A:A,'steel Mint data'!B:B,"",0) -> 43200 | E8: =_xlfn.XLOOKUP(A8,'steel Mint data'!A:A,'steel Mint data'!D:D,"",0) -> 43800 | I8: =_xlfn.XLOOKUP(A8,'steel Mint data'!A:A,'steel Mint data'!I:I,"",0) -> 42500 | K8: =_xlfn.XLOOKUP(A8,'steel Mint data'!A:A,'steel Mint data'!L:L,"",0) -> 45000 | P8: =_xlfn.XLOOKUP(A8,'steel Mint data'!A:A,'steel Mint data'!Q:Q,"",0) -> 39000 | Q8: =_xlfn.XLOOKUP(A8,'steel Mint data'!A:A,'steel Mint data'!R:R,"",0) -> 40300
A9: 45860 | B9: =_xlfn.XLOOKUP(A9,'steel Mint data'!A:A,'steel Mint data'!B:B,"",0) -> 43200 | E9: =_xlfn.XLOOKUP(A9,'steel Mint data'!A:A,'steel Mint data'!D:D,"",0) -> 43600 | I9: =_xlfn.XLOOKUP(A9,'steel Mint data'!A:A,'steel Mint data'!I:I,"",0) -> 42500 | K9: =_xlfn.XLOOKUP(A9,'steel Mint data'!A:A,'steel Mint data'!L:L,"",0) -> 44900 | P9: =_xlfn.XLOOKUP(A9,'steel Mint data'!A:A,'steel Mint data'!Q:Q,"",0) -> 39100 | Q9: =_xlfn.XLOOKUP(A9,'steel Mint data'!A:A,'steel Mint data'!R:R,"",0) -> 40200
A10: 45861 | B10: =_xlfn.XLOOKUP(A10,'steel Mint data'!A:A,'steel Mint data'!B:B,"",0) -> 43400 | E10: =_xlfn.XLOOKUP(A10,'steel Mint data'!A:A,'steel Mint data'!D:D,"",0) -> 43800 | I10: =_xlfn.XLOOKUP(A10,'steel Mint data'!A:A,'steel Mint data'!I:I,"",0) -> 42800 | K10: =_xlfn.XLOOKUP(A10,'steel Mint data'!A:A,'steel Mint data'!L:L,"",0) -> 45100 | P10: =_xlfn.XLOOKUP(A10,'steel Mint data'!A:A,'steel Mint data'!Q:Q,"",0) -> 39500 | Q10: =_xlfn.XLOOKUP(A10,'steel Mint data'!A:A,'steel Mint data'!R:R,"",0) -> 40400
A11: 45862 | B11: =_xlfn.XLOOKUP(A11,'steel Mint data'!A:A,'steel Mint data'!B:B,"",0) -> 43800 | E11: =_xlfn.XLOOKUP(A11,'steel Mint data'!A:A,'steel Mint data'!D:D,"",0) -> 44000 | I11: =_xlfn.XLOOKUP(A11,'steel Mint data'!A:A,'steel Mint data'!I:I,"",0) -> 43300 | K11: =_xlfn.XLOOKUP(A11,'steel Mint data'!A:A,'steel Mint data'!L:L,"",0) -> 45200 | P11: =_xlfn.XLOOKUP(A11,'steel Mint data'!A:A,'steel Mint data'!Q:Q,"",0) -> 40200 | Q11: =_xlfn.XLOOKUP(A11,'steel Mint data'!A:A,'steel Mint data'!R:R,"",0) -> 40400
A12: 45863 | B12: =_xlfn.XLOOKUP(A12,'steel Mint data'!A:A,'steel Mint data'!B:B,"",0) -> 44500 | E12: =_xlfn.XLOOKUP(A12,'steel Mint data'!A:A,'steel Mint data'!D:D,"",0) -> 44800 | I12: =_xlfn.XLOOKUP(A12,'steel Mint data'!A:A,'steel Mint data'!I:I,"",0) -> 43700 | K12: =_xlfn.XLOOKUP(A12,'steel Mint data'!A:A,'steel Mint data'!L:L,"",0) -> 45500 | P12: =_xlfn.XLOOKUP(A12,'steel Mint data'!A:A,'steel Mint data'!Q:Q,"",0) -> 41200 | Q12: =_xlfn.XLOOKUP(A12,'steel Mint data'!A:A,'steel Mint data'!R:R,"",0) -> 41000
A13: 45864 | B13: =_xlfn.XLOOKUP(A13,'steel Mint data'!A:A,'steel Mint data'!B:B,"",0) -> 44500 | E13: =_xlfn.XLOOKUP(A13,'steel Mint data'!A:A,'steel Mint data'!D:D,"",0) -> 45000 | I13: =_xlfn.XLOOKUP(A13,'steel Mint data'!A:A,'steel Mint data'!I:I,"",0) -> 43600 | K13: =_xlfn.XLOOKUP(A13,'steel Mint data'!A:A,'steel Mint data'!L:L,"",0) -> 45600 | P13: =_xlfn.XLOOKUP(A13,'steel Mint data'!A:A,'steel Mint data'!Q:Q,"",0) -> 41000 | Q13: =_xlfn.XLOOKUP(A13,'steel Mint data'!A:A,'steel Mint data'!R:R,"",0) -> 41000
A14: 45865 | B14: =_xlfn.XLOOKUP(A14,'steel Mint data'!A:A,'steel Mint data'!B:B,"",0) -> H | E14: =_xlfn.XLOOKUP(A14,'steel Mint data'!A:A,'steel Mint data'!D:D,"",0) -> H | I14: =_xlfn.XLOOKUP(A14,'steel Mint data'!A:A,'steel Mint data'!I:I,"",0) -> H | K14: =_xlfn.XLOOKUP(A14,'steel Mint data'!A:A,'steel Mint data'!L:L,"",0) -> H | P14: =_xlfn.XLOOKUP(A14,'steel Mint data'!A:A,'steel Mint data'!Q:Q,"",0) -> H | Q14: =_xlfn.XLOOKUP(A14,'steel Mint data'!A:A,'steel Mint data'!R:R,"",0) -> H
... A17: 45868 | B17: =_xlfn.XLOOKUP(A17,'steel Mint data'!A:A,'steel Mint data'!B:B,"",0) -> 44100 | E17: =_xlfn.XLOOKUP(A17,'steel Mint data'!A:A,'steel Mint data'!D:D,"",0) -> 44700 | I17: =_xlfn.XLOOKUP(A17,'steel Mint data'!A:A,'steel Mint data'!I:I,"",0) -> 43200 | K17: =_xlfn.XLOOKUP(A17,'steel Mint data'!A:A,'steel Mint data'!L:L,"",0) -> 45400 | P17: =_xlfn.XLOOKUP(A17,'steel Mint data'!A:A,'steel Mint data'!Q:Q,"",0) -> 40200 | Q17: =_xlfn.XLOOKUP(A17,'steel Mint data'!A:A,'steel Mint data'!R:R,"",0) -> 40700
B18: =_xlfn.XLOOKUP(A18,'steel Mint data'!A:A,'steel Mint data'!B:B,"",0)
B19: =SUM(B3:B18) -> 567400 | E19: =SUM(E3:E18) -> 575500 | I19: =SUM(I3:I18) -> 558850 | K19: =SUM(K3:K18) -> 588100 | P19: =SUM(P3:P18) -> 517400 | Q19: =SUM(Q3:Q18) -> 526900
B20: Amba Shakti (NCR) | C20: API (Raipur) | D20: Aditya Industries (Mandi) | E20: Shree Ganesh (Rourkela) | F20: SKA Raipur | G20: Amba Gwalior | H20: Rajasthan | I20: Gujarat
A21: Avg Price - Divided by no of days steel mint price is available | B21: =E19/O21 -> 44269.231 | C21: =P19/O21 -> 39800 | D21: =K19/O21 -> 45238.462 | E21: =Q19/O21 -> 40530.769 | F21: =C21 -> 39800 | G21: =B21-800 -> 43469.231 | H21: =I19/O21 -> 42988.462 | I21: =B19/O21 -> 43646.154 | O21: =COUNT(P3:P18) -> 13
A22: BIS | B22: 1200 | C22: 2150 | D22: 400 | E22: 2200 | F22: 1800 | G22: 1200 | H22: 800 | I22: 0
A23: Loading Charges | B23: 200 | C23: 265 | D23: 250 | E23: 275 | F23: 275 | G23: 200 | H23: 270 | I23: 200
A24: Actual PO Price (base dia): A | B24: =SUM(B21:B23) -> 45669.231 | C24: =SUM(C21:C23) -> 42215 | D24: =SUM(D21:D23) -> 45888.462 | E24: =SUM(E21:E23) -> 43005.769 | F24: =SUM(F21:F23) -> 41875 | G24: =SUM(G21:G23) -> 44869.231 | H24: =SUM(H21:H23) -> 44058.462 | I24: =SUM(I21:I23) -> 43846.154
A25: Notional PO: B | B25: 45300 | C25: 41615 | D25: 45850 | E25: 42675 | F25: 41275 | G25: 44500 | H25: 43770 | I25: 43000
A26: Change (A-B) | B26: =B24-B25 -> 369.23077 | C26: =C24-C25 -> 600 | D26: =D24-D25 -> 38.461538 | E26: =E24-E25 -> 330.76923 | F26: =F24-F25 -> 600 | G26: =G24-G25 -> 369.23077 | H26: =H24-H25 -> 288.46154 | I26: =I24-I25 -> 846.15385
A28: Current PL | B28: 48300 | C28: 45550 | D28: 48800 | E28: 45550 | F28: 45550 | G28: 47500 | H28: 47800 | I28: 48300
A29: Current ex plant NR | B29: =B28-500-(200+300+300)-250-400 -> 46350 | C29: =C28-500-(200+300+300)-250-400 -> 43600 | D29: =D28-500-(200+300+300)-250-400 -> 46850 | E29: =E28-500-(200+300+300)-250-400 -> 43600 | F29: =F28-500-(200+300+300)-250-400 -> 43600 | G29: =G28-500-(200+300+300)-250-400 -> 45550 | H29: =H28-500-(200+300+300)-250-400 -> 45850 | I29: =I28-500-(200+300+300)-250-400 -> 46350
A30: Current GM: C | B30: =B29-B24 -> 680.76923 | C30: =C29-C24 -> 1385 | D30: =D29-D24 -> 961.53846 | E30: =E29-E24 -> 594.23077 | F30: =F29-F24 -> 1725 | G30: =G29-G24 -> 680.76923 | H30: =H29-H24 -> 1791.5385 | I30: =I29-I24 -> 2503.8462
T31: API
B32: =B28-B24-1000 -> 1630.7692 | C32: =C28-C24-1000 -> 2335 | D32: =D28-D24-1000 -> 1911.5385 | E32: =E28-E24-1000 -> 1544.2308 | F32: =F28-F24-1000 -> 2675 | G32: =G28-G24-1000 -> 1630.7692 | H32: =H28-H24-1000 -> 2741.5385 | I32: =I28-I24-1000 -> 3453.8462
B33: =B24+500+1000 -> 47169.231 | E33: =E8-P8 -> 4800 | L33: Name of Customer | M33: Qnty. | N33: Delivery Location | O33: Asking Price Deliverd | P33: Quoted Price | Q33: Status | R33: Freight | S33: Margin | XFD33: Asking Price Deliverd
B34: Fe 500 | C34: Fe 550D | D34: =C24+3000+1200 -> 46415 | G34: =F24+1000+3000 -> 45875 | K34: 1 | L34: Fuel pro System | M34: 200 | N34: Balram pur Chini Kumbhi, U.P. | O34: 43500 | P34: 44000 | Q34: Open/Client approval awaited | R34: =3200 -> 3200 | S34: =O34-R34-$F$24-1000 -> -2575 | XFD34: 43500
A35: Plant | B35: Jul H1 notional | D35: =46500-C24 -> 4285 | E35: =D24+800+1200 -> 47888.462 | F35: =B24+1500 -> 47169.231 | H35: =F24+500+1000+3000 -> 46375 | K35: 2 | L35: Ram Kripal Singh | M35: 170 | N35: Muzzafrpur Railway station | O35: 44000 | P35: 45300 | Q35: Under Negotation | R35: 3500 | S35: =O35-R35-$F$24-1000 -> -2375 | XFD35: 44000
A36: Sikandarabad | B36: 46000 | K36: 3 | L36: Shree Balajee Engicon | M36: 64 | N36: Jharsguda | O36: 43500 | P36: 43500 | Q36: PO Aawited | R36: 2500 | S36: =O36-R36-$F$24-1000 -> -1875 | XFD36: 43500
A37: API, Raipur | B37: 42615 | C37: =B37+1250 -> 43865 | F37: =F24+500+3000 -> 45375 | H37: =45000-1000-F24 -> 2125 | K37: 4 | L37: Trishul Engicon | M37: 300 | N37: Motihari -Bihar | O37: 44000 | P37: 47500 | Q37: Under Negotation | R37: 3500 | S37: =O37-R37-$F$24-1000 -> -2375 | XFD37: 44000
A38: SKA, Raipur | B38: 42275 | C38: =B38+1000 -> 43275 | E38: =46700-1200 -> 45500 | K38: 5 | L38: Orissa Engicon | M38: 84 | N38: CDA Cuttack | O38: 43000 | P38: 44000 | Q38: Under Negotation | R38: 2500 | S38: =O38-R38-$F$24-1000 -> -2375 | XFD38: 43000
A39: Kala Amb | B39: 46450 | C39: =B39+800 -> 47250 | K39: 6 | L39: GR INFRA | M39: 850 | N39: NAGPUR METRO | O39: 43500 | P39: 44700 | Q39: Cilent approval awaited | R39: 1500 | S39: =O39-R39-$F$24-1000 -> -875 | XFD39: 43500
A40: Gwalior | B40: 45200 | C40: =B40+1000 -> 46200 | D40: =C40-C39 -> -1050 | I40: =46200+2000+2000 -> 50200 | K40: 7 | L40: Velecha engg Co. Ltd | M40: 250 | N40: Muzzafarpur Smart City | O40: 44000 | P40: 45500 | Q40: Customer response awaited | R40: 3500 | S40: =O40-R40-$F$24-1000 -> -2375 | XFD40: 44000
A41: Jaipur | B41: 44470 | K41: 8 | L41: Rakesh Masala | M41: 84 | N41: Hajipur Bihar | O41: 45000 | P41: 45500 | Q41: PO awaited | R41: 3200 | S41: =O41-R41-$F$24-1000 -> -1075 | XFD41: 45000
A42: Roukeral | B42: 43675 | K42: 9 | L42: Ansh Enterprises | M42: 300 | N42: Ranchi | O42: 43500 | P42: 44500 | Q42: Bardhman Rolling awaited | R42: 3200 | S42: =O42-R42-$F$24-1000 -> -2575 | XFD42: 43500
A43: Gujarat | B43: =44500-1000 -> 43500 | C43: =B43+1000 -> 44500 | K43: 10 | L43: Shakti Merchant | M43: 500 | N43: Mixed | O43: 44000 | P43: 44000 | Q43: PO Confiration awaited | R43: 3200 | S43: =O43-R43-$F$24-1000 -> -2075 | XFD43: 44000
K44: 11 | L44: Angelique International | M44: 300 | N44: Delhi | O44: 44000 | P44: 44000 | Q44: Under InternalApproval | R44: 3200 | S44: =O44-R44-$F$24-1000 -> -2075 | XFD44: 44000
K45: 12 | L45: Ritesh Infrastructure | M45: 500 | N45: Chapra | O45: 44000 | P45: 45500 | Q45: Under Negotation | R45: 3500 | S45: =O45-R45-$F$24-1000 -> -2375 | XFD45: 44000
B46: 46800 | C46: 44050 | D46: =B46+500 -> 47300 | E46: =C46 -> 44050 | F46: 44050 | G46: =B46-800 -> 46000 | H46: =B46-500 -> 46300 | I46: =B46 -> 46800 | K46: 13 | L46: M.A Construction | M46: 200 | N46: Kolkata | O46: 41000 | P46: 46000 | Q46: Rashmi Used / Closed | XFD46: 41000
B47: =B46+1500 -> 48300 | C47: =C46+1500 -> 45550 | D47: =D46+1500 -> 48800 | E47: =E46+1500 -> 45550 | F47: =F46+1500 -> 45550 | G47: =G46+1500 -> 47500 | H47: =H46+1500 -> 47800 | I47: =I46+1500 -> 48300 | K47: TOTAL | M47: 3802
C73: Grade | D73: CM | E73: 8 | F73: 10 | G73: 12 | H73: 16 | I73: 20 | J73: 25 | K73: 32 | L73: Grand Total
C74: Fe 550D | D74: API Ispat | E74: 171 | F74: 179 | G74: 288 | H74: 242 | I74: 393 | J74: 72 | L74: 1345
D75: SKA ISPAT | E75: 156 | F75: 54 | G75: 250 | H75: 250 | I75: 228 | J75: 280 | K75: 110 | L75: 1328
D76: Aditya Industries | E76: 46 | F76: 34 | G76: 195 | H76: 63 | I76: 31 | J76: 25 | L76: 394
D77: ASUL- Gwalior | E77: 89 | F77: 42 | G77: 17 | H77: 32 | I77: 55 | L77: 235
C78: Fe 550D Total | E78: 462 | F78: 309 | G78: 750 | H78: 587 | I78: 707 | J78: 377 | K78: 110 | L78: 3302

Sheet Aug25 H1
B1: Fe 500
A2: Region / Date | B2: Ex-Ahmedabad | C2: Ex-Bangalore | D2: Ex-Chennai | E2: Ex-Delhi/NCR | F2: Ex-Durgapur | G2: Ex-Goa | H2: Ex-Hyderabad | I2: Ex-Jaipur | J2: Ex-Jalna | K2: Ex-Mandi Gobindgarh | L2: Ex-Mumbai | M2: Ex-Muzaffarnagar | N2: Ex-Patna | O2: Ex-Raigarh | P2: Ex-Raipur | Q2: Ex-Rourkela
A3: 45870 | B3: =_xlfn.XLOOKUP(A3,'steel Mint data'!A:A,'steel Mint data'!B:B,"",0) -> 44100 | E3: =_xlfn.XLOOKUP(A3,'steel Mint data'!A:A,'steel Mint data'!D:D,"",0) -> 44600 | F3: =_xlfn.XLOOKUP(A3,'steel Mint data'!A:A,'steel Mint data'!E:E,"",0) -> 40300 | I3: =_xlfn.XLOOKUP(A3,'steel Mint data'!A:A,'steel Mint data'!I:I,"",0) -> 43200 | K3: =_xlfn.XLOOKUP(A3,'steel Mint data'!A:A,'steel Mint data'!L:L,"",0) -> 45500 | P3: =_xlfn.XLOOKUP(A3,'steel Mint data'!A:A,'steel Mint data'!Q:Q,"",0) -> 39600 | Q3: =_xlfn.XLOOKUP(A3,'steel Mint data'!A:A,'steel Mint data'!R:R,"",0) -> 40700
A4: 45871 | B4: =_xlfn.XLOOKUP(A4,'steel Mint data'!A:A,'steel Mint data'!B:B,"",0) -> 44100 | E4: =_xlfn.XLOOKUP(A4,'steel Mint data'!A:A,'steel Mint data'!D:D,"",0) -> 44800 | F4: =_xlfn.XLOOKUP(A4,'steel Mint data'!A:A,'steel Mint data'!E:E,"",0) -> 40500 | I4: =_xlfn.XLOOKUP(A4,'steel Mint data'!A:A,'steel Mint data'!I:I,"",0) -> 43400 | K4: =_xlfn.XLOOKUP(A4,'steel Mint data'!A:A,'steel Mint data'!L:L,"",0) -> 45600 | P4: =_xlfn.XLOOKUP(A4,'steel Mint data'!A:A,'steel Mint data'!Q:Q,"",0) -> 39700 | Q4: =_xlfn.XLOOKUP(A4,'steel Mint data'!A:A,'steel Mint data'!R:R,"",0) -> 40800
A5: 45872 | B5: =_xlfn.XLOOKUP(A5,'steel Mint data'!A:A,'steel Mint data'!B:B,"",0) -> H | E5: =_xlfn.XLOOKUP(A5,'steel Mint data'!A:A,'steel Mint data'!D:D,"",0) -> H | F5: =_xlfn.XLOOKUP(A5,'steel Mint data'!A:A,'steel Mint data'!E:E,"",0) -> H | I5: =_xlfn.XLOOKUP(A5,'steel Mint data'!A:A,'steel Mint data'!I:I,"",0) -> H | K5: =_xlfn.XLOOKUP(A5,'steel Mint data'!A:A,'steel Mint data'!L:L,"",0) -> H | P5: =_xlfn.XLOOKUP(A5,'steel Mint data'!A:A,'steel Mint data'!Q:Q,"",0) -> H | Q5: =_xlfn.XLOOKUP(A5,'steel Mint data'!A:A,'steel Mint data'!R:R,"",0) -> H
A6: 45873 | B6: =_xlfn.XLOOKUP(A6,'steel Mint data'!A:A,'steel Mint data'!B:B,"",0) -> 44600 | E6: =_xlfn.XLOOKUP(A6,'steel Mint data'!A:A,'steel Mint data'!D:D,"",0) -> 45000 | F6: =_xlfn.XLOOKUP(A6,'steel Mint data'!A:A,'steel Mint data'!E:E,"",0) -> 40800 | I6: =_xlfn.XLOOKUP(A6,'steel Mint data'!A:A,'steel Mint data'!I:I,"",0) -> 43500 | K6: =_xlfn.XLOOKUP(A6,'steel Mint data'!A:A,'steel Mint data'!L:L,"",0) -> 45800 | P6: =_xlfn.XLOOKUP(A6,'steel Mint data'!A:A,'steel Mint data'!Q:Q,"",0) -> 40300 | Q6: =_xlfn.XLOOKUP(A6,'steel Mint data'!A:A,'steel Mint data'!R:R,"",0) -> 41000
A7: 45874 | B7: =_xlfn.XLOOKUP(A7,'steel Mint data'!A:A,'steel Mint data'!B:B,"",0) -> 44800 | E7: =_xlfn.XLOOKUP(A7,'steel Mint data'!A:A,'steel Mint data'!D:D,"",0) -> 45200 | F7: =_xlfn.XLOOKUP(A7,'steel Mint data'!A:A,'steel Mint data'!E:E,"",0) -> 40500 | I7: =_xlfn.XLOOKUP(A7,'steel Mint data'!A:A,'steel Mint data'!I:I,"",0) -> 43500 | K7: =_xlfn.XLOOKUP(A7,'steel Mint data'!A:A,'steel Mint data'!L:L,"",0) -> 46000 | P7: =_xlfn.XLOOKUP(A7,'steel Mint data'!A:A,'steel Mint data'!Q:Q,"",0) -> 40100 | Q7: =_xlfn.XLOOKUP(A7,'steel Mint data'!A:A,'steel Mint data'!R:R,"",0) -> 41000
A8: 45875 | B8: =_xlfn.XLOOKUP(A8,'steel Mint data'!A:A,'steel Mint data'!B:B,"",0) -> 44800 | E8: =_xlfn.XLOOKUP(A8,'steel Mint data'!A:A,'steel Mint data'!D:D,"",0) -> 44900 | F8: =_xlfn.XLOOKUP(A8,'steel Mint data'!A:A,'steel Mint data'!E:E,"",0) -> 40300 | I8: =_xlfn.XLOOKUP(A8,'steel Mint data'!A:A,'steel Mint data'!I:I,"",0) -> 43300 | K8: =_xlfn.XLOOKUP(A8,'steel Mint data'!A:A,'steel Mint data'!L:L,"",0) -> 45900 | P8: =_xlfn.XLOOKUP(A8,'steel Mint data'!A:A,'steel Mint data'!Q:Q,"",0) -> 39800 | Q8: =_xlfn.XLOOKUP(A8,'steel Mint data'!A:A,'steel Mint data'!R:R,"",0) -> 41000
A9: 45876 | B9: =_xlfn.XLOOKUP(A9,'steel Mint data'!A:A,'steel Mint data'!B:B,"",0) -> 44600 | E9: =_xlfn.XLOOKUP(A9,'steel Mint data'!A:A,'steel Mint data'!D:D,"",0) -> 44700 | F9: =_xlfn.XLOOKUP(A9,'steel Mint data'!A:A,'steel Mint data'!E:E,"",0) -> 39900 | I9: =_xlfn.XLOOKUP(A9,'steel Mint data'!A:A,'steel Mint data'!I:I,"",0) -> 43150 | K9: =_xlfn.XLOOKUP(A9,'steel Mint data'!A:A,'steel Mint data'!L:L,"",0) -> 45700 | P9: =_xlfn.XLOOKUP(A9,'steel Mint data'!A:A,'steel Mint data'!Q:Q,"",0) -> 39700 | Q9: =_xlfn.XLOOKUP(A9,'steel Mint data'!A:A,'steel Mint data'!R:R,"",0) -> 40800
A10: 45877 | B10: =_xlfn.XLOOKUP(A10,'steel Mint data'!A:A,'steel Mint data'!B:B,"",0) -> 44600 | E10: =_xlfn.XLOOKUP(A10,'steel Mint data'!A:A,'steel Mint data'!D:D,"",0) -> 44100 | F10: =_xlfn.XLOOKUP(A10,'steel Mint data'!A:A,'steel Mint data'!E:E,"",0) -> 39800 | I10: =_xlfn.XLOOKUP(A10,'steel Mint data'!A:A,'steel Mint data'!I:I,"",0) -> 43100 | K10: =_xlfn.XLOOKUP(A10,'steel Mint data'!A:A,'steel Mint data'!L:L,"",0) -> 45600 | P10: =_xlfn.XLOOKUP(A10,'steel Mint data'!A:A,'steel Mint data'!Q:Q,"",0) -> 39800 | Q10: =_xlfn.XLOOKUP(A10,'steel Mint data'!A:A,'steel Mint data'!R:R,"",0) -> 40800
A11: 45878 | B11: =_xlfn.XLOOKUP(A11,'steel Mint data'!A:A,'steel Mint data'!B:B,"",0) -> H | E11: =_xlfn.XLOOKUP(A11,'steel Mint data'!A:A,'steel Mint data'!D:D,"",0) -> H | F11: =_xlfn.XLOOKUP(A11,'steel Mint data'!A:A,'steel Mint data'!E:E,"",0) -> H | I11: =_xlfn.XLOOKUP(A11,'steel Mint data'!A:A,'steel Mint data'!I:I,"",0) -> H | K11: =_xlfn.XLOOKUP(A11,'steel Mint data'!A:A,'steel Mint data'!L:L,"",0) -> H | P11: =_xlfn.XLOOKUP(A11,'steel Mint data'!A:A,'steel Mint data'!Q:Q,"",0) -> H | Q11: =_xlfn.XLOOKUP(A11,'steel Mint data'!A:A,'steel Mint data'!R:R,"",0) -> H
A12: 45879 | B12: =_xlfn.XLOOKUP(A12,'steel Mint data'!A:A,'steel Mint data'!B:B,"",0) -> H | E12: =_xlfn.XLOOKUP(A12,'steel Mint data'!A:A,'steel Mint data'!D:D,"",0) -> H | F12: =_xlfn.XLOOKUP(A12,'steel Mint data'!A:A,'steel Mint data'!E:E,"",0) -> H | I12: =_xlfn.XLOOKUP(A12,'steel Mint data'!A:A,'steel Mint data'!I:I,"",0) -> H | K12: =_xlfn.XLOOKUP(A12,'steel Mint data'!A:A,'steel Mint data'!L:L,"",0) -> H | P12: =_xlfn.XLOOKUP(A12,'steel Mint data'!A:A,'steel Mint data'!Q:Q,"",0) -> H | Q12: =_xlfn.XLOOKUP(A12,'steel Mint data'!A:A,'steel Mint data'!R:R,"",0) -> H
A13: 45880 | B13: =_xlfn.XLOOKUP(A13,'steel Mint data'!A:A,'steel Mint data'!B:B,"",0) -> 44800 | E13: =_xlfn.XLOOKUP(A13,'steel Mint data'!A:A,'steel Mint data'!D:D,"",0) -> 44000 | F13: =_xlfn.XLOOKUP(A13,'steel Mint data'!A:A,'steel Mint data'!E:E,"",0) -> 40000 | I13: =_xlfn.XLOOKUP(A13,'steel Mint data'!A:A,'steel Mint data'!I:I,"",0) -> 43200 | K13: =_xlfn.XLOOKUP(A13,'steel Mint data'!A:A,'steel Mint data'!L:L,"",0) -> 45600 | P13: =_xlfn.XLOOKUP(A13,'steel Mint data'!A:A,'steel Mint data'!Q:Q,"",0) -> 40000 | Q13: =_xlfn.XLOOKUP(A13,'steel Mint data'!A:A,'steel Mint data'!R:R,"",0) -> 40800
A14: 45881 | B14: =_xlfn.XLOOKUP(A14,'steel Mint data'!A:A,'steel Mint data'!B:B,"",0) -> 44800 | E14: =_xlfn.XLOOKUP(A14,'steel Mint data'!A:A,'steel Mint data'!D:D,"",0) -> 43700 | F14: =_xlfn.XLOOKUP(A14,'steel Mint data'!A:A,'steel Mint data'!E:E,"",0) -> 40000 | I14: =_xlfn.XLOOKUP(A14,'steel Mint data'!A:A,'steel Mint data'!I:I,"",0) -> 43100 | K14: =_xlfn.XLOOKUP(A14,'steel Mint data'!A:A,'steel Mint data'!L:L,"",0) -> 45500 | P14: =_xlfn.XLOOKUP(A14,'steel Mint data'!A:A,'steel Mint data'!Q:Q,"",0) -> 39900 | Q14: =_xlfn.XLOOKUP(A14,'steel Mint data'!A:A,'steel Mint data'!R:R,"",0) -> 40800
... A17: 45884 | B17: =_xlfn.XLOOKUP(A17,'steel Mint data'!A:A,'steel Mint data'!B:B,"",0) -> H | E17: =_xlfn.XLOOKUP(A17,'steel Mint data'!A:A,'steel Mint data'!D:D,"",0) -> H | F17: =_xlfn.XLOOKUP(A17,'steel Mint data'!A:A,'steel Mint data'!E:E,"",0) -> H | I17: =_xlfn.XLOOKUP(A17,'steel Mint data'!A:A,'steel Mint data'!I:I,"",0) -> H | K17: =_xlfn.XLOOKUP(A17,'steel Mint data'!A:A,'steel Mint data'!L:L,"",0) -> H | P17: =_xlfn.XLOOKUP(A17,'steel Mint data'!A:A,'steel Mint data'!Q:Q,"",0) -> H | Q17: =_xlfn.XLOOKUP(A17,'steel Mint data'!A:A,'steel Mint data'!R:R,"",0) -> H
B18: =_xlfn.XLOOKUP(A18,'steel Mint data'!A:A,'steel Mint data'!B:B,"",0) | F18: =_xlfn.XLOOKUP(A18,'steel Mint data'!A:A,'steel Mint data'!E:E,"",0)
B19: =SUM(B3:B18) -> 490400 | E19: =SUM(E3:E18) -> 488200 | F19: =SUM(F3:F18) -> 441700 | I19: =SUM(I3:I18) -> 475550 | K19: =SUM(K3:K18) -> 502000 | P19: =SUM(P3:P18) -> 438300 | Q19: =SUM(Q3:Q18) -> 448700
B20: Amba Shakti (NCR) | C20: API (Raipur) | D20: Aditya Industries (Mandi) | E20: Shree Ganesh (Rourkela) | F20: SKA Raipur | G20: Amba Gwalior | H20: Rajasthan | I20: Gujarat | J20: Durgapur
A21: Avg Price - Divided by no of days steel mint price is available | B21: =E19/O21 -> 44381.818 | C21: =P19/O21 -> 39845.455 | D21: =K19/O21 -> 45636.364 | E21: =Q19/O21 -> 40790.909 | F21: =C21 -> 39845.455 | G21: =B21-800 -> 43581.818 | H21: =I19/O21 -> 43231.818 | I21: =B19/O21 -> 44581.818 | J21: =F19/O21 -> 40154.545 | O21: =COUNT(P3:P18) -> 11
A22: BIS | B22: 1200 | C22: 2150 | D22: 400 | E22: 2200 | F22: 1800 | G22: 1200 | H22: 800 | I22: 0 | J22: 2000
A23: Loading Charges | B23: 200 | C23: 265 | D23: 250 | E23: 275 | F23: 275 | G23: 200 | H23: 270 | I23: 200 | J23: 270 | L23: =45200-3400-F24 -> -120.45455 | M23: =46000-3100-F24 -> 979.54545
A24: Actual PO Price (base dia): A | B24: =SUM(B21:B23) -> 45781.818 | C24: =SUM(C21:C23) -> 42260.455 | D24: =SUM(D21:D23) -> 46286.364 | E24: =SUM(E21:E23) -> 43265.909 | F24: =SUM(F21:F23) -> 41920.455 | G24: =SUM(G21:G23) -> 44981.818 | H24: =SUM(H21:H23) -> 44301.818 | I24: =SUM(I21:I23) -> 44781.818 | J24: =SUM(J21:J23) -> 42424.545 | K24: =B24+800 -> 46581.818 | L24: =45200-3400-F25 -> -475 | M24: =46000-3100-F25 -> 625 | N24: =D24+700 -> 46986.364
A25: Notional PO: B | B25: 46400 | C25: 42615 | D25: 46050 | F25: 42275 | G25: 45300 | I25: 44300 | J25: 42870 | S25: 8 | T25: 10 | U25: 46000 | V25: =U25*T25 -> 460000 | X25: 8 | Y25: 9 | Z25: =Z27+2500 -> 45800 | AA25: =Z25*Y25 -> 412200
A26: Change (A-B) | B26: =B24-B25 -> -618.18182 | C26: =C24-C25 -> -354.54545 | D26: =D24-D25 -> 236.36364 | E26: =E24-E25 -> 43265.909 | F26: =F24-F25 -> -354.54545 | G26: =G24-G25 -> -318.18182 | H26: =H24-H25 -> 44301.818 | I26: =I24-I25 -> 481.81818 | J26: =J24-J25 -> -445.45455 | S26: 10 | T26: 8 | U26: 44000 | V26: =U26*T26 -> 352000 | X26: 10 | Y26: 9 | Z26: =Z27+1000 -> 44300 | AA26: =Z26*Y26 -> 398700
B27: =B25-2500 -> 43900 | G27: =G25-2500 -> 42800 | S27: 12 | T27: 14 | U27: 43000 | V27: =U27*T27 -> 602000 | X27: 12 | Y27: 12 | Z27: 43300 | AA27: =Z27*Y27 -> 519600
A28: Current PL | B28: 48300 | C28: 45550 | D28: 48800 | E28: 45550 | F28: 45550 | G28: 47500 | H28: 47800 | I28: 48300 | O28: =45500-3250-F24 -> 329.54545 | P28: =45500-2000-J24 -> 1075.4545 | U28: total | V28: =SUM(V25:V27) -> 1414000 | Y28: =Y27+Y26+Y25 -> 30 | Z28: total | AA28: =SUM(AA25:AA27) -> 1330500
A29: Current ex plant NR | B29: =B28-500-(200+300+300)-250-400 -> 46350 | C29: =C28-500-(200+300+300)-250-400 -> 43600 | D29: =D28-500-(200+300+300)-250-400 -> 46850 | E29: =E28-500-(200+300+300)-250-400 -> 43600 | F29: =F28-500-(200+300+300)-250-400 -> 43600 | G29: =G28-500-(200+300+300)-250-400 -> 45550 | H29: =H28-500-(200+300+300)-250-400 -> 45850 | I29: =I28-500-(200+300+300)-250-400 -> 46350 | L29: =46300-G24 -> 1318.1818 | Q29: =44750+2750 -> 47500 | U29: gst | V29: =V28*0.18 -> 254520 | Z29: gst | AA29: =AA28*0.18 -> 239490
A30: Current GM: C | B30: =B29-B24 -> 568.18182 | C30: =C29-C24 -> 1339.5455 | D30: =D29-D24 -> 563.63636 | E30: =E29-E24 -> 334.09091 | F30: =F29-F24 -> 1679.5455 | G30: =G29-G24 -> 568.18182 | H30: =H29-H24 -> 1548.1818 | I30: =I29-I24 -> 1568.1818 | L30: =46300-G25 -> 1000 | U30: total | V30: =V28+V29 -> 1668520 | Z30: total | AA30: =AA28+AA29 -> 1569990
D32: =D24+800 -> 47086.364 | H32: 1000 | Y32: =AA30-V30 -> -98530
E33: 1250 | XFD33: Asking Price Deliverd
I34: =F24+500 -> 42420.455 | J34: 750 | K34: =E28-42500 -> 3050 | XFD34: 43500
A35: Plant | B35: Jul H1 notional | J35: 250-500 | M35: =48000-1100-D24-800 -> -186.36364 | XFD35: 44000
A36: Sikandarabad | B36: 46000 | M36: =48000-1100-D25-800 -> 50 | XFD36: 43500
A37: API, Raipur | B37: 42615 | C37: =B37+1250 -> 43865 | R37: Raunak Infra | S37: Approved Qty from SKA Plant | T37: Invoiced qty from Gwalior | U37: Planned to Inoviced from API | XFD37: 44000
A38: SKA, Raipur | B38: 42275 | C38: =B38+1000 -> 43275 | R38: Qty (MT) | S38: 815 | T38: 207 | U38: =S38-T38 -> 608 | XFD38: 43000
A39: Kala Amb | B39: 46450 | C39: =B39+800 -> 47250 | R39: Approval FOR Price | S39: 46000 | T39: 46000 | U39: 46000 | XFD39: 43500
A40: Gwalior | B40: 45200 | C40: =B40+1000 -> 46200 | R40: Freight | S40: 3300 | T40: 1450 | U40: 3350 | XFD40: 44000
A41: Jaipur | B41: 44470 | R41: Grade -550D | S41: 1000 | T41: 1000 | U41: 1250 | XFD41: 45000
A42: Roukeral | B42: 43675 | R42: Ex-works Price | S42: =S39-S40-S41 -> 41700 | T42: =T39-T40-T41 -> 43550 | U42: =U39-U40-U41 -> 41400 | XFD42: 43500
A43: Gujarat | B43: =44500-1000 -> 43500 | C43: =B43+1000 -> 44500 | R43: Adjusted margin as on 4th Aug'25 | S43: =S42-F24 -> -220.45455 | T43: =T42-G24 -> -1431.8182 | U43: =U42-C24 -> -860.45455 | XFD43: 44000
R44: Wt. Margin (Rs/MT) | T44: =SUMPRODUCT(T43:U43,T38:U38)/SUM(T38:U38) -> -1005.5739 | XFD44: 44000
XFD45: 44000
XFD46: 41000

Sheet Aug25 H1 (2)
B1: Fe 500
A2: Region / Date | B2: Ex-Ahmedabad | C2: Ex-Bangalore | D2: Ex-Chennai | E2: Ex-Delhi/NCR | F2: Ex-Durgapur | G2: Ex-Goa | H2: Ex-Hyderabad | I2: Ex-Jaipur | J2: Ex-Jalna | K2: Ex-Mandi Gobindgarh | L2: Ex-Mumbai | M2: Ex-Muzaffarnagar | N2: Ex-Patna | O2: Ex-Raigarh | P2: Ex-Raipur | Q2: Ex-Rourkela
A3: 45870 | B3: =_xlfn.XLOOKUP(A3,'steel Mint data'!A:A,'steel Mint data'!B:B,"",0) -> 44100 | E3: =_xlfn.XLOOKUP(A3,'steel Mint data'!A:A,'steel Mint data'!D:D,"",0) -> 44600 | F3: =_xlfn.XLOOKUP(A3,'steel Mint data'!A:A,'steel Mint data'!E:E,"",0) -> 40300 | I3: =_xlfn.XLOOKUP(A3,'steel Mint data'!A:A,'steel Mint data'!I:I,"",0) -> 43200 | K3: =_xlfn.XLOOKUP(A3,'steel Mint data'!A:A,'steel Mint data'!L:L,"",0) -> 45500 | P3: =_xlfn.XLOOKUP(A3,'steel Mint data'!A:A,'steel Mint data'!Q:Q,"",0) -> 39600 | Q3: =_xlfn.XLOOKUP(A3,'steel Mint data'!A:A,'steel Mint data'!R:R,"",0) -> 40700
A4: 45871 | B4: =_xlfn.XLOOKUP(A4,'steel Mint data'!A:A,'steel Mint data'!B:B,"",0) -> 44100 | E4: =_xlfn.XLOOKUP(A4,'steel Mint data'!A:A,'steel Mint data'!D:D,"",0) -> 44800 | F4: =_xlfn.XLOOKUP(A4,'steel Mint data'!A:A,'steel Mint data'!E:E,"",0) -> 40500 | I4: =_xlfn.XLOOKUP(A4,'steel Mint data'!A:A,'steel Mint data'!I:I,"",0) -> 43400 | K4: =_xlfn.XLOOKUP(A4,'steel Mint data'!A:A,'steel Mint data'!L:L,"",0) -> 45600 | P4: =_xlfn.XLOOKUP(A4,'steel Mint data'!A:A,'steel Mint data'!Q:Q,"",0) -> 39700 | Q4: =_xlfn.XLOOKUP(A4,'steel Mint data'!A:A,'steel Mint data'!R:R,"",0) -> 40800
A5: 45872 | B5: =_xlfn.XLOOKUP(A5,'steel Mint data'!A:A,'steel Mint data'!B:B,"",0) -> H | E5: =_xlfn.XLOOKUP(A5,'steel Mint data'!A:A,'steel Mint data'!D:D,"",0) -> H | F5: =_xlfn.XLOOKUP(A5,'steel Mint data'!A:A,'steel Mint data'!E:E,"",0) -> H | I5: =_xlfn.XLOOKUP(A5,'steel Mint data'!A:A,'steel Mint data'!I:I,"",0) -> H | K5: =_xlfn.XLOOKUP(A5,'steel Mint data'!A:A,'steel Mint data'!L:L,"",0) -> H | P5: =_xlfn.XLOOKUP(A5,'steel Mint data'!A:A,'steel Mint data'!Q:Q,"",0) -> H | Q5: =_xlfn.XLOOKUP(A5,'steel Mint data'!A:A,'steel Mint data'!R:R,"",0) -> H
A6: 45873 | B6: =_xlfn.XLOOKUP(A6,'steel Mint data'!A:A,'steel Mint data'!B:B,"",0) -> 44600 | E6: =_xlfn.XLOOKUP(A6,'steel Mint data'!A:A,'steel Mint data'!D:D,"",0) -> 45000 | F6: =_xlfn.XLOOKUP(A6,'steel Mint data'!A:A,'steel Mint data'!E:E,"",0) -> 40800 | I6: =_xlfn.XLOOKUP(A6,'steel Mint data'!A:A,'steel Mint data'!I:I,"",0) -> 43500 | K6: =_xlfn.XLOOKUP(A6,'steel Mint data'!A:A,'steel Mint data'!L:L,"",0) -> 45800 | P6: =_xlfn.XLOOKUP(A6,'steel Mint data'!A:A,'steel Mint data'!Q:Q,"",0) -> 40300 | Q6: =_xlfn.XLOOKUP(A6,'steel Mint data'!A:A,'steel Mint data'!R:R,"",0) -> 41000
A7: 45874 | B7: =_xlfn.XLOOKUP(A7,'steel Mint data'!A:A,'steel Mint data'!B:B,"",0) -> 44800 | E7: =_xlfn.XLOOKUP(A7,'steel Mint data'!A:A,'steel Mint data'!D:D,"",0) -> 45200 | F7: =_xlfn.XLOOKUP(A7,'steel Mint data'!A:A,'steel Mint data'!E:E,"",0) -> 40500 | I7: =_xlfn.XLOOKUP(A7,'steel Mint data'!A:A,'steel Mint data'!I:I,"",0) -> 43500 | K7: =_xlfn.XLOOKUP(A7,'steel Mint data'!A:A,'steel Mint data'!L:L,"",0) -> 46000 | P7: =_xlfn.XLOOKUP(A7,'steel Mint data'!A:A,'steel Mint data'!Q:Q,"",0) -> 40100 | Q7: =_xlfn.XLOOKUP(A7,'steel Mint data'!A:A,'steel Mint data'!R:R,"",0) -> 41000
A8: 45875 | B8: =_xlfn.XLOOKUP(A8,'steel Mint data'!A:A,'steel Mint data'!B:B,"",0) -> 44800 | E8: =_xlfn.XLOOKUP(A8,'steel Mint data'!A:A,'steel Mint data'!D:D,"",0) -> 44900 | F8: =_xlfn.XLOOKUP(A8,'steel Mint data'!A:A,'steel Mint data'!E:E,"",0) -> 40300 | I8: =_xlfn.XLOOKUP(A8,'steel Mint data'!A:A,'steel Mint data'!I:I,"",0) -> 43300 | K8: =_xlfn.XLOOKUP(A8,'steel Mint data'!A:A,'steel Mint data'!L:L,"",0) -> 45900 | P8: =_xlfn.XLOOKUP(A8,'steel Mint data'!A:A,'steel Mint data'!Q:Q,"",0) -> 39800 | Q8: =_xlfn.XLOOKUP(A8,'steel Mint data'!A:A,'steel Mint data'!R:R,"",0) -> 41000
A9: 45875 | B9: =_xlfn.XLOOKUP(A9,'steel Mint data'!A:A,'steel Mint data'!B:B,"",0) -> 44800 | E9: =_xlfn.XLOOKUP(A9,'steel Mint data'!A:A,'steel Mint data'!D:D,"",0) -> 44900 | F9: =_xlfn.XLOOKUP(A9,'steel Mint data'!A:A,'steel Mint data'!E:E,"",0) -> 40300 | I9: =_xlfn.XLOOKUP(A9,'steel Mint data'!A:A,'steel Mint data'!I:I,"",0) -> 43300 | K9: =_xlfn.XLOOKUP(A9,'steel Mint data'!A:A,'steel Mint data'!L:L,"",0) -> 45900 | P9: =_xlfn.XLOOKUP(A9,'steel Mint data'!A:A,'steel Mint data'!Q:Q,"",0) -> 39800 | Q9: =_xlfn.XLOOKUP(A9,'steel Mint data'!A:A,'steel Mint data'!R:R,"",0) -> 41000
A10: 45875 | B10: =_xlfn.XLOOKUP(A10,'steel Mint data'!A:A,'steel Mint data'!B:B,"",0) -> 44800 | E10: =_xlfn.XLOOKUP(A10,'steel Mint data'!A:A,'steel Mint data'!D:D,"",0) -> 44900 | F10: =_xlfn.XLOOKUP(A10,'steel Mint data'!A:A,'steel Mint data'!E:E,"",0) -> 40300 | I10: =_xlfn.XLOOKUP(A10,'steel Mint data'!A:A,'steel Mint data'!I:I,"",0) -> 43300 | K10: =_xlfn.XLOOKUP(A10,'steel Mint data'!A:A,'steel Mint data'!L:L,"",0) -> 45900 | P10: =_xlfn.XLOOKUP(A10,'steel Mint data'!A:A,'steel Mint data'!Q:Q,"",0) -> 39800 | Q10: =_xlfn.XLOOKUP(A10,'steel Mint data'!A:A,'steel Mint data'!R:R,"",0) -> 41000
A11: 45875 | B11: =_xlfn.XLOOKUP(A11,'steel Mint data'!A:A,'steel Mint data'!B:B,"",0) -> 44800 | E11: =_xlfn.XLOOKUP(A11,'steel Mint data'!A:A,'steel Mint data'!D:D,"",0) -> 44900 | F11: =_xlfn.XLOOKUP(A11,'steel Mint data'!A:A,'steel Mint data'!E:E,"",0) -> 40300 | I11: =_xlfn.XLOOKUP(A11,'steel Mint data'!A:A,'steel Mint data'!I:I,"",0) -> 43300 | K11: =_xlfn.XLOOKUP(A11,'steel Mint data'!A:A,'steel Mint data'!L:L,"",0) -> 45900 | P11: =_xlfn.XLOOKUP(A11,'steel Mint data'!A:A,'steel Mint data'!Q:Q,"",0) -> 39800 | Q11: =_xlfn.XLOOKUP(A11,'steel Mint data'!A:A,'steel Mint data'!R:R,"",0) -> 41000
A12: 45875 | B12: =_xlfn.XLOOKUP(A12,'steel Mint data'!A:A,'steel Mint data'!B:B,"",0) -> 44800 | E12: =_xlfn.XLOOKUP(A12,'steel Mint data'!A:A,'steel Mint data'!D:D,"",0) -> 44900 | F12: =_xlfn.XLOOKUP(A12,'steel Mint data'!A:A,'steel Mint data'!E:E,"",0) -> 40300 | I12: =_xlfn.XLOOKUP(A12,'steel Mint data'!A:A,'steel Mint data'!I:I,"",0) -> 43300 | K12: =_xlfn.XLOOKUP(A12,'steel Mint data'!A:A,'steel Mint data'!L:L,"",0) -> 45900 | P12: =_xlfn.XLOOKUP(A12,'steel Mint data'!A:A,'steel Mint data'!Q:Q,"",0) -> 39800 | Q12: =_xlfn.XLOOKUP(A12,'steel Mint data'!A:A,'steel Mint data'!R:R,"",0) -> 41000
A13: 45875 | B13: =_xlfn.XLOOKUP(A13,'steel Mint data'!A:A,'steel Mint data'!B:B,"",0) -> 44800 | E13: =_xlfn.XLOOKUP(A13,'steel Mint data'!A:A,'steel Mint data'!D:D,"",0) -> 44900 | F13: =_xlfn.XLOOKUP(A13,'steel Mint data'!A:A,'steel Mint data'!E:E,"",0) -> 40300 | I13: =_xlfn.XLOOKUP(A13,'steel Mint data'!A:A,'steel Mint data'!I:I,"",0) -> 43300 | K13: =_xlfn.XLOOKUP(A13,'steel Mint data'!A:A,'steel Mint data'!L:L,"",0) -> 45900 | P13: =_xlfn.XLOOKUP(A13,'steel Mint data'!A:A,'steel Mint data'!Q:Q,"",0) -> 39800 | Q13: =_xlfn.XLOOKUP(A13,'steel Mint data'!A:A,'steel Mint data'!R:R,"",0) -> 41000
A14: 45875 | B14: =_xlfn.XLOOKUP(A14,'steel Mint data'!A:A,'steel Mint data'!B:B,"",0) -> 44800 | E14: =_xlfn.XLOOKUP(A14,'steel Mint data'!A:A,'steel Mint data'!D:D,"",0) -> 44900 | F14: =_xlfn.XLOOKUP(A14,'steel Mint data'!A:A,'steel Mint data'!E:E,"",0) -> 40300 | I14: =_xlfn.XLOOKUP(A14,'steel Mint data'!A:A,'steel Mint data'!I:I,"",0) -> 43300 | K14: =_xlfn.XLOOKUP(A14,'steel Mint data'!A:A,'steel Mint data'!L:L,"",0) -> 45900 | P14: =_xlfn.XLOOKUP(A14,'steel Mint data'!A:A,'steel Mint data'!Q:Q,"",0) -> 39800 | Q14: =_xlfn.XLOOKUP(A14,'steel Mint data'!A:A,'steel Mint data'!R:R,"",0) -> 41000
... A17: 45875 | B17: =_xlfn.XLOOKUP(A17,'steel Mint data'!A:A,'steel Mint data'!B:B,"",0) -> 44800 | E17: =_xlfn.XLOOKUP(A17,'steel Mint data'!A:A,'steel Mint data'!D:D,"",0) -> 44900 | F17: =_xlfn.XLOOKUP(A17,'steel Mint data'!A:A,'steel Mint data'!E:E,"",0) -> 40300 | I17: =_xlfn.XLOOKUP(A17,'steel Mint data'!A:A,'steel Mint data'!I:I,"",0) -> 43300 | K17: =_xlfn.XLOOKUP(A17,'steel Mint data'!A:A,'steel Mint data'!L:L,"",0) -> 45900 | P17: =_xlfn.XLOOKUP(A17,'steel Mint data'!A:A,'steel Mint data'!Q:Q,"",0) -> 39800 | Q17: =_xlfn.XLOOKUP(A17,'steel Mint data'!A:A,'steel Mint data'!R:R,"",0) -> 41000
B18: =_xlfn.XLOOKUP(A18,'steel Mint data'!A:A,'steel Mint data'!B:B,"",0) | F18: =_xlfn.XLOOKUP(A18,'steel Mint data'!A:A,'steel Mint data'!E:E,"",0)
B19: =SUM(B3:B18) -> 625600 | E19: =SUM(E3:E18) -> 628600 | F19: =SUM(F3:F18) -> 565100 | I19: =SUM(I3:I18) -> 606600 | K19: =SUM(K3:K18) -> 641900 | P19: =SUM(P3:P18) -> 557700 | Q19: =SUM(Q3:Q18) -> 573500
B20: Amba Shakti (NCR) | C20: API (Raipur) | D20: Aditya Industries (Mandi) | E20: Shree Ganesh (Rourkela) | F20: SKA Raipur | G20: Amba Gwalior | H20: Rajasthan | I20: Gujarat | J20: Durgapur
A21: Avg Price - Divided by no of days steel mint price is available | B21: =E19/O21 -> 44900 | C21: =P19/O21 -> 39835.714 | D21: =K19/O21 -> 45850 | E21: =Q19/O21 -> 40964.286 | F21: =C21 -> 39835.714 | G21: =B21-800 -> 44100 | H21: =I19/O21 -> 43328.571 | I21: =B19/O21 -> 44685.714 | J21: =F19/O21 -> 40364.286 | O21: =COUNT(P3:P18) -> 14
A22: BIS | B22: 1200 | C22: 2150 | D22: 400 | E22: 2200 | F22: 1800 | G22: 1200 | H22: 800 | I22: 0 | J22: 2000
A23: Loading Charges | B23: 200 | C23: 265 | D23: 250 | E23: 275 | F23: 275 | G23: 200 | H23: 270 | I23: 200 | J23: 270 | K23: =F24+1000+3500 -> 46410.714
A24: Actual PO Price (base dia): A | B24: =SUM(B21:B23) -> 46300 | C24: =SUM(C21:C23) -> 42250.714 | D24: =SUM(D21:D23) -> 46500 | E24: =SUM(E21:E23) -> 43439.286 | F24: =SUM(F21:F23) -> 41910.714 | G24: =SUM(G21:G23) -> 45500 | H24: =SUM(H21:H23) -> 44398.571 | I24: =SUM(I21:I23) -> 44885.714 | J24: =SUM(J21:J23) -> 42634.286
A25: Notional PO: B | B25: 46400 | C25: 42615 | D25: 46050 | F25: 42275 | G25: 45300 | I25: 44300 | J25: 42870
A26: Change (A-B) | B26: =B24-B25 -> -100 | C26: =C24-C25 -> -364.28571 | D26: =D24-D25 -> 450 | E26: =E24-E25 -> 43439.286 | F26: =F24-F25 -> -364.28571 | G26: =G24-G25 -> 200 | H26: =H24-H25 -> 44398.571 | I26: =I24-I25 -> 585.71429 | M26: =45500-3200-1000-C24 -> -950.71429
B27: =B25-2500 -> 43900 | G27: =G25-2500 -> 42800 | L27: =44000-1000-F24 -> 1089.2857
A28: Current PL | B28: 48300 | C28: 45550 | D28: 48800 | E28: 45550 | F28: 45550 | G28: 47500 | H28: 47800 | I28: 48300 | O28: =J24+1250 -> 43884.286
A29: Current ex plant NR | B29: =B28-500-(200+300+300)-250-400 -> 46350 | C29: =C28-500-(200+300+300)-250-400 -> 43600 | D29: =D28-500-(200+300+300)-250-400 -> 46850 | E29: =E28-500-(200+300+300)-250-400 -> 43600 | F29: =F28-500-(200+300+300)-250-400 -> 43600 | G29: =G28-500-(200+300+300)-250-400 -> 45550 | H29: =H28-500-(200+300+300)-250-400 -> 45850 | I29: =I28-500-(200+300+300)-250-400 -> 46350
A30: Current GM: C | B30: =B29-B24 -> 50 | C30: =C29-C24 -> 1349.2857 | D30: =D29-D24 -> 350 | E30: =E29-E24 -> 160.71429 | F30: =F29-F24 -> 1689.2857 | G30: =G29-G24 -> 50 | H30: =H29-H24 -> 1451.4286 | I30: =I29-I24 -> 1464.2857 | M30: =44500-3200-1000-F24 -> -1610.7143
O31: =F24+1000-500+3500 -> 45910.714
B32: =B28-B24-1000 -> 1000 | C32: =C28-C24 -> 3299.2857 | D32: =D28-D24-1000 -> 1300 | E32: =E28-E24-1000 -> 1110.7143 | F32: =F28-F24-1000 -> 2639.2857 | G32: =G28-G24-1000 -> 1000 | H32: =H28-H24-1000 -> 2401.4286 | I32: =I28-I24-1000 -> 2414.2857
F33: =F24+2500-45450 -> -1039.2857 | XFD33: Asking Price Deliverd
XFD34: 43500
A35: Plant | B35: Jul H1 notional | XFD35: 44000
A36: Sikandarabad | B36: 46000 | XFD36: 43500
A37: API, Raipur | B37: 42615 | C37: =B37+1250 -> 43865 | R37: Raunak Infra | S37: Approved Qty from SKA Plant | T37: Invoiced qty from Gwalior | U37: Planned to Inoviced from API | XFD37: 44000
A38: SKA, Raipur | B38: 42275 | C38: =B38+1000 -> 43275 | R38: Qty (MT) | S38: 815 | T38: 207 | U38: =S38-T38 -> 608 | XFD38: 43000
A39: Kala Amb | B39: 46450 | C39: =B39+800 -> 47250 | L39: 207 | M39: =815-L39 -> 608 | R39: Approval FOR Price | S39: 46000 | T39: 46000 | U39: 46000 | XFD39: 43500
A40: Gwalior | B40: 45200 | C40: =B40+1000 -> 46200 | L40: =46000-1450-1000-G24 -> -1950 | M40: =46000-3350-1000-F24 -> -260.71429 | N40: =SUMPRODUCT(L40:M40,L39:M39)/SUM(L39:M39) -> -689.77213 | R40: Freight | S40: 3300 | T40: 1450 | U40: 3350 | XFD40: 44000
A41: Jaipur | B41: 44470 | R41: Grade -550D | S41: 1000 | T41: 1000 | U41: 1250 | XFD41: 45000
A42: Roukeral | B42: 43675 | R42: Ex-works Price | S42: =S39-S40-S41 -> 41700 | T42: =T39-T40-T41 -> 43550 | U42: =U39-U40-U41 -> 41400 | XFD42: 43500
A43: Gujarat | B43: =44500-1000 -> 43500 | C43: =B43+1000 -> 44500 | R43: Adjusted margin as on 4th Aug'25 | S43: =S42-F24 -> -210.71429 | T43: =T42-G24 -> -1950 | U43: =U42-C24 -> -850.71429 | XFD43: 44000
R44: Wt. Margin (Rs/MT) | T44: =SUMPRODUCT(T43:U43,T38:U38)/SUM(T38:U38) -> -1129.9194 | XFD44: 44000
XFD45: 44000
XFD46: 41000

Sheet Aug25 H2
B1: Fe 500
A2: Region / Date | B2: Ex-Ahmedabad | C2: Ex-Bangalore | D2: Ex-Chennai | E2: Ex-Delhi/NCR | F2: Ex-Durgapur | G2: Ex-Goa | H2: Ex-Hyderabad | I2: Ex-Jaipur | J2: Ex-Jalna | K2: Ex-Mandi Gobindgarh | L2: Ex-Mumbai | M2: Ex-Muzaffarnagar | N2: Ex-Patna | O2: Ex-Raigarh | P2: Ex-Raipur | Q2: Ex-Rourkela
A3: 45885 | B3: =_xlfn.XLOOKUP(A3,'steel Mint data'!A:A,'steel Mint data'!B:B,"",0) -> H | E3: =_xlfn.XLOOKUP(A3,'steel Mint data'!A:A,'steel Mint data'!D:D,"",0) -> H | F3: =_xlfn.XLOOKUP(A3,'steel Mint data'!A:A,'steel Mint data'!E:E,"",0) -> H | I3: =_xlfn.XLOOKUP(A3,'steel Mint data'!A:A,'steel Mint data'!I:I,"",0) -> H | K3: =_xlfn.XLOOKUP(A3,'steel Mint data'!A:A,'steel Mint data'!L:L,"",0) -> H | P3: =_xlfn.XLOOKUP(A3,'steel Mint data'!A:A,'steel Mint data'!Q:Q,"",0) -> H | Q3: =_xlfn.XLOOKUP(A3,'steel Mint data'!A:A,'steel Mint data'!R:R,"",0) -> H
A4: 45886 | B4: =_xlfn.XLOOKUP(A4,'steel Mint data'!A:A,'steel Mint data'!B:B,"",0) -> H | E4: =_xlfn.XLOOKUP(A4,'steel Mint data'!A:A,'steel Mint data'!D:D,"",0) -> H | F4: =_xlfn.XLOOKUP(A4,'steel Mint data'!A:A,'steel Mint data'!E:E,"",0) -> H | I4: =_xlfn.XLOOKUP(A4,'steel Mint data'!A:A,'steel Mint data'!I:I,"",0) -> H | K4: =_xlfn.XLOOKUP(A4,'steel Mint data'!A:A,'steel Mint data'!L:L,"",0) -> H | P4: =_xlfn.XLOOKUP(A4,'steel Mint data'!A:A,'steel Mint data'!Q:Q,"",0) -> H | Q4: =_xlfn.XLOOKUP(A4,'steel Mint data'!A:A,'steel Mint data'!R:R,"",0) -> H
A5: 45887 | B5: =_xlfn.XLOOKUP(A5,'steel Mint data'!A:A,'steel Mint data'!B:B,"",0) -> 44500 | E5: =_xlfn.XLOOKUP(A5,'steel Mint data'!A:A,'steel Mint data'!D:D,"",0) -> 43400 | F5: =_xlfn.XLOOKUP(A5,'steel Mint data'!A:A,'steel Mint data'!E:E,"",0) -> 39800 | I5: =_xlfn.XLOOKUP(A5,'steel Mint data'!A:A,'steel Mint data'!I:I,"",0) -> 43000 | K5: =_xlfn.XLOOKUP(A5,'steel Mint data'!A:A,'steel Mint data'!L:L,"",0) -> 45400 | P5: =_xlfn.XLOOKUP(A5,'steel Mint data'!A:A,'steel Mint data'!Q:Q,"",0) -> 40000 | Q5: =_xlfn.XLOOKUP(A5,'steel Mint data'!A:A,'steel Mint data'!R:R,"",0) -> 40300
A6: 45888 | B6: =_xlfn.XLOOKUP(A6,'steel Mint data'!A:A,'steel Mint data'!B:B,"",0) -> 44700 | E6: =_xlfn.XLOOKUP(A6,'steel Mint data'!A:A,'steel Mint data'!D:D,"",0) -> 43600 | F6: =_xlfn.XLOOKUP(A6,'steel Mint data'!A:A,'steel Mint data'!E:E,"",0) -> 39800 | I6: =_xlfn.XLOOKUP(A6,'steel Mint data'!A:A,'steel Mint data'!I:I,"",0) -> 43100 | K6: =_xlfn.XLOOKUP(A6,'steel Mint data'!A:A,'steel Mint data'!L:L,"",0) -> 45500 | P6: =_xlfn.XLOOKUP(A6,'steel Mint data'!A:A,'steel Mint data'!Q:Q,"",0) -> 40300 | Q6: =_xlfn.XLOOKUP(A6,'steel Mint data'!A:A,'steel Mint data'!R:R,"",0) -> 40500
A7: 45889 | B7: =_xlfn.XLOOKUP(A7,'steel Mint data'!A:A,'steel Mint data'!B:B,"",0) -> 44700 | E7: =_xlfn.XLOOKUP(A7,'steel Mint data'!A:A,'steel Mint data'!D:D,"",0) -> 43500 | F7: =_xlfn.XLOOKUP(A7,'steel Mint data'!A:A,'steel Mint data'!E:E,"",0) -> 39700 | I7: =_xlfn.XLOOKUP(A7,'steel Mint data'!A:A,'steel Mint data'!I:I,"",0) -> 43100 | K7: =_xlfn.XLOOKUP(A7,'steel Mint data'!A:A,'steel Mint data'!L:L,"",0) -> 45500 | P7: =_xlfn.XLOOKUP(A7,'steel Mint data'!A:A,'steel Mint data'!Q:Q,"",0) -> 40300 | Q7: =_xlfn.XLOOKUP(A7,'steel Mint data'!A:A,'steel Mint data'!R:R,"",0) -> 40500
A8: 45890 | B8: =_xlfn.XLOOKUP(A8,'steel Mint data'!A:A,'steel Mint data'!B:B,"",0) -> 44500 | E8: =_xlfn.XLOOKUP(A8,'steel Mint data'!A:A,'steel Mint data'!D:D,"",0) -> 43300 | F8: =_xlfn.XLOOKUP(A8,'steel Mint data'!A:A,'steel Mint data'!E:E,"",0) -> 39800 | I8: =_xlfn.XLOOKUP(A8,'steel Mint data'!A:A,'steel Mint data'!I:I,"",0) -> 42800 | K8: =_xlfn.XLOOKUP(A8,'steel Mint data'!A:A,'steel Mint data'!L:L,"",0) -> 45300 | P8: =_xlfn.XLOOKUP(A8,'steel Mint data'!A:A,'steel Mint data'!Q:Q,"",0) -> 40200 | Q8: =_xlfn.XLOOKUP(A8,'steel Mint data'!A:A,'steel Mint data'!R:R,"",0) -> 40400
A9: 45891 | B9: =_xlfn.XLOOKUP(A9,'steel Mint data'!A:A,'steel Mint data'!B:B,"",0) -> 44300 | E9: =_xlfn.XLOOKUP(A9,'steel Mint data'!A:A,'steel Mint data'!D:D,"",0) -> 43000 | F9: =_xlfn.XLOOKUP(A9,'steel Mint data'!A:A,'steel Mint data'!E:E,"",0) -> 39700 | I9: =_xlfn.XLOOKUP(A9,'steel Mint data'!A:A,'steel Mint data'!I:I,"",0) -> 42700 | K9: =_xlfn.XLOOKUP(A9,'steel Mint data'!A:A,'steel Mint data'!L:L,"",0) -> 45200 | P9: =_xlfn.XLOOKUP(A9,'steel Mint data'!A:A,'steel Mint data'!Q:Q,"",0) -> 39900 | Q9: =_xlfn.XLOOKUP(A9,'steel Mint data'!A:A,'steel Mint data'!R:R,"",0) -> 40300
A10: 45892 | B10: =_xlfn.XLOOKUP(A10,'steel Mint data'!A:A,'steel Mint data'!B:B,"",0) -> 44300 | E10: =_xlfn.XLOOKUP(A10,'steel Mint data'!A:A,'steel Mint data'!D:D,"",0) -> 42900 | F10: =_xlfn.XLOOKUP(A10,'steel Mint data'!A:A,'steel Mint data'!E:E,"",0) -> 39700 | I10: =_xlfn.XLOOKUP(A10,'steel Mint data'!A:A,'steel Mint data'!I:I,"",0) -> 42700 | K10: =_xlfn.XLOOKUP(A10,'steel Mint data'!A:A,'steel Mint data'!L:L,"",0) -> 45100 | P10: =_xlfn.XLOOKUP(A10,'steel Mint data'!A:A,'steel Mint data'!Q:Q,"",0) -> 39900 | Q10: =_xlfn.XLOOKUP(A10,'steel Mint data'!A:A,'steel Mint data'!R:R,"",0) -> 40200
A11: 45893 | B11: =_xlfn.XLOOKUP(A11,'steel Mint data'!A:A,'steel Mint data'!B:B,"",0) -> H | E11: =_xlfn.XLOOKUP(A11,'steel Mint data'!A:A,'steel Mint data'!D:D,"",0) -> H | F11: =_xlfn.XLOOKUP(A11,'steel Mint data'!A:A,'steel Mint data'!E:E,"",0) -> H | I11: =_xlfn.XLOOKUP(A11,'steel Mint data'!A:A,'steel Mint data'!I:I,"",0) -> H | K11: =_xlfn.XLOOKUP(A11,'steel Mint data'!A:A,'steel Mint data'!L:L,"",0) -> H | P11: =_xlfn.XLOOKUP(A11,'steel Mint data'!A:A,'steel Mint data'!Q:Q,"",0) -> H | Q11: =_xlfn.XLOOKUP(A11,'steel Mint data'!A:A,'steel Mint data'!R:R,"",0) -> H
A12: 45894 | B12: =_xlfn.XLOOKUP(A12,'steel Mint data'!A:A,'steel Mint data'!B:B,"",0) -> 44000 | E12: =_xlfn.XLOOKUP(A12,'steel Mint data'!A:A,'steel Mint data'!D:D,"",0) -> 42700 | F12: =_xlfn.XLOOKUP(A12,'steel Mint data'!A:A,'steel Mint data'!E:E,"",0) -> 39400 | I12: =_xlfn.XLOOKUP(A12,'steel Mint data'!A:A,'steel Mint data'!I:I,"",0) -> 42600 | K12: =_xlfn.XLOOKUP(A12,'steel Mint data'!A:A,'steel Mint data'!L:L,"",0) -> 45000 | P12: =_xlfn.XLOOKUP(A12,'steel Mint data'!A:A,'steel Mint data'!Q:Q,"",0) -> 39600 | Q12: =_xlfn.XLOOKUP(A12,'steel Mint data'!A:A,'steel Mint data'!R:R,"",0) -> 40000
A13: 45895 | B13: =_xlfn.XLOOKUP(A13,'steel Mint data'!A:A,'steel Mint data'!B:B,"",0) -> 43800 | E13: =_xlfn.XLOOKUP(A13,'steel Mint data'!A:A,'steel Mint data'!D:D,"",0) -> 42500 | F13: =_xlfn.XLOOKUP(A13,'steel Mint data'!A:A,'steel Mint data'!E:E,"",0) -> 39300 | I13: =_xlfn.XLOOKUP(A13,'steel Mint data'!A:A,'steel Mint data'!I:I,"",0) -> 42200 | K13: =_xlfn.XLOOKUP(A13,'steel Mint data'!A:A,'steel Mint data'!L:L,"",0) -> 44800 | P13: =_xlfn.XLOOKUP(A13,'steel Mint data'!A:A,'steel Mint data'!Q:Q,"",0) -> 39400 | Q13: =_xlfn.XLOOKUP(A13,'steel Mint data'!A:A,'steel Mint data'!R:R,"",0) -> 39800
A14: 45896 | B14: =_xlfn.XLOOKUP(A14,'steel Mint data'!A:A,'steel Mint data'!B:B,"",0) -> 43800 | E14: =_xlfn.XLOOKUP(A14,'steel Mint data'!A:A,'steel Mint data'!D:D,"",0) -> 42500 | F14: =_xlfn.XLOOKUP(A14,'steel Mint data'!A:A,'steel Mint data'!E:E,"",0) -> 39200 | I14: =_xlfn.XLOOKUP(A14,'steel Mint data'!A:A,'steel Mint data'!I:I,"",0) -> 42200 | K14: =_xlfn.XLOOKUP(A14,'steel Mint data'!A:A,'steel Mint data'!L:L,"",0) -> 44500 | P14: =_xlfn.XLOOKUP(A14,'steel Mint data'!A:A,'steel Mint data'!Q:Q,"",0) -> 39500 | Q14: =_xlfn.XLOOKUP(A14,'steel Mint data'!A:A,'steel Mint data'!R:R,"",0) -> 39800
... A18: 45900 | B18: =_xlfn.XLOOKUP(A18,'steel Mint data'!A:A,'steel Mint data'!B:B,"",0) -> H | E18: =_xlfn.XLOOKUP(A18,'steel Mint data'!A:A,'steel Mint data'!D:D,"",0) -> H | F18: =_xlfn.XLOOKUP(A18,'steel Mint data'!A:A,'steel Mint data'!E:E,"",0) -> H | I18: =_xlfn.XLOOKUP(A18,'steel Mint data'!A:A,'steel Mint data'!I:I,"",0) -> H | K18: =_xlfn.XLOOKUP(A18,'steel Mint data'!A:A,'steel Mint data'!L:L,"",0) -> H | P18: =_xlfn.XLOOKUP(A18,'steel Mint data'!A:A,'steel Mint data'!Q:Q,"",0) -> H | Q18: =_xlfn.XLOOKUP(A18,'steel Mint data'!A:A,'steel Mint data'!R:R,"",0) -> H
B19: =SUM(B3:B18) -> 529600 | E19: =SUM(E3:E18) -> 514400 | F19: =SUM(F3:F18) -> 473500 | I19: =SUM(I3:I18) -> 510400 | K19: =SUM(K3:K18) -> 539500 | P19: =SUM(P3:P18) -> 477600 | Q19: =SUM(Q3:Q18) -> 481000
B20: Amba Shakti (NCR) | C20: API (Raipur) | D20: Aditya Industries (Mandi) | E20: Shree Ganesh (Rourkela) | F20: SKA Raipur | G20: Amba Gwalior | H20: Rajasthan | I20: Gujarat | J20: Bardhman | L20: =F24+2200 -> 44075 | M20: =44000-2200 -> 41800 | N20: =M20-F24 -> -75
A21: Avg Price - Divided by no of days steel mint price is available | B21: =E19/O21 -> 42866.667 | C21: =P19/O21 -> 39800 | D21: =K19/O21 -> 44958.333 | E21: =Q19/O21 -> 40083.333 | F21: =C21 -> 39800 | G21: =B21-800 -> 42066.667 | H21: =I19/O21 -> 42533.333 | I21: =B19/O21 -> 44133.333 | J21: =F19/O21 -> 39458.333 | O21: =COUNT(P3:P18) -> 12
A22: BIS | B22: 1200 | C22: 2150 | D22: 400 | E22: 2200 | F22: 1800 | G22: 1200 | H22: 800 | I22: 0 | J22: 2000
A23: Loading Charges | B23: 200 | C23: 265 | D23: 250 | E23: 275 | F23: 275 | G23: 200 | H23: 270 | I23: 200 | J23: 270 | R23: 3550 | S23: alwar
A24: Actual PO Price (base dia): A | B24: =SUM(B21:B23) -> 44266.667 | C24: =SUM(C21:C23) -> 42215 | D24: =SUM(D21:D23) -> 45608.333 | E24: =SUM(E21:E23) -> 42558.333 | F24: =SUM(F21:F23) -> 41875 | G24: =SUM(G21:G23) -> 43466.667 | H24: =SUM(H21:H23) -> 43603.333 | I24: =SUM(I21:I23) -> 44333.333 | J24: =SUM(J21:J23) -> 41728.333 | K24: =G24-F24 -> 1591.6667 | M24: =46000-3400-1000-F24 -> -275 | S24: =45000-3450-1000-F24 -> -1325
A25: Notional PO: B | B25: 45100 | C25: 42315 | D25: 46150 | F25: 41975 | G25: 44300 | I25: 44300 | J25: 42470 | L25: =F24+1000+2500+500 -> 45875 | M25: =46000-3400-1000-F25 -> -375 | O25: =45500-3400 -> 42100 | P25: =45500-3400-F24 -> 225 | S25: =45000-3450-1000-F25 -> -1425
A26: Change (A-B) | B26: =B24-B25 -> -833.33333 | C26: =C24-C25 -> -100 | D26: =D24-D25 -> -541.66667 | E26: =E24-E25 -> 42558.333 | F26: =F24-F25 -> -100 | G26: =G24-G25 -> -833.33333 | H26: =H24-H25 -> 43603.333 | I26: =I24-I25 -> 33.333333 | J26: =J24-J25 -> -741.66667
B27: =B25-2500 -> 42600 | G27: =G25-2500 -> 41800
A28: Current PL | B28: 48300 | C28: 45550 | D28: 48800 | E28: 45550 | F28: 45550 | G28: 47500 | H28: 47800 | I28: 48300
A29: Current ex plant NR | B29: =B28-500-(200+300+300)-250-400 -> 46350 | C29: =C28-500-(200+300+300)-250-400 -> 43600 | D29: =D28-500-(200+300+300)-250-400 -> 46850 | E29: =E28-500-(200+300+300)-250-400 -> 43600 | F29: =F28-500-(200+300+300)-250-400 -> 43600 | G29: =G28-500-(200+300+300)-250-400 -> 45550 | H29: =H28-500-(200+300+300)-250-400 -> 45850 | I29: =I28-500-(200+300+300)-250-400 -> 46350
A30: Current GM: C | B30: =B29-B24 -> 2083.3333 | C30: =C29-C24 -> 1385 | D30: =D29-D24 -> 1241.6667 | E30: =E29-E24 -> 1041.6667 | F30: =F29-F24 -> 1725 | G30: =G29-G24 -> 2083.3333 | H30: =H29-H24 -> 2246.6667 | I30: =I29-I24 -> 2016.6667
D32: =D24+800 -> 46408.333 | E32: =46000-D24-750 -> -358.33333
D33: =D24+800 -> 46408.333 | F33: =42500-F24 -> 625 | G33: =C24+750 -> 42965 | H33: 500 | I33: =C28-G33 -> 2585 | J33: >500 | XFD33: Asking Price Deliverd
J34: 250-500 | M34: 500 | XFD34: 43500
A35: Plant | B35: Jul H1 notional | J35: 100-250 | XFD35: 44000
A36: Sikandarabad | B36: 46000 | G36: Alwar | H36: Badayun | J36: <100 | K36: 1500 | XFD36: 43500
A37: API, Raipur | B37: 42615 | C37: =B37+1250 -> 43865 | F37: Gwalior 550D | G37: =G24+1000 -> 44466.667 | H37: =G37 -> 44466.667 | R37: Raunak Infra | S37: Approved Qty from SKA Plant | T37: Invoiced qty from Gwalior | U37: Planned to Inoviced from API | XFD37: 44000
A38: SKA, Raipur | B38: 42275 | C38: =B38+1000 -> 43275 | F38: Freight | G38: 1000 | H38: 1400 | R38: Qty (MT) | S38: 815 | T38: 207 | U38: =S38-T38 -> 608 | XFD38: 43000
A39: Kala Amb | B39: 46450 | C39: =B39+800 -> 47250 | G39: =G37+G38 -> 45466.667 | H39: =H37+H38 -> 45866.667 | R39: Approval FOR Price | S39: 46000 | T39: 46000 | U39: 46000 | XFD39: 43500
A40: Gwalior | B40: 45200 | C40: =B40+1000 -> 46200 | F40: Target price | G40: =45400 -> 45400 | H40: =45400 -> 45400 | R40: Freight | S40: 3300 | T40: 1450 | U40: 3350 | XFD40: 44000
A41: Jaipur | B41: 44470 | F41: NEt loss | G41: =G39-G40 -> 66.666667 | H41: =H39-H40 -> 466.66667 | I41: =SUMPRODUCT(G41:H41,G42:H42)/I42 -> 306.66667 | R41: Grade -550D | S41: 1000 | T41: 1000 | U41: 1250 | XFD41: 45000
A42: Roukeral | B42: 43675 | F42: Tonnage | G42: 800 | H42: 1200 | I42: =SUM(G42:H42) -> 2000 | R42: Ex-works Price | S42: =S39-S40-S41 -> 41700 | T42: =T39-T40-T41 -> 43550 | U42: =U39-U40-U41 -> 41400 | XFD42: 43500
A43: Gujarat | B43: =44500-1000 -> 43500 | C43: =B43+1000 -> 44500 | M43: 12m | N43: Neo | O43: pricing | R43: Adjusted margin as on 4th Aug'25 | S43: =S42-F24 -> -175 | T43: =T42-G24 -> 83.333333 | U43: =U42-C24 -> -815 | XFD43: 44000
R44: Wt. Margin (Rs/MT) | T44: =SUMPRODUCT(T43:U43,T38:U38)/SUM(T38:U38) -> -586.83436 | XFD44: 44000
H45: 500 | XFD45: 44000
XFD46: 41000

Sheet Sept H1
B1: Fe 500
A2: Region / Date | B2: Ex-Ahmedabad | C2: Ex-Bangalore | D2: Ex-Chennai | E2: Ex-Delhi/NCR | F2: Ex-Durgapur | G2: Ex-Goa | H2: Ex-Hyderabad | I2: Ex-Jaipur | J2: Ex-Jalna | K2: Ex-Mandi Gobindgarh | L2: Ex-Mumbai | M2: Ex-Muzaffarnagar | N2: Ex-Patna | O2: Ex-Raigarh | P2: Ex-Raipur | Q2: Ex-Rourkela
A3: 45901 | B3: =_xlfn.XLOOKUP(A3,'steel Mint data'!A:A,'steel Mint data'!B:B,"",0) -> 43500 | E3: =_xlfn.XLOOKUP(A3,'steel Mint data'!A:A,'steel Mint data'!D:D,"",0) -> 42100 | F3: =_xlfn.XLOOKUP(A3,'steel Mint data'!A:A,'steel Mint data'!E:E,"",0) -> 38900 | I3: =_xlfn.XLOOKUP(A3,'steel Mint data'!A:A,'steel Mint data'!I:I,"",0) -> 41800 | K3: =_xlfn.XLOOKUP(A3,'steel Mint data'!A:A,'steel Mint data'!L:L,"",0) -> 44100 | P3: =_xlfn.XLOOKUP(A3,'steel Mint data'!A:A,'steel Mint data'!Q:Q,"",0) -> 39600 | Q3: =_xlfn.XLOOKUP(A3,'steel Mint data'!A:A,'steel Mint data'!R:R,"",0) -> 39700
A4: 45902 | B4: =_xlfn.XLOOKUP(A4,'steel Mint data'!A:A,'steel Mint data'!B:B,"",0) -> 43400 | E4: =_xlfn.XLOOKUP(A4,'steel Mint data'!A:A,'steel Mint data'!D:D,"",0) -> 41900 | F4: =_xlfn.XLOOKUP(A4,'steel Mint data'!A:A,'steel Mint data'!E:E,"",0) -> 38800 | I4: =_xlfn.XLOOKUP(A4,'steel Mint data'!A:A,'steel Mint data'!I:I,"",0) -> 41500 | K4: =_xlfn.XLOOKUP(A4,'steel Mint data'!A:A,'steel Mint data'!L:L,"",0) -> 43900 | P4: =_xlfn.XLOOKUP(A4,'steel Mint data'!A:A,'steel Mint data'!Q:Q,"",0) -> 39400 | Q4: =_xlfn.XLOOKUP(A4,'steel Mint data'!A:A,'steel Mint data'!R:R,"",0) -> 39700
A5: 45903 | B5: =_xlfn.XLOOKUP(A5,'steel Mint data'!A:A,'steel Mint data'!B:B,"",0) -> 43200 | E5: =_xlfn.XLOOKUP(A5,'steel Mint data'!A:A,'steel Mint data'!D:D,"",0) -> 41500 | F5: =_xlfn.XLOOKUP(A5,'steel Mint data'!A:A,'steel Mint data'!E:E,"",0) -> 38700 | I5: =_xlfn.XLOOKUP(A5,'steel Mint data'!A:A,'steel Mint data'!I:I,"",0) -> 41300 | K5: =_xlfn.XLOOKUP(A5,'steel Mint data'!A:A,'steel Mint data'!L:L,"",0) -> 43700 | P5: =_xlfn.XLOOKUP(A5,'steel Mint data'!A:A,'steel Mint data'!Q:Q,"",0) -> 39300 | Q5: =_xlfn.XLOOKUP(A5,'steel Mint data'!A:A,'steel Mint data'!R:R,"",0) -> 39500
A6: 45904 | B6: =_xlfn.XLOOKUP(A6,'steel Mint data'!A:A,'steel Mint data'!B:B,"",0) -> 43400 | E6: =_xlfn.XLOOKUP(A6,'steel Mint data'!A:A,'steel Mint data'!D:D,"",0) -> 41500 | F6: =_xlfn.XLOOKUP(A6,'steel Mint data'!A:A,'steel Mint data'!E:E,"",0) -> 39100 | I6: =_xlfn.XLOOKUP(A6,'steel Mint data'!A:A,'steel Mint data'!I:I,"",0) -> 41600 | K6: =_xlfn.XLOOKUP(A6,'steel Mint data'!A:A,'steel Mint data'!L:L,"",0) -> 43800 | P6: =_xlfn.XLOOKUP(A6,'steel Mint data'!A:A,'steel Mint data'!Q:Q,"",0) -> 39400 | Q6: =_xlfn.XLOOKUP(A6,'steel Mint data'!A:A,'steel Mint data'!R:R,"",0) -> 39700
A7: 45905 | B7: =_xlfn.XLOOKUP(A7,'steel Mint data'!A:A,'steel Mint data'!B:B,"",0) -> 43500 | E7: =_xlfn.XLOOKUP(A7,'steel Mint data'!A:A,'steel Mint data'!D:D,"",0) -> 42000 | F7: =_xlfn.XLOOKUP(A7,'steel Mint data'!A:A,'steel Mint data'!E:E,"",0) -> 39100 | I7: =_xlfn.XLOOKUP(A7,'steel Mint data'!A:A,'steel Mint data'!I:I,"",0) -> 42000 | K7: =_xlfn.XLOOKUP(A7,'steel Mint data'!A:A,'steel Mint data'!L:L,"",0) -> 43600 | P7: =_xlfn.XLOOKUP(A7,'steel Mint data'!A:A,'steel Mint data'!Q:Q,"",0) -> 39500 | Q7: =_xlfn.XLOOKUP(A7,'steel Mint data'!A:A,'steel Mint data'!R:R,"",0) -> 39700
A8: 45906 | B8: =_xlfn.XLOOKUP(A8,'steel Mint data'!A:A,'steel Mint data'!B:B,"",0) -> 43500 | E8: =_xlfn.XLOOKUP(A8,'steel Mint data'!A:A,'steel Mint data'!D:D,"",0) -> 42000 | F8: =_xlfn.XLOOKUP(A8,'steel Mint data'!A:A,'steel Mint data'!E:E,"",0) -> 39300 | I8: =_xlfn.XLOOKUP(A8,'steel Mint data'!A:A,'steel Mint data'!I:I,"",0) -> 42200 | K8: =_xlfn.XLOOKUP(A8,'steel Mint data'!A:A,'steel Mint data'!L:L,"",0) -> 44000 | P8: =_xlfn.XLOOKUP(A8,'steel Mint data'!A:A,'steel Mint data'!Q:Q,"",0) -> 39700 | Q8: =_xlfn.XLOOKUP(A8,'steel Mint data'!A:A,'steel Mint data'!R:R,"",0) -> 39700
A9: 45907 | B9: =_xlfn.XLOOKUP(A9,'steel Mint data'!A:A,'steel Mint data'!B:B,"",0) -> H | E9: =_xlfn.XLOOKUP(A9,'steel Mint data'!A:A,'steel Mint data'!D:D,"",0) -> H | F9: =_xlfn.XLOOKUP(A9,'steel Mint data'!A:A,'steel Mint data'!E:E,"",0) -> H | I9: =_xlfn.XLOOKUP(A9,'steel Mint data'!A:A,'steel Mint data'!I:I,"",0) -> H | K9: =_xlfn.XLOOKUP(A9,'steel Mint data'!A:A,'steel Mint data'!L:L,"",0) -> H | P9: =_xlfn.XLOOKUP(A9,'steel Mint data'!A:A,'steel Mint data'!Q:Q,"",0) -> H | Q9: =_xlfn.XLOOKUP(A9,'steel Mint data'!A:A,'steel Mint data'!R:R,"",0) -> H
A10: 45908 | B10: =_xlfn.XLOOKUP(A10,'steel Mint data'!A:A,'steel Mint data'!B:B,"",0) -> 43800 | E10: =_xlfn.XLOOKUP(A10,'steel Mint data'!A:A,'steel Mint data'!D:D,"",0) -> 42800 | F10: =_xlfn.XLOOKUP(A10,'steel Mint data'!A:A,'steel Mint data'!E:E,"",0) -> 39550 | I10: =_xlfn.XLOOKUP(A10,'steel Mint data'!A:A,'steel Mint data'!I:I,"",0) -> 42700 | K10: =_xlfn.XLOOKUP(A10,'steel Mint data'!A:A,'steel Mint data'!L:L,"",0) -> 44200 | P10: =_xlfn.XLOOKUP(A10,'steel Mint data'!A:A,'steel Mint data'!Q:Q,"",0) -> 40000 | Q10: =_xlfn.XLOOKUP(A10,'steel Mint data'!A:A,'steel Mint data'!R:R,"",0) -> 39900
A11: 45909 | B11: =_xlfn.XLOOKUP(A11,'steel Mint data'!A:A,'steel Mint data'!B:B,"",0) -> 43800 | E11: =_xlfn.XLOOKUP(A11,'steel Mint data'!A:A,'steel Mint data'!D:D,"",0) -> 43500 | F11: =_xlfn.XLOOKUP(A11,'steel Mint data'!A:A,'steel Mint data'!E:E,"",0) -> 39450 | I11: =_xlfn.XLOOKUP(A11,'steel Mint data'!A:A,'steel Mint data'!I:I,"",0) -> 42400 | K11: =_xlfn.XLOOKUP(A11,'steel Mint data'!A:A,'steel Mint data'!L:L,"",0) -> 44400 | P11: =_xlfn.XLOOKUP(A11,'steel Mint data'!A:A,'steel Mint data'!Q:Q,"",0) -> 40200 | Q11: =_xlfn.XLOOKUP(A11,'steel Mint data'!A:A,'steel Mint data'!R:R,"",0) -> 40100 | R11: `
A12: 45910 | B12: =_xlfn.XLOOKUP(A12,'steel Mint data'!A:A,'steel Mint data'!B:B,"",0) -> 43800 | E12: =_xlfn.XLOOKUP(A12,'steel Mint data'!A:A,'steel Mint data'!D:D,"",0) -> 43200 | F12: =_xlfn.XLOOKUP(A12,'steel Mint data'!A:A,'steel Mint data'!E:E,"",0) -> 39300 | I12: =_xlfn.XLOOKUP(A12,'steel Mint data'!A:A,'steel Mint data'!I:I,"",0) -> 42200 | K12: =_xlfn.XLOOKUP(A12,'steel Mint data'!A:A,'steel Mint data'!L:L,"",0) -> 44400 | P12: =_xlfn.XLOOKUP(A12,'steel Mint data'!A:A,'steel Mint data'!Q:Q,"",0) -> 39900 | Q12: =_xlfn.XLOOKUP(A12,'steel Mint data'!A:A,'steel Mint data'!R:R,"",0) -> 40100
A13: 45911 | B13: =_xlfn.XLOOKUP(A13,'steel Mint data'!A:A,'steel Mint data'!B:B,"",0) -> 43600 | E13: =_xlfn.XLOOKUP(A13,'steel Mint data'!A:A,'steel Mint data'!D:D,"",0) -> 42800 | F13: =_xlfn.XLOOKUP(A13,'steel Mint data'!A:A,'steel Mint data'!E:E,"",0) -> 39200 | I13: =_xlfn.XLOOKUP(A13,'steel Mint data'!A:A,'steel Mint data'!I:I,"",0) -> 42000 | K13: =_xlfn.XLOOKUP(A13,'steel Mint data'!A:A,'steel Mint data'!L:L,"",0) -> 44200 | P13: =_xlfn.XLOOKUP(A13,'steel Mint data'!A:A,'steel Mint data'!Q:Q,"",0) -> 39700 | Q13: =_xlfn.XLOOKUP(A13,'steel Mint data'!A:A,'steel Mint data'!R:R,"",0) -> 39900
A14: 45912 | B14: =_xlfn.XLOOKUP(A14,'steel Mint data'!A:A,'steel Mint data'!B:B,"",0) -> 43500 | E14: =_xlfn.XLOOKUP(A14,'steel Mint data'!A:A,'steel Mint data'!D:D,"",0) -> 42500 | F14: =_xlfn.XLOOKUP(A14,'steel Mint data'!A:A,'steel Mint data'!E:E,"",0) -> 39200 | I14: =_xlfn.XLOOKUP(A14,'steel Mint data'!A:A,'steel Mint data'!I:I,"",0) -> 42000 | K14: =_xlfn.XLOOKUP(A14,'steel Mint data'!A:A,'steel Mint data'!L:L,"",0) -> 44100 | P14: =_xlfn.XLOOKUP(A14,'steel Mint data'!A:A,'steel Mint data'!Q:Q,"",0) -> 39700 | Q14: =_xlfn.XLOOKUP(A14,'steel Mint data'!A:A,'steel Mint data'!R:R,"",0) -> 39900
A15: 45913 | B15: =_xlfn.XLOOKUP(A15,'steel Mint data'!A:A,'steel Mint data'!B:B,"",0) -> 43500 | E15: =_xlfn.XLOOKUP(A15,'steel Mint data'!A:A,'steel Mint data'!D:D,"",0) -> 42400 | F15: =_xlfn.XLOOKUP(A15,'steel Mint data'!A:A,'steel Mint data'!E:E,"",0) -> 39200 | I15: =_xlfn.XLOOKUP(A15,'steel Mint data'!A:A,'steel Mint data'!I:I,"",0) -> 42200 | K15: =_xlfn.XLOOKUP(A15,'steel Mint data'!A:A,'steel Mint data'!L:L,"",0) -> 44100 | P15: =_xlfn.XLOOKUP(A15,'steel Mint data'!A:A,'steel Mint data'!Q:Q,"",0) -> 39700 | Q15: =_xlfn.XLOOKUP(A15,'steel Mint data'!A:A,'steel Mint data'!R:R,"",0) -> 39900
A16: 45914 | B16: =_xlfn.XLOOKUP(A16,'steel Mint data'!A:A,'steel Mint data'!B:B,"",0) -> H | E16: =_xlfn.XLOOKUP(A16,'steel Mint data'!A:A,'steel Mint data'!D:D,"",0) -> H | F16: =_xlfn.XLOOKUP(A16,'steel Mint data'!A:A,'steel Mint data'!E:E,"",0) -> H | I16: =_xlfn.XLOOKUP(A16,'steel Mint data'!A:A,'steel Mint data'!I:I,"",0) -> H | K16: =_xlfn.XLOOKUP(A16,'steel Mint data'!A:A,'steel Mint data'!L:L,"",0) -> H | P16: =_xlfn.XLOOKUP(A16,'steel Mint data'!A:A,'steel Mint data'!Q:Q,"",0) -> H | Q16: =_xlfn.XLOOKUP(A16,'steel Mint data'!A:A,'steel Mint data'!R:R,"",0) -> H
A17: 45915 | B17: =_xlfn.XLOOKUP(A17,'steel Mint data'!A:A,'steel Mint data'!B:B,"",0) -> 43500 | E17: =_xlfn.XLOOKUP(A17,'steel Mint data'!A:A,'steel Mint data'!D:D,"",0) -> 42400 | F17: =_xlfn.XLOOKUP(A17,'steel Mint data'!A:A,'steel Mint data'!E:E,"",0) -> 38900 | I17: =_xlfn.XLOOKUP(A17,'steel Mint data'!A:A,'steel Mint data'!I:I,"",0) -> 42200 | K17: =_xlfn.XLOOKUP(A17,'steel Mint data'!A:A,'steel Mint data'!L:L,"",0) -> 44100 | P17: =_xlfn.XLOOKUP(A17,'steel Mint data'!A:A,'steel Mint data'!Q:Q,"",0) -> 39600 | Q17: =_xlfn.XLOOKUP(A17,'steel Mint data'!A:A,'steel Mint data'!R:R,"",0) -> 39700
B19: =SUM(B3:B18) -> 566000 | E19: =SUM(E3:E18) -> 550600 | F19: =SUM(F3:F18) -> 508700 | I19: =SUM(I3:I18) -> 546100 | K19: =SUM(K3:K18) -> 572600 | P19: =SUM(P3:P18) -> 515700 | Q19: =SUM(Q3:Q18) -> 517500
B20: Amba Shakti (NCR) | C20: API (Raipur) | D20: Aditya Industries (Mandi) | E20: Shree Ganesh (Rourkela) | F20: SKA Raipur | G20: Amba Gwalior | H20: Rajasthan | I20: Gujarat | J20: Bardhman
A21: Avg Price - Divided by no of days steel mint price is available | B21: =E19/O21 -> 42353.846 | C21: =P19/O21 -> 39669.231 | D21: =K19/O21 -> 44046.154 | E21: =Q19/O21 -> 39807.692 | F21: =C21 -> 39669.231 | G21: =B21-800 -> 41553.846 | H21: =I19/O21 -> 42007.692 | I21: =B19/O21 -> 43538.462 | J21: =F19/O21 -> 39130.769 | O21: =COUNT(P3:P18) -> 13
A22: BIS | B22: 1200 | C22: 2150 | D22: 400 | E22: 2200 | F22: 1800 | G22: 1200 | H22: 800 | I22: 0 | J22: 2000 | R22: =43000-1400-F24 -> -144.23077
A23: Loading Charges | B23: 200 | C23: 265 | D23: 250 | E23: 275 | F23: 275 | G23: 200 | H23: 270 | I23: 200 | J23: 270 | P23: =45000-3000-F24 -> 255.76923 | S23: alwar
A24: Actual PO Price (base dia): A | B24: =SUM(B21:B23) -> 43753.846 | C24: =SUM(C21:C23) -> 42084.231 | D24: =SUM(D21:D23) -> 44696.154 | E24: =SUM(E21:E23) -> 42282.692 | F24: =SUM(F21:F23) -> 41744.231 | G24: =SUM(G21:G23) -> 42953.846 | H24: =SUM(H21:H23) -> 43077.692 | I24: =SUM(I21:I23) -> 43738.462 | J24: =SUM(J21:J23) -> 41400.769 | P24: =45000-3000-F25 -> 25 | S24: =45000-3450-1000-F24 -> -1194.2308
A25: Notional PO: B | B25: 45100 | C25: 42315 | D25: 46150 | F25: 41975 | G25: 44300 | I25: 44300 | J25: 42470 | O25: =46000-1800-1000-G24 -> 246.15385 | S25: =45000-3450-1000-F25 -> -1425
A26: Change (A-B) | B26: =B24-B25 -> -1346.1538 | C26: =C24-C25 -> -230.76923 | D26: =D24-D25 -> -1453.8462 | E26: =E24-E25 -> 42282.692 | F26: =F24-F25 -> -230.76923 | G26: =G24-G25 -> -1346.1538 | H26: =H24-H25 -> 43077.692 | I26: =I24-I25 -> -561.53846 | J26: =J24-J25 -> -1069.2308
B27: =B25-2500 -> 42600 | G27: =G25-2500 -> 41800 | N27: =46500-2250-1000-G24 -> 296.15385
A28: Current PL | B28: 48300 | C28: 45550 | D28: 48800 | E28: 45550 | F28: 45550 | G28: 47500 | H28: 47800 | I28: 48300
A29: Current ex plant NR | B29: =B28-500-(200+300+300)-250-400 -> 46350 | C29: =C28-500-(200+300+300)-250-400 -> 43600 | D29: =D28-500-(200+300+300)-250-400 -> 46850 | E29: =E28-500-(200+300+300)-250-400 -> 43600 | F29: =F28-500-(200+300+300)-250-400 -> 43600 | G29: =G28-500-(200+300+300)-250-400 -> 45550 | H29: =H28-500-(200+300+300)-250-400 -> 45850 | I29: =I28-500-(200+300+300)-250-400 -> 46350
A30: Current GM: C | B30: =B29-B24 -> 2596.1538 | C30: =C29-C24 -> 1515.7692 | D30: =D29-D24 -> 2153.8462 | E30: =E29-E24 -> 1317.3077 | F30: =F29-F24 -> 1855.7692 | G30: =G29-G24 -> 2596.1538 | H30: =H29-H24 -> 2772.3077 | I30: =I29-I24 -> 2611.5385
C32: =G24+1000+2000 -> 45953.846 | E32: =45000-1750-G24-1000 -> -703.84615 | G32: =45200-G24-1000-1200 -> 46.153846 | H32: =F24+3000 -> 44744.231
E33: =51500/1.18 -> 43644.068 | F33: =42200*1.18 -> 49796 | G33: =51500/0.18 -> 286111.11 | H33: =45500-G24-1000-1000 -> 546.15385 | XFD33: Asking Price Deliverd
J34: =46200-1600-D24 -> -96.153846 | M34: =45000-700-G25 -> 0 | XFD34: 43500
A35: Plant | B35: Jul H1 notional | P35: =45000-700-G24 -> 1346.1538 | XFD35: 44000
A36: Sikandarabad | B36: 46000 | G36: =F24+3200 -> 44944.231 | P36: =45000-700-G25 -> 0 | XFD36: 43500
A37: API, Raipur | B37: 42615 | C37: =B37+1250 -> 43865 | G37: =43550-500-200 -> 42850 | R37: Raunak Infra | S37: Approved Qty from SKA Plant | T37: Invoiced qty from Gwalior | U37: Planned to Inoviced from API | XFD37: 44000
A38: SKA, Raipur | B38: 42275 | C38: =B38+1000 -> 43275 | G38: =G36-G37 -> 2094.2308 | R38: Qty (MT) | S38: 815 | T38: 207 | U38: =S38-T38 -> 608 | XFD38: 43000
A39: Kala Amb | B39: 46450 | C39: =B39+800 -> 47250 | R39: Approval FOR Price | S39: 46000 | T39: 46000 | U39: 46000 | XFD39: 43500
A40: Gwalior | B40: 45200 | C40: =B40+1000 -> 46200 | R40: Freight | S40: 3300 | T40: 1450 | U40: 3350 | XFD40: 44000
A41: Jaipur | B41: 44470 | R41: Grade -550D | S41: 1000 | T41: 1000 | U41: 1250 | XFD41: 45000
A42: Roukeral | B42: 43675 | R42: Ex-works Price | S42: =S39-S40-S41 -> 41700 | T42: =T39-T40-T41 -> 43550 | U42: =U39-U40-U41 -> 41400 | XFD42: 43500
A43: Gujarat | B43: =44500-1000 -> 43500 | C43: =B43+1000 -> 44500 | R43: Adjusted margin as on 4th Aug'25 | S43: =S42-F24 -> -44.230769 | T43: =T42-G24 -> 596.15385 | U43: =U42-C24 -> -684.23077 | XFD43: 44000
R44: Wt. Margin (Rs/MT) | T44: =SUMPRODUCT(T43:U43,T38:U38)/SUM(T38:U38) -> -359.02879 | XFD44: 44000
XFD45: 44000
XFD46: 41000

Sheet Sept H2
B1: Fe 500
A2: Region / Date | B2: Ex-Ahmedabad | C2: Ex-Bangalore | D2: Ex-Chennai | E2: Ex-Delhi/NCR | F2: Ex-Durgapur | G2: Ex-Goa | H2: Ex-Hyderabad | I2: Ex-Jaipur | J2: Ex-Jalna | K2: Ex-Mandi Gobindgarh | L2: Ex-Mumbai | M2: Ex-Muzaffarnagar | N2: Ex-Patna | O2: Ex-Raigarh | P2: Ex-Raipur | Q2: Ex-Rourkela
A3: 45916 | B3: =_xlfn.XLOOKUP(A3,'steel Mint data'!A:A,'steel Mint data'!B:B,"",0) -> 43300 | E3: =_xlfn.XLOOKUP(A3,'steel Mint data'!A:A,'steel Mint data'!D:D,"",0) -> 42200 | F3: =_xlfn.XLOOKUP(A3,'steel Mint data'!A:A,'steel Mint data'!E:E,"",0) -> 38800 | I3: =_xlfn.XLOOKUP(A3,'steel Mint data'!A:A,'steel Mint data'!I:I,"",0) -> 42000 | K3: =_xlfn.XLOOKUP(A3,'steel Mint data'!A:A,'steel Mint data'!L:L,"",0) -> 44000 | P3: =_xlfn.XLOOKUP(A3,'steel Mint data'!A:A,'steel Mint data'!Q:Q,"",0) -> 39400 | Q3: =_xlfn.XLOOKUP(A3,'steel Mint data'!A:A,'steel Mint data'!R:R,"",0) -> 39400
A4: 45917 | B4: =_xlfn.XLOOKUP(A4,'steel Mint data'!A:A,'steel Mint data'!B:B,"",0) -> 43200 | E4: =_xlfn.XLOOKUP(A4,'steel Mint data'!A:A,'steel Mint data'!D:D,"",0) -> 41900 | F4: =_xlfn.XLOOKUP(A4,'steel Mint data'!A:A,'steel Mint data'!E:E,"",0) -> 38700 | I4: =_xlfn.XLOOKUP(A4,'steel Mint data'!A:A,'steel Mint data'!I:I,"",0) -> 42000 | K4: =_xlfn.XLOOKUP(A4,'steel Mint data'!A:A,'steel Mint data'!L:L,"",0) -> 43700 | P4: =_xlfn.XLOOKUP(A4,'steel Mint data'!A:A,'steel Mint data'!Q:Q,"",0) -> 39400 | Q4: =_xlfn.XLOOKUP(A4,'steel Mint data'!A:A,'steel Mint data'!R:R,"",0) -> 39400
A5: 45918 | B5: =_xlfn.XLOOKUP(A5,'steel Mint data'!A:A,'steel Mint data'!B:B,"",0) -> 43300 | E5: =_xlfn.XLOOKUP(A5,'steel Mint data'!A:A,'steel Mint data'!D:D,"",0) -> 41900 | F5: =_xlfn.XLOOKUP(A5,'steel Mint data'!A:A,'steel Mint data'!E:E,"",0) -> 38900 | I5: =_xlfn.XLOOKUP(A5,'steel Mint data'!A:A,'steel Mint data'!I:I,"",0) -> 42200 | K5: =_xlfn.XLOOKUP(A5,'steel Mint data'!A:A,'steel Mint data'!L:L,"",0) -> 43800 | P5: =_xlfn.XLOOKUP(A5,'steel Mint data'!A:A,'steel Mint data'!Q:Q,"",0) -> 39800 | Q5: =_xlfn.XLOOKUP(A5,'steel Mint data'!A:A,'steel Mint data'!R:R,"",0) -> 39400 | T5: Plant | U5: Fe 550 | V5: Fe 550D
A6: 45919 | B6: =_xlfn.XLOOKUP(A6,'steel Mint data'!A:A,'steel Mint data'!B:B,"",0) -> 43500 | E6: =_xlfn.XLOOKUP(A6,'steel Mint data'!A:A,'steel Mint data'!D:D,"",0) -> 42200 | F6: =_xlfn.XLOOKUP(A6,'steel Mint data'!A:A,'steel Mint data'!E:E,"",0) -> 38900 | I6: =_xlfn.XLOOKUP(A6,'steel Mint data'!A:A,'steel Mint data'!I:I,"",0) -> 42250 | K6: =_xlfn.XLOOKUP(A6,'steel Mint data'!A:A,'steel Mint data'!L:L,"",0) -> 44000 | P6: =_xlfn.XLOOKUP(A6,'steel Mint data'!A:A,'steel Mint data'!Q:Q,"",0) -> 39600 | Q6: =_xlfn.XLOOKUP(A6,'steel Mint data'!A:A,'steel Mint data'!R:R,"",0) -> 39500 | T6: Sikandarabad | U6: 47800 | V6: =U6+700 -> 48500
A7: 45920 | B7: =_xlfn.XLOOKUP(A7,'steel Mint data'!A:A,'steel Mint data'!B:B,"",0) -> 43500 | E7: =_xlfn.XLOOKUP(A7,'steel Mint data'!A:A,'steel Mint data'!D:D,"",0) -> 42200 | F7: =_xlfn.XLOOKUP(A7,'steel Mint data'!A:A,'steel Mint data'!E:E,"",0) -> 38900 | I7: =_xlfn.XLOOKUP(A7,'steel Mint data'!A:A,'steel Mint data'!I:I,"",0) -> 42100 | K7: =_xlfn.XLOOKUP(A7,'steel Mint data'!A:A,'steel Mint data'!L:L,"",0) -> 44100 | P7: =_xlfn.XLOOKUP(A7,'steel Mint data'!A:A,'steel Mint data'!Q:Q,"",0) -> 39600 | Q7: =_xlfn.XLOOKUP(A7,'steel Mint data'!A:A,'steel Mint data'!R:R,"",0) -> 39500 | T7: Gwalior | U7: 47000 | V7: =U7+1000 -> 48000
A8: 45921 | B8: =_xlfn.XLOOKUP(A8,'steel Mint data'!A:A,'steel Mint data'!B:B,"",0) -> H | E8: =_xlfn.XLOOKUP(A8,'steel Mint data'!A:A,'steel Mint data'!D:D,"",0) -> H | F8: =_xlfn.XLOOKUP(A8,'steel Mint data'!A:A,'steel Mint data'!E:E,"",0) -> H | I8: =_xlfn.XLOOKUP(A8,'steel Mint data'!A:A,'steel Mint data'!I:I,"",0) -> H | K8: =_xlfn.XLOOKUP(A8,'steel Mint data'!A:A,'steel Mint data'!L:L,"",0) -> H | P8: =_xlfn.XLOOKUP(A8,'steel Mint data'!A:A,'steel Mint data'!Q:Q,"",0) -> H | Q8: =_xlfn.XLOOKUP(A8,'steel Mint data'!A:A,'steel Mint data'!R:R,"",0) -> H | T8: RAipur | U8: 45050 | V8: =U8+1750 -> 46800
A9: 45922 | B9: =_xlfn.XLOOKUP(A9,'steel Mint data'!A:A,'steel Mint data'!B:B,"",0) -> 43300 | E9: =_xlfn.XLOOKUP(A9,'steel Mint data'!A:A,'steel Mint data'!D:D,"",0) -> 42500 | F9: =_xlfn.XLOOKUP(A9,'steel Mint data'!A:A,'steel Mint data'!E:E,"",0) -> 39000 | I9: =_xlfn.XLOOKUP(A9,'steel Mint data'!A:A,'steel Mint data'!I:I,"",0) -> 42300 | K9: =_xlfn.XLOOKUP(A9,'steel Mint data'!A:A,'steel Mint data'!L:L,"",0) -> 44200 | P9: =_xlfn.XLOOKUP(A9,'steel Mint data'!A:A,'steel Mint data'!Q:Q,"",0) -> 39600 | Q9: =_xlfn.XLOOKUP(A9,'steel Mint data'!A:A,'steel Mint data'!R:R,"",0) -> 39500
A10: 45923 | B10: =_xlfn.XLOOKUP(A10,'steel Mint data'!A:A,'steel Mint data'!B:B,"",0) -> 43500 | E10: =_xlfn.XLOOKUP(A10,'steel Mint data'!A:A,'steel Mint data'!D:D,"",0) -> 42700 | F10: =_xlfn.XLOOKUP(A10,'steel Mint data'!A:A,'steel Mint data'!E:E,"",0) -> 38900 | I10: =_xlfn.XLOOKUP(A10,'steel Mint data'!A:A,'steel Mint data'!I:I,"",0) -> 42400 | K10: =_xlfn.XLOOKUP(A10,'steel Mint data'!A:A,'steel Mint data'!L:L,"",0) -> 44300 | P10: =_xlfn.XLOOKUP(A10,'steel Mint data'!A:A,'steel Mint data'!Q:Q,"",0) -> 39900 | Q10: =_xlfn.XLOOKUP(A10,'steel Mint data'!A:A,'steel Mint data'!R:R,"",0) -> 39600
A11: 45924 | B11: =_xlfn.XLOOKUP(A11,'steel Mint data'!A:A,'steel Mint data'!B:B,"",0) -> 43500 | E11: =_xlfn.XLOOKUP(A11,'steel Mint data'!A:A,'steel Mint data'!D:D,"",0) -> 42600 | F11: =_xlfn.XLOOKUP(A11,'steel Mint data'!A:A,'steel Mint data'!E:E,"",0) -> 38700 | I11: =_xlfn.XLOOKUP(A11,'steel Mint data'!A:A,'steel Mint data'!I:I,"",0) -> 42200 | K11: =_xlfn.XLOOKUP(A11,'steel Mint data'!A:A,'steel Mint data'!L:L,"",0) -> 44200 | P11: =_xlfn.XLOOKUP(A11,'steel Mint data'!A:A,'steel Mint data'!Q:Q,"",0) -> 39800 | Q11: =_xlfn.XLOOKUP(A11,'steel Mint data'!A:A,'steel Mint data'!R:R,"",0) -> 39600
A12: 45925 | B12: =_xlfn.XLOOKUP(A12,'steel Mint data'!A:A,'steel Mint data'!B:B,"",0) -> 43500 | E12: =_xlfn.XLOOKUP(A12,'steel Mint data'!A:A,'steel Mint data'!D:D,"",0) -> 42600 | F12: =_xlfn.XLOOKUP(A12,'steel Mint data'!A:A,'steel Mint data'!E:E,"",0) -> 38800 | I12: =_xlfn.XLOOKUP(A12,'steel Mint data'!A:A,'steel Mint data'!I:I,"",0) -> 42200 | K12: =_xlfn.XLOOKUP(A12,'steel Mint data'!A:A,'steel Mint data'!L:L,"",0) -> 44200 | P12: =_xlfn.XLOOKUP(A12,'steel Mint data'!A:A,'steel Mint data'!Q:Q,"",0) -> 39800 | Q12: =_xlfn.XLOOKUP(A12,'steel Mint data'!A:A,'steel Mint data'!R:R,"",0) -> 39600
A13: 45926 | B13: =_xlfn.XLOOKUP(A13,'steel Mint data'!A:A,'steel Mint data'!B:B,"",0) -> 43500 | E13: =_xlfn.XLOOKUP(A13,'steel Mint data'!A:A,'steel Mint data'!D:D,"",0) -> 42600 | F13: =_xlfn.XLOOKUP(A13,'steel Mint data'!A:A,'steel Mint data'!E:E,"",0) -> 38800 | I13: =_xlfn.XLOOKUP(A13,'steel Mint data'!A:A,'steel Mint data'!I:I,"",0) -> 42000 | K13: =_xlfn.XLOOKUP(A13,'steel Mint data'!A:A,'steel Mint data'!L:L,"",0) -> 44100 | P13: =_xlfn.XLOOKUP(A13,'steel Mint data'!A:A,'steel Mint data'!Q:Q,"",0) -> 39700 | Q13: =_xlfn.XLOOKUP(A13,'steel Mint data'!A:A,'steel Mint data'!R:R,"",0) -> 39400
A14: 45927 | B14: =_xlfn.XLOOKUP(A14,'steel Mint data'!A:A,'steel Mint data'!B:B,"",0) -> 43500 | E14: =_xlfn.XLOOKUP(A14,'steel Mint data'!A:A,'steel Mint data'!D:D,"",0) -> 42800 | F14: =_xlfn.XLOOKUP(A14,'steel Mint data'!A:A,'steel Mint data'!E:E,"",0) -> 38800 | I14: =_xlfn.XLOOKUP(A14,'steel Mint data'!A:A,'steel Mint data'!I:I,"",0) -> 42000 | K14: =_xlfn.XLOOKUP(A14,'steel Mint data'!A:A,'steel Mint data'!L:L,"",0) -> 44300 | P14: =_xlfn.XLOOKUP(A14,'steel Mint data'!A:A,'steel Mint data'!Q:Q,"",0) -> 39600 | Q14: =_xlfn.XLOOKUP(A14,'steel Mint data'!A:A,'steel Mint data'!R:R,"",0) -> 39400
A15: 45928 | B15: =_xlfn.XLOOKUP(A15,'steel Mint data'!A:A,'steel Mint data'!B:B,"",0) -> H | E15: =_xlfn.XLOOKUP(A15,'steel Mint data'!A:A,'steel Mint data'!D:D,"",0) -> H | F15: =_xlfn.XLOOKUP(A15,'steel Mint data'!A:A,'steel Mint data'!E:E,"",0) -> H | I15: =_xlfn.XLOOKUP(A15,'steel Mint data'!A:A,'steel Mint data'!I:I,"",0) -> H | K15: =_xlfn.XLOOKUP(A15,'steel Mint data'!A:A,'steel Mint data'!L:L,"",0) -> H | P15: =_xlfn.XLOOKUP(A15,'steel Mint data'!A:A,'steel Mint data'!Q:Q,"",0) -> H | Q15: =_xlfn.XLOOKUP(A15,'steel Mint data'!A:A,'steel Mint data'!R:R,"",0) -> H
A16: 45929 | B16: =_xlfn.XLOOKUP(A16,'steel Mint data'!A:A,'steel Mint data'!B:B,"",0) -> 43200 | E16: =_xlfn.XLOOKUP(A16,'steel Mint data'!A:A,'steel Mint data'!D:D,"",0) -> 42800 | F16: =_xlfn.XLOOKUP(A16,'steel Mint data'!A:A,'steel Mint data'!E:E,"",0) -> - | I16: =_xlfn.XLOOKUP(A16,'steel Mint data'!A:A,'steel Mint data'!I:I,"",0) -> 41800 | K16: =_xlfn.XLOOKUP(A16,'steel Mint data'!A:A,'steel Mint data'!L:L,"",0) -> 44300 | P16: =_xlfn.XLOOKUP(A16,'steel Mint data'!A:A,'steel Mint data'!Q:Q,"",0) -> 39400 | Q16: =_xlfn.XLOOKUP(A16,'steel Mint data'!A:A,'steel Mint data'!R:R,"",0) -> 39400
A17: 45930 | B17: =_xlfn.XLOOKUP(A17,'steel Mint data'!A:A,'steel Mint data'!B:B,"",0) -> 43000 | E17: =_xlfn.XLOOKUP(A17,'steel Mint data'!A:A,'steel Mint data'!D:D,"",0) -> 42300 | F17: =_xlfn.XLOOKUP(A17,'steel Mint data'!A:A,'steel Mint data'!E:E,"",0) -> - | I17: =_xlfn.XLOOKUP(A17,'steel Mint data'!A:A,'steel Mint data'!I:I,"",0) -> 41800 | K17: =_xlfn.XLOOKUP(A17,'steel Mint data'!A:A,'steel Mint data'!L:L,"",0) -> 44100 | P17: =_xlfn.XLOOKUP(A17,'steel Mint data'!A:A,'steel Mint data'!Q:Q,"",0) -> 39300 | Q17: =_xlfn.XLOOKUP(A17,'steel Mint data'!A:A,'steel Mint data'!R:R,"",0) -> 39400
B19: =SUM(B3:B18) -> 563800 | E19: =SUM(E3:E18) -> 551300 | F19: =SUM(F3:F18) -> 427200 | I19: =SUM(I3:I18) -> 547250 | K19: =SUM(K3:K18) -> 573300 | P19: =SUM(P3:P18) -> 514900 | Q19: =SUM(Q3:Q18) -> 513100
B20: Amba Shakti (NCR) | C20: API (Raipur) | D20: Aditya Industries (Mandi) | E20: Shree Ganesh (Rourkela) | F20: SKA Raipur | G20: Amba Gwalior | H20: Rajasthan | I20: Gujarat | J20: Bardhman
A21: Avg Price - Divided by no of days steel mint price is available | B21: =E19/O21 -> 42407.692 | C21: =P19/O21 -> 39607.692 | D21: =K19/O21 -> 44100 | E21: =Q19/O21 -> 39469.231 | F21: =C21 -> 39607.692 | G21: =B21-800 -> 41607.692 | H21: =I19/O21 -> 42096.154 | I21: =B19/O21 -> 43369.231 | J21: =F19/O21 -> 32861.538 | O21: =COUNT(P3:P18) -> 13
A22: BIS | B22: 1200 | C22: 2150 | D22: 400 | E22: 2200 | F22: 1800 | G22: 1200 | H22: 800 | I22: 0 | J22: 2000 | S22: 46000
A23: Loading Charges | B23: 200 | C23: 265 | D23: 250 | E23: 275 | F23: 275 | G23: 200 | H23: 270 | I23: 200 | J23: 270 | N23: =46000-1800-1000-G24 -> 192.30769 | P23: =45000-3000-F24 -> 317.30769 | S23: 94
A24: Actual PO Price (base dia): A | B24: =SUM(B21:B23) -> 43807.692 | C24: =SUM(C21:C23) -> 42022.692 | D24: =SUM(D21:D23) -> 44750 | E24: =SUM(E21:E23) -> 41944.231 | F24: =SUM(F21:F23) -> 41682.692 | G24: =SUM(G21:G23) -> 43007.692 | H24: =SUM(H21:H23) -> 43166.154 | I24: =SUM(I21:I23) -> 43569.231 | J24: =SUM(J21:J23) -> 35131.538 | L24: =41600-2600-J24 -> 3868.4615 | N24: =46000-1800-1000-G25 -> -1100 | P24: =45000-3000-F25 -> 25 | S24: =46000-1500-1000-G24 -> 492.30769
A25: Notional PO: B | B25: 45100 | C25: 42315 | D25: 46150 | F25: 41975 | G25: 44300 | I25: 44300 | J25: 42470 | K25: =42000-317 -> 41683 | L25: =44500-1750-1000-G24 -> -1257.6923 | S25: 46000
A26: Change (A-B) | B26: =B24-B25 -> -1292.3077 | C26: =C24-C25 -> -292.30769 | D26: =D24-D25 -> -1400 | E26: =E24-E25 -> 41944.231 | F26: =F24-F25 -> -292.30769 | G26: =G24-G25 -> -1292.3077 | H26: =H24-H25 -> 43166.154 | I26: =I24-I25 -> -730.76923 | J26: =J24-J25 -> -7338.4615 | N26: =44200-3100-1000-F24 -> -1582.6923
B27: =B25-2500 -> 42600 | G27: =G25-2500 -> 41800 | L27: =44000-3600-1000-F24 -> -2282.6923 | M27: =46500-1450-1000-G24 -> 1042.3077 | O27: =44500-2000-1000-G24 -> -1507.6923
A28: Current PL | B28: 48300 | C28: 45550 | D28: 48800 | E28: 45550 | F28: 45550 | G28: 47500 | H28: 47800 | I28: 48300
A29: Current ex plant NR | B29: =B28-500-(200+300+300)-250-400 -> 46350 | C29: =C28-500-(200+300+300)-250-400 -> 43600 | D29: =D28-500-(200+300+300)-250-400 -> 46850 | E29: =E28-500-(200+300+300)-250-400 -> 43600 | F29: =F28-500-(200+300+300)-250-400 -> 43600 | G29: =G28-500-(200+300+300)-250-400 -> 45550 | H29: =H28-500-(200+300+300)-250-400 -> 45850 | I29: =I28-500-(200+300+300)-250-400 -> 46350 | L29: =44500-2550-1000-G24 -> -2057.6923 | M29: =45250-1600-1000-G24 -> -357.69231 | N29: =44200-1700-1000-G24 -> -1507.6923
A30: Current GM: C | B30: =B29-B24 -> 2542.3077 | C30: =C29-C24 -> 1577.3077 | D30: =D29-D24 -> 2100 | E30: =E29-E24 -> 1655.7692 | F30: =F29-F24 -> 1917.3077 | G30: =G29-G24 -> 2542.3077 | H30: =H29-H24 -> 2683.8462 | I30: =I29-I24 -> 2780.7692 | M30: =45500-900-800-D24 -> -950
M31: =45500-900-800-D25 -> -2350 | O31: =42000-F24 -> 317.30769
C32: =G24+1000+2000 -> 46007.692 | E32: =45000-1750-G24-1000 -> -757.69231 | G32: =45200-G24-1000-1200 -> -7.6923077 | H32: =F24+3000 -> 44682.692 | J32: =G24+1400 -> 44407.692
D33: =46400-2000-D24-800 -> -1150 | E33: =51500/1.18 -> 43644.068 | F33: =42200*1.18 -> 49796 | G33: =51500/0.18 -> 286111.11 | H33: =45500-G24-1000-1000 -> 492.30769 | XFD33: Asking Price Deliverd
J34: =46200-1600-D24 -> -150 | XFD34: 43500
A35: Plant | B35: Jul H1 notional | XFD35: 44000
A36: Sikandarabad | B36: 46000 | G36: =F24+3200 -> 44882.692 | XFD36: 43500
A37: API, Raipur | B37: 42615 | C37: =B37+1250 -> 43865 | G37: =43550-500-200 -> 42850 | R37: Raunak Infra | S37: Approved Qty from SKA Plant | T37: Invoiced qty from Gwalior | U37: Planned to Inoviced from API | XFD37: 44000
A38: SKA, Raipur | B38: 42275 | C38: =B38+1000 -> 43275 | G38: =G36-G37 -> 2032.6923 | L38: =47700-800-2000-D24 -> 150 | R38: Qty (MT) | S38: 815 | T38: 207 | U38: =S38-T38 -> 608 | XFD38: 43000
A39: Kala Amb | B39: 46450 | C39: =B39+800 -> 47250 | L39: =47700-800-2000-D25 -> -1250 | R39: Approval FOR Price | S39: 46000 | T39: 46000 | U39: 46000 | XFD39: 43500
A40: Gwalior | B40: 45200 | C40: =B40+1000 -> 46200 | R40: Freight | S40: 3300 | T40: 1450 | U40: 3350 | XFD40: 44000
A41: Jaipur | B41: 44470 | R41: Grade -550D | S41: 1000 | T41: 1000 | U41: 1250 | XFD41: 45000
A42: Roukeral | B42: 43675 | R42: Ex-works Price | S42: =S39-S40-S41 -> 41700 | T42: =T39-T40-T41 -> 43550 | U42: =U39-U40-U41 -> 41400 | XFD42: 43500
A43: Gujarat | B43: =44500-1000 -> 43500 | C43: =B43+1000 -> 44500 | R43: Adjusted margin as on 4th Aug'25 | S43: =S42-F24 -> 17.307692 | T43: =T42-G24 -> 542.30769 | U43: =U42-C24 -> -622.69231 | XFD43: 44000
R44: Wt. Margin (Rs/MT) | T44: =SUMPRODUCT(T43:U43,T38:U38)/SUM(T38:U38) -> -326.7966 | XFD44: 44000
XFD45: 44000
XFD46: 41000

Sheet Oct H1 
B1: Fe 500
A2: Region / Date | B2: Ex-Ahmedabad | C2: Ex-Bangalore | D2: Ex-Chennai | E2: Ex-Delhi/NCR | F2: Ex-Durgapur | G2: Ex-Goa | H2: Ex-Hyderabad | I2: Ex-Jaipur | J2: Ex-Jalna | K2: Ex-Mandi Gobindgarh | L2: Ex-Mumbai | M2: Ex-Muzaffarnagar | N2: Ex-Patna | O2: Ex-Raigarh | P2: Ex-Raipur | Q2: Ex-Rourkela
A3: 45931 | B3: =_xlfn.XLOOKUP(A3,'steel Mint data'!A:A,'steel Mint data'!B:B,"",0) -> 43000 | E3: =_xlfn.XLOOKUP(A3,'steel Mint data'!A:A,'steel Mint data'!D:D,"",0) -> 42300 | F3: =_xlfn.XLOOKUP(A3,'steel Mint data'!A:A,'steel Mint data'!E:E,"",0) -> - | I3: =_xlfn.XLOOKUP(A3,'steel Mint data'!A:A,'steel Mint data'!I:I,"",0) -> 41600 | K3: =_xlfn.XLOOKUP(A3,'steel Mint data'!A:A,'steel Mint data'!L:L,"",0) -> 44100 | P3: =_xlfn.XLOOKUP(A3,'steel Mint data'!A:A,'steel Mint data'!Q:Q,"",0) -> 39300 | Q3: =_xlfn.XLOOKUP(A3,'steel Mint data'!A:A,'steel Mint data'!R:R,"",0) -> 39400
A4: 45932 | B4: =_xlfn.XLOOKUP(A4,'steel Mint data'!A:A,'steel Mint data'!B:B,"",0) -> H | E4: =_xlfn.XLOOKUP(A4,'steel Mint data'!A:A,'steel Mint data'!D:D,"",0) -> H | F4: =_xlfn.XLOOKUP(A4,'steel Mint data'!A:A,'steel Mint data'!E:E,"",0) -> H | I4: =_xlfn.XLOOKUP(A4,'steel Mint data'!A:A,'steel Mint data'!I:I,"",0) -> H | K4: =_xlfn.XLOOKUP(A4,'steel Mint data'!A:A,'steel Mint data'!L:L,"",0) -> H | P4: =_xlfn.XLOOKUP(A4,'steel Mint data'!A:A,'steel Mint data'!Q:Q,"",0) -> H | Q4: =_xlfn.XLOOKUP(A4,'steel Mint data'!A:A,'steel Mint data'!R:R,"",0) -> H
A5: 45933 | B5: =_xlfn.XLOOKUP(A5,'steel Mint data'!A:A,'steel Mint data'!B:B,"",0) -> 42800 | E5: =_xlfn.XLOOKUP(A5,'steel Mint data'!A:A,'steel Mint data'!D:D,"",0) -> 42700 | F5: =_xlfn.XLOOKUP(A5,'steel Mint data'!A:A,'steel Mint data'!E:E,"",0) -> 38800 | I5: =_xlfn.XLOOKUP(A5,'steel Mint data'!A:A,'steel Mint data'!I:I,"",0) -> 41800 | K5: =_xlfn.XLOOKUP(A5,'steel Mint data'!A:A,'steel Mint data'!L:L,"",0) -> 44100 | P5: =_xlfn.XLOOKUP(A5,'steel Mint data'!A:A,'steel Mint data'!Q:Q,"",0) -> 39200 | Q5: =_xlfn.XLOOKUP(A5,'steel Mint data'!A:A,'steel Mint data'!R:R,"",0) -> 39400 | T5: Plant | U5: Fe 550 | V5: Fe 550D
A6: 45934 | B6: =_xlfn.XLOOKUP(A6,'steel Mint data'!A:A,'steel Mint data'!B:B,"",0) -> 42700 | E6: =_xlfn.XLOOKUP(A6,'steel Mint data'!A:A,'steel Mint data'!D:D,"",0) -> 42300 | F6: =_xlfn.XLOOKUP(A6,'steel Mint data'!A:A,'steel Mint data'!E:E,"",0) -> 38700 | I6: =_xlfn.XLOOKUP(A6,'steel Mint data'!A:A,'steel Mint data'!I:I,"",0) -> 41600 | K6: =_xlfn.XLOOKUP(A6,'steel Mint data'!A:A,'steel Mint data'!L:L,"",0) -> 44000 | P6: =_xlfn.XLOOKUP(A6,'steel Mint data'!A:A,'steel Mint data'!Q:Q,"",0) -> 39100 | Q6: =_xlfn.XLOOKUP(A6,'steel Mint data'!A:A,'steel Mint data'!R:R,"",0) -> 39400 | T6: Sikandarabad | U6: 47800 | V6: =U6+700 -> 48500
A7: 45935 | B7: =_xlfn.XLOOKUP(A7,'steel Mint data'!A:A,'steel Mint data'!B:B,"",0) -> H | E7: =_xlfn.XLOOKUP(A7,'steel Mint data'!A:A,'steel Mint data'!D:D,"",0) -> H | F7: =_xlfn.XLOOKUP(A7,'steel Mint data'!A:A,'steel Mint data'!E:E,"",0) -> H | I7: =_xlfn.XLOOKUP(A7,'steel Mint data'!A:A,'steel Mint data'!I:I,"",0) -> H | K7: =_xlfn.XLOOKUP(A7,'steel Mint data'!A:A,'steel Mint data'!L:L,"",0) -> H | P7: =_xlfn.XLOOKUP(A7,'steel Mint data'!A:A,'steel Mint data'!Q:Q,"",0) -> H | Q7: =_xlfn.XLOOKUP(A7,'steel Mint data'!A:A,'steel Mint data'!R:R,"",0) -> H | T7: Gwalior | U7: 47000 | V7: =U7+1000 -> 48000
A8: 45936 | B8: =_xlfn.XLOOKUP(A8,'steel Mint data'!A:A,'steel Mint data'!B:B,"",0) -> 42600 | E8: =_xlfn.XLOOKUP(A8,'steel Mint data'!A:A,'steel Mint data'!D:D,"",0) -> 42000 | F8: =_xlfn.XLOOKUP(A8,'steel Mint data'!A:A,'steel Mint data'!E:E,"",0) -> 38500 | I8: =_xlfn.XLOOKUP(A8,'steel Mint data'!A:A,'steel Mint data'!I:I,"",0) -> 41500 | K8: =_xlfn.XLOOKUP(A8,'steel Mint data'!A:A,'steel Mint data'!L:L,"",0) -> 43900 | P8: =_xlfn.XLOOKUP(A8,'steel Mint data'!A:A,'steel Mint data'!Q:Q,"",0) -> 38800 | Q8: =_xlfn.XLOOKUP(A8,'steel Mint data'!A:A,'steel Mint data'!R:R,"",0) -> 39200 | T8: RAipur | U8: 45050 | V8: =U8+1750 -> 46800
A9: 45937 | B9: =_xlfn.XLOOKUP(A9,'steel Mint data'!A:A,'steel Mint data'!B:B,"",0) -> 42400 | E9: =_xlfn.XLOOKUP(A9,'steel Mint data'!A:A,'steel Mint data'!D:D,"",0) -> 41600 | F9: =_xlfn.XLOOKUP(A9,'steel Mint data'!A:A,'steel Mint data'!E:E,"",0) -> 38400 | I9: =_xlfn.XLOOKUP(A9,'steel Mint data'!A:A,'steel Mint data'!I:I,"",0) -> 41300 | K9: =_xlfn.XLOOKUP(A9,'steel Mint data'!A:A,'steel Mint data'!L:L,"",0) -> 43700 | P9: =_xlfn.XLOOKUP(A9,'steel Mint data'!A:A,'steel Mint data'!Q:Q,"",0) -> 38500 | Q9: =_xlfn.XLOOKUP(A9,'steel Mint data'!A:A,'steel Mint data'!R:R,"",0) -> 39000
A10: 45938 | B10: =_xlfn.XLOOKUP(A10,'steel Mint data'!A:A,'steel Mint data'!B:B,"",0) -> 42400 | E10: =_xlfn.XLOOKUP(A10,'steel Mint data'!A:A,'steel Mint data'!D:D,"",0) -> 41600 | F10: =_xlfn.XLOOKUP(A10,'steel Mint data'!A:A,'steel Mint data'!E:E,"",0) -> 38300 | I10: =_xlfn.XLOOKUP(A10,'steel Mint data'!A:A,'steel Mint data'!I:I,"",0) -> 41200 | K10: =_xlfn.XLOOKUP(A10,'steel Mint data'!A:A,'steel Mint data'!L:L,"",0) -> 43500 | P10: =_xlfn.XLOOKUP(A10,'steel Mint data'!A:A,'steel Mint data'!Q:Q,"",0) -> 38500 | Q10: =_xlfn.XLOOKUP(A10,'steel Mint data'!A:A,'steel Mint data'!R:R,"",0) -> 38800
A11: 45939 | B11: =_xlfn.XLOOKUP(A11,'steel Mint data'!A:A,'steel Mint data'!B:B,"",0) -> 42300 | E11: =_xlfn.XLOOKUP(A11,'steel Mint data'!A:A,'steel Mint data'!D:D,"",0) -> 41400 | F11: =_xlfn.XLOOKUP(A11,'steel Mint data'!A:A,'steel Mint data'!E:E,"",0) -> 38400 | I11: =_xlfn.XLOOKUP(A11,'steel Mint data'!A:A,'steel Mint data'!I:I,"",0) -> 41100 | K11: =_xlfn.XLOOKUP(A11,'steel Mint data'!A:A,'steel Mint data'!L:L,"",0) -> 43500 | P11: =_xlfn.XLOOKUP(A11,'steel Mint data'!A:A,'steel Mint data'!Q:Q,"",0) -> 38400 | Q11: =_xlfn.XLOOKUP(A11,'steel Mint data'!A:A,'steel Mint data'!R:R,"",0) -> 38700
A12: 45940 | B12: =_xlfn.XLOOKUP(A12,'steel Mint data'!A:A,'steel Mint data'!B:B,"",0) -> 42400 | E12: =_xlfn.XLOOKUP(A12,'steel Mint data'!A:A,'steel Mint data'!D:D,"",0) -> 41700 | F12: =_xlfn.XLOOKUP(A12,'steel Mint data'!A:A,'steel Mint data'!E:E,"",0) -> 38500 | I12: =_xlfn.XLOOKUP(A12,'steel Mint data'!A:A,'steel Mint data'!I:I,"",0) -> 41200 | K12: =_xlfn.XLOOKUP(A12,'steel Mint data'!A:A,'steel Mint data'!L:L,"",0) -> 43800 | P12: =_xlfn.XLOOKUP(A12,'steel Mint data'!A:A,'steel Mint data'!Q:Q,"",0) -> 38600 | Q12: =_xlfn.XLOOKUP(A12,'steel Mint data'!A:A,'steel Mint data'!R:R,"",0) -> 38800
A13: 45941 | B13: =_xlfn.XLOOKUP(A13,'steel Mint data'!A:A,'steel Mint data'!B:B,"",0) -> 42400 | E13: =_xlfn.XLOOKUP(A13,'steel Mint data'!A:A,'steel Mint data'!D:D,"",0) -> 41700 | F13: =_xlfn.XLOOKUP(A13,'steel Mint data'!A:A,'steel Mint data'!E:E,"",0) -> 38400 | I13: =_xlfn.XLOOKUP(A13,'steel Mint data'!A:A,'steel Mint data'!I:I,"",0) -> 41200 | K13: =_xlfn.XLOOKUP(A13,'steel Mint data'!A:A,'steel Mint data'!L:L,"",0) -> 43800 | P13: =_xlfn.XLOOKUP(A13,'steel Mint data'!A:A,'steel Mint data'!Q:Q,"",0) -> 38500 | Q13: =_xlfn.XLOOKUP(A13,'steel Mint data'!A:A,'steel Mint data'!R:R,"",0) -> 38800
A14: 45942 | B14: =_xlfn.XLOOKUP(A14,'steel Mint data'!A:A,'steel Mint data'!B:B,"",0) -> H | E14: =_xlfn.XLOOKUP(A14,'steel Mint data'!A:A,'steel Mint data'!D:D,"",0) -> H | F14: =_xlfn.XLOOKUP(A14,'steel Mint data'!A:A,'steel Mint data'!E:E,"",0) -> H | I14: =_xlfn.XLOOKUP(A14,'steel Mint data'!A:A,'steel Mint data'!I:I,"",0) -> H | K14: =_xlfn.XLOOKUP(A14,'steel Mint data'!A:A,'steel Mint data'!L:L,"",0) -> H | P14: =_xlfn.XLOOKUP(A14,'steel Mint data'!A:A,'steel Mint data'!Q:Q,"",0) -> H | Q14: =_xlfn.XLOOKUP(A14,'steel Mint data'!A:A,'steel Mint data'!R:R,"",0) -> H | S14: =41742 -> 41742
A15: 45943 | B15: =_xlfn.XLOOKUP(A15,'steel Mint data'!A:A,'steel Mint data'!B:B,"",0) -> 42300 | E15: =_xlfn.XLOOKUP(A15,'steel Mint data'!A:A,'steel Mint data'!D:D,"",0) -> 41200 | F15: =_xlfn.XLOOKUP(A15,'steel Mint data'!A:A,'steel Mint data'!E:E,"",0) -> 38200 | I15: =_xlfn.XLOOKUP(A15,'steel Mint data'!A:A,'steel Mint data'!I:I,"",0) -> 41000 | K15: =_xlfn.XLOOKUP(A15,'steel Mint data'!A:A,'steel Mint data'!L:L,"",0) -> 43700 | P15: =_xlfn.XLOOKUP(A15,'steel Mint data'!A:A,'steel Mint data'!Q:Q,"",0) -> 38200 | Q15: =_xlfn.XLOOKUP(A15,'steel Mint data'!A:A,'steel Mint data'!R:R,"",0) -> 38500
A16: 45944 | B16: =_xlfn.XLOOKUP(A16,'steel Mint data'!A:A,'steel Mint data'!B:B,"",0) -> 42200 | E16: =_xlfn.XLOOKUP(A16,'steel Mint data'!A:A,'steel Mint data'!D:D,"",0) -> 41200 | F16: =_xlfn.XLOOKUP(A16,'steel Mint data'!A:A,'steel Mint data'!E:E,"",0) -> 38000 | I16: =_xlfn.XLOOKUP(A16,'steel Mint data'!A:A,'steel Mint data'!I:I,"",0) -> 40900 | K16: =_xlfn.XLOOKUP(A16,'steel Mint data'!A:A,'steel Mint data'!L:L,"",0) -> 43500 | P16: =_xlfn.XLOOKUP(A16,'steel Mint data'!A:A,'steel Mint data'!Q:Q,"",0) -> 38000 | Q16: =_xlfn.XLOOKUP(A16,'steel Mint data'!A:A,'steel Mint data'!R:R,"",0) -> 38300 | S16: =S14-800 -> 40942
A17: 45945 | B17: =_xlfn.XLOOKUP(A17,'steel Mint data'!A:A,'steel Mint data'!B:B,"",0) -> 42200 | E17: =_xlfn.XLOOKUP(A17,'steel Mint data'!A:A,'steel Mint data'!D:D,"",0) -> 41200 | F17: =_xlfn.XLOOKUP(A17,'steel Mint data'!A:A,'steel Mint data'!E:E,"",0) -> 37900 | I17: =_xlfn.XLOOKUP(A17,'steel Mint data'!A:A,'steel Mint data'!I:I,"",0) -> 40500 | K17: =_xlfn.XLOOKUP(A17,'steel Mint data'!A:A,'steel Mint data'!L:L,"",0) -> 43400 | P17: =_xlfn.XLOOKUP(A17,'steel Mint data'!A:A,'steel Mint data'!Q:Q,"",0) -> 37900 | Q17: =_xlfn.XLOOKUP(A17,'steel Mint data'!A:A,'steel Mint data'!R:R,"",0) -> 38200 | S17: =43900-S16 -> 2958
B18: =_xlfn.XLOOKUP(A18,'steel Mint data'!A:A,'steel Mint data'!B:B,"",0) | E18: =_xlfn.XLOOKUP(A18,'steel Mint data'!A:A,'steel Mint data'!D:D,"",0) | F18: =_xlfn.XLOOKUP(A18,'steel Mint data'!A:A,'steel Mint data'!E:E,"",0) | I18: =_xlfn.XLOOKUP(A18,'steel Mint data'!A:A,'steel Mint data'!I:I,"",0) | K18: =_xlfn.XLOOKUP(A18,'steel Mint data'!A:A,'steel Mint data'!L:L,"",0) | P18: =_xlfn.XLOOKUP(A18,'steel Mint data'!A:A,'steel Mint data'!Q:Q,"",0) | Q18: =_xlfn.XLOOKUP(A18,'steel Mint data'!A:A,'steel Mint data'!R:R,"",0)
B19: =SUM(B3:B18) -> 509700 | E19: =SUM(E3:E18) -> 500900 | F19: =SUM(F3:F18) -> 422100 | I19: =SUM(I3:I18) -> 494900 | K19: =SUM(K3:K18) -> 525000 | P19: =SUM(P3:P18) -> 463000 | Q19: =SUM(Q3:Q18) -> 466500
B20: Amba Shakti (NCR) | C20: API (Raipur) | D20: Aditya Industries (Mandi) | E20: Shree Ganesh (Rourkela) | F20: SKA Raipur | G20: Amba Gwalior | H20: Rajasthan | I20: Gujarat | J20: Bardhman
A21: Avg Price - Divided by no of days steel mint price is available | B21: =E19/O21 -> 41741.667 | C21: =P19/O21 -> 38583.333 | D21: =K19/O21 -> 43750 | E21: =Q19/O21 -> 38875 | F21: =C21 -> 38583.333 | G21: =B21-800 -> 40941.667 | H21: =I19/O21 -> 41241.667 | I21: =B19/O21 -> 42475 | J21: =F19/(O21-1) -> 38372.727 | O21: =COUNT(P3:P18) -> 12
A22: BIS | B22: 1200 | C22: 2150 | D22: 400 | E22: 2200 | F22: 1800 | G22: 1200 | H22: 800 | I22: 0 | J22: 2000 | L22: =43142+41900 -> 85042
A23: Loading Charges | B23: 200 | C23: 265 | D23: 250 | E23: 275 | F23: 275 | G23: 200 | H23: 270 | I23: 200 | J23: 270 | L23: =L22/2 -> 42521
A24: Actual PO Price (base dia): A | B24: =SUM(B21:B23) -> 43141.667 | C24: =SUM(C21:C23) -> 40998.333 | D24: =SUM(D21:D23) -> 44400 | E24: =SUM(E21:E23) -> 41350 | F24: =SUM(F21:F23) -> 40658.333 | G24: =SUM(G21:G23) -> 42341.667 | H24: =SUM(H21:H23) -> 42311.667 | I24: =SUM(I21:I23) -> 42675 | J24: =SUM(J21:J23) -> 40642.727 | K24: =G24+500 -> 42841.667
A25: Notional PO: B | B25: 45100 | C25: 42315 | D25: 46150 | F25: 41975 | G25: 44300 | I25: 44300 | J25: 42470 | M25: =44700-800-1000-F24 -> 2241.6667 | N25: =46500-2250-1000-G24 -> 908.33333 | O25: =46700-1000-2250-G24 -> 1108.3333 | P25: =44700-800-1000-F24 -> 2241.6667 | Q25: =46250-800-850-D24 -> 200 | R25: =46000-900-1000-I24 -> 1425
A26: Change (A-B) | B26: =B24-B25 -> -1958.3333 | C26: =C24-C25 -> -1316.6667 | D26: =D24-D25 -> -1750 | E26: =E24-E25 -> 41350 | F26: =F24-F25 -> -1316.6667 | G26: =G24-G25 -> -1958.3333 | H26: =H24-H25 -> 42311.667 | I26: =I24-I25 -> -1625 | J26: =J24-J25 -> -1827.2727 | N26: =46500-2250-1000-G25 -> -1050
B27: =B25-2500 -> 42600 | G27: =G25-2500 -> 41800
A28: Current PL | B28: 48300 | C28: 45550 | D28: 48800 | E28: 45550 | F28: 45550 | G28: 47500 | H28: 47800 | I28: 48300
A29: Current ex plant NR | B29: =B28-500-(200+300+300)-250-400 -> 46350 | C29: =C28-500-(200+300+300)-250-400 -> 43600 | D29: =D28-500-(200+300+300)-250-400 -> 46850 | E29: =E28-500-(200+300+300)-250-400 -> 43600 | F29: =F28-500-(200+300+300)-250-400 -> 43600 | G29: =G28-500-(200+300+300)-250-400 -> 45550 | H29: =H28-500-(200+300+300)-250-400 -> 45850 | I29: =I28-500-(200+300+300)-250-400 -> 46350 | N29: =44850-2450-J24 -> 1757.2727 | P29: =44750-2500-F24 -> 1591.6667
A30: Current GM: C | B30: =B29-B24 -> 3208.3333 | C30: =C29-C24 -> 2601.6667 | D30: =D29-D24 -> 2450 | E30: =E29-E24 -> 2250 | F30: =F29-F24 -> 2941.6667 | G30: =G29-G24 -> 3208.3333 | H30: =H29-H24 -> 3538.3333 | I30: =I29-I24 -> 3675
XFD33: Asking Price Deliverd
G34: =G24+1000 -> 43341.667 | XFD34: 43500
A35: Plant | B35: Jul H1 notional | XFD35: 44000
A36: Sikandarabad | B36: 46000 | XFD36: 43500
A37: API, Raipur | B37: 42615 | C37: =B37+1250 -> 43865 | R37: Raunak Infra | S37: Approved Qty from SKA Plant | T37: Invoiced qty from Gwalior | U37: Planned to Inoviced from API | XFD37: 44000
A38: SKA, Raipur | B38: 42275 | C38: =B38+1000 -> 43275 | R38: Qty (MT) | S38: 815 | T38: 207 | U38: =S38-T38 -> 608 | XFD38: 43000
A39: Kala Amb | B39: 46450 | C39: =B39+800 -> 47250 | R39: Approval FOR Price | S39: 46000 | T39: 46000 | U39: 46000 | XFD39: 43500
A40: Gwalior | B40: 45200 | C40: =B40+1000 -> 46200 | R40: Freight | S40: 3300 | T40: 1450 | U40: 3350 | XFD40: 44000
A41: Jaipur | B41: 44470 | R41: Grade -550D | S41: 1000 | T41: 1000 | U41: 1250 | XFD41: 45000
A42: Roukeral | B42: 43675 | R42: Ex-works Price | S42: =S39-S40-S41 -> 41700 | T42: =T39-T40-T41 -> 43550 | U42: =U39-U40-U41 -> 41400 | XFD42: 43500
A43: Gujarat | B43: =44500-1000 -> 43500 | C43: =B43+1000 -> 44500 | R43: Adjusted margin as on 4th Aug'25 | S43: =S42-F24 -> 1041.6667 | T43: =T42-G24 -> 1208.3333 | U43: =U42-C24 -> 401.66667 | XFD43: 44000
R44: Wt. Margin (Rs/MT) | T44: =SUMPRODUCT(T43:U43,T38:U38)/SUM(T38:U38) -> 606.5501 | XFD44: 44000
XFD45: 44000
XFD46: 41000

Sheet Oct H2 
B1: Fe 500
A2: Region / Date | B2: Ex-Ahmedabad | C2: Ex-Bangalore | D2: Ex-Chennai | E2: Ex-Delhi/NCR | F2: Ex-Durgapur | G2: Ex-Goa | H2: Ex-Hyderabad | I2: Ex-Jaipur | J2: Ex-Jalna | K2: Ex-Mandi Gobindgarh | L2: Ex-Mumbai | M2: Ex-Muzaffarnagar | N2: Ex-Patna | O2: Ex-Raigarh | P2: Ex-Raipur | Q2: Ex-Rourkela
A3: 45946 | B3: =_xlfn.XLOOKUP(A3,'steel Mint data'!A:A,'steel Mint data'!B:B,"",0) -> 42200 | E3: =_xlfn.XLOOKUP(A3,'steel Mint data'!A:A,'steel Mint data'!D:D,"",0) -> 41000 | F3: =_xlfn.XLOOKUP(A3,'steel Mint data'!A:A,'steel Mint data'!E:E,"",0) -> 37700 | I3: =_xlfn.XLOOKUP(A3,'steel Mint data'!A:A,'steel Mint data'!I:I,"",0) -> 40400 | K3: =_xlfn.XLOOKUP(A3,'steel Mint data'!A:A,'steel Mint data'!L:L,"",0) -> 43200 | P3: =_xlfn.XLOOKUP(A3,'steel Mint data'!A:A,'steel Mint data'!Q:Q,"",0) -> 37800 | Q3: =_xlfn.XLOOKUP(A3,'steel Mint data'!A:A,'steel Mint data'!R:R,"",0) -> 38200
A4: 45947 | B4: =_xlfn.XLOOKUP(A4,'steel Mint data'!A:A,'steel Mint data'!B:B,"",0) -> 42100 | E4: =_xlfn.XLOOKUP(A4,'steel Mint data'!A:A,'steel Mint data'!D:D,"",0) -> 40900 | F4: =_xlfn.XLOOKUP(A4,'steel Mint data'!A:A,'steel Mint data'!E:E,"",0) -> 37700 | I4: =_xlfn.XLOOKUP(A4,'steel Mint data'!A:A,'steel Mint data'!I:I,"",0) -> 40300 | K4: =_xlfn.XLOOKUP(A4,'steel Mint data'!A:A,'steel Mint data'!L:L,"",0) -> 43200 | P4: =_xlfn.XLOOKUP(A4,'steel Mint data'!A:A,'steel Mint data'!Q:Q,"",0) -> 37800 | Q4: =_xlfn.XLOOKUP(A4,'steel Mint data'!A:A,'steel Mint data'!R:R,"",0) -> 38200
A5: 45948 | B5: =_xlfn.XLOOKUP(A5,'steel Mint data'!A:A,'steel Mint data'!B:B,"",0) -> 42100 | E5: =_xlfn.XLOOKUP(A5,'steel Mint data'!A:A,'steel Mint data'!D:D,"",0) -> 40700 | F5: =_xlfn.XLOOKUP(A5,'steel Mint data'!A:A,'steel Mint data'!E:E,"",0) -> 37700 | I5: =_xlfn.XLOOKUP(A5,'steel Mint data'!A:A,'steel Mint data'!I:I,"",0) -> 40300 | K5: =_xlfn.XLOOKUP(A5,'steel Mint data'!A:A,'steel Mint data'!L:L,"",0) -> 43200 | P5: =_xlfn.XLOOKUP(A5,'steel Mint data'!A:A,'steel Mint data'!Q:Q,"",0) -> 37800 | Q5: =_xlfn.XLOOKUP(A5,'steel Mint data'!A:A,'steel Mint data'!R:R,"",0) -> 38000
A6: 45949 | B6: =_xlfn.XLOOKUP(A6,'steel Mint data'!A:A,'steel Mint data'!B:B,"",0) -> H | E6: =_xlfn.XLOOKUP(A6,'steel Mint data'!A:A,'steel Mint data'!D:D,"",0) -> H | F6: =_xlfn.XLOOKUP(A6,'steel Mint data'!A:A,'steel Mint data'!E:E,"",0) -> H | I6: =_xlfn.XLOOKUP(A6,'steel Mint data'!A:A,'steel Mint data'!I:I,"",0) -> H | K6: =_xlfn.XLOOKUP(A6,'steel Mint data'!A:A,'steel Mint data'!L:L,"",0) -> H | P6: =_xlfn.XLOOKUP(A6,'steel Mint data'!A:A,'steel Mint data'!Q:Q,"",0) -> H | Q6: =_xlfn.XLOOKUP(A6,'steel Mint data'!A:A,'steel Mint data'!R:R,"",0) -> H
A7: 45950 | B7: =_xlfn.XLOOKUP(A7,'steel Mint data'!A:A,'steel Mint data'!B:B,"",0) -> H | E7: =_xlfn.XLOOKUP(A7,'steel Mint data'!A:A,'steel Mint data'!D:D,"",0) -> H | F7: =_xlfn.XLOOKUP(A7,'steel Mint data'!A:A,'steel Mint data'!E:E,"",0) -> H | I7: =_xlfn.XLOOKUP(A7,'steel Mint data'!A:A,'steel Mint data'!I:I,"",0) -> H | K7: =_xlfn.XLOOKUP(A7,'steel Mint data'!A:A,'steel Mint data'!L:L,"",0) -> H | P7: =_xlfn.XLOOKUP(A7,'steel Mint data'!A:A,'steel Mint data'!Q:Q,"",0) -> H | Q7: =_xlfn.XLOOKUP(A7,'steel Mint data'!A:A,'steel Mint data'!R:R,"",0) -> H
A8: 45951 | B8: =_xlfn.XLOOKUP(A8,'steel Mint data'!A:A,'steel Mint data'!B:B,"",0) -> H | E8: =_xlfn.XLOOKUP(A8,'steel Mint data'!A:A,'steel Mint data'!D:D,"",0) -> H | F8: =_xlfn.XLOOKUP(A8,'steel Mint data'!A:A,'steel Mint data'!E:E,"",0) -> H | I8: =_xlfn.XLOOKUP(A8,'steel Mint data'!A:A,'steel Mint data'!I:I,"",0) -> H | K8: =_xlfn.XLOOKUP(A8,'steel Mint data'!A:A,'steel Mint data'!L:L,"",0) -> H | P8: =_xlfn.XLOOKUP(A8,'steel Mint data'!A:A,'steel Mint data'!Q:Q,"",0) -> H | Q8: =_xlfn.XLOOKUP(A8,'steel Mint data'!A:A,'steel Mint data'!R:R,"",0) -> H
A9: 45952 | B9: =_xlfn.XLOOKUP(A9,'steel Mint data'!A:A,'steel Mint data'!B:B,"",0) -> H | E9: =_xlfn.XLOOKUP(A9,'steel Mint data'!A:A,'steel Mint data'!D:D,"",0) -> H | F9: =_xlfn.XLOOKUP(A9,'steel Mint data'!A:A,'steel Mint data'!E:E,"",0) -> H | I9: =_xlfn.XLOOKUP(A9,'steel Mint data'!A:A,'steel Mint data'!I:I,"",0) -> H | K9: =_xlfn.XLOOKUP(A9,'steel Mint data'!A:A,'steel Mint data'!L:L,"",0) -> H | P9: =_xlfn.XLOOKUP(A9,'steel Mint data'!A:A,'steel Mint data'!Q:Q,"",0) -> H | Q9: =_xlfn.XLOOKUP(A9,'steel Mint data'!A:A,'steel Mint data'!R:R,"",0) -> H
A10: 45953 | B10: =_xlfn.XLOOKUP(A10,'steel Mint data'!A:A,'steel Mint data'!B:B,"",0) -> - | E10: =_xlfn.XLOOKUP(A10,'steel Mint data'!A:A,'steel Mint data'!D:D,"",0) -> 40300 | F10: =_xlfn.XLOOKUP(A10,'steel Mint data'!A:A,'steel Mint data'!E:E,"",0) -> 37500 | I10: =_xlfn.XLOOKUP(A10,'steel Mint data'!A:A,'steel Mint data'!I:I,"",0) -> 40100 | K10: =_xlfn.XLOOKUP(A10,'steel Mint data'!A:A,'steel Mint data'!L:L,"",0) -> 42900 | P10: =_xlfn.XLOOKUP(A10,'steel Mint data'!A:A,'steel Mint data'!Q:Q,"",0) -> 37500 | Q10: =_xlfn.XLOOKUP(A10,'steel Mint data'!A:A,'steel Mint data'!R:R,"",0) -> 37400
A11: 45954 | B11: =_xlfn.XLOOKUP(A11,'steel Mint data'!A:A,'steel Mint data'!B:B,"",0) -> 41900 | E11: =_xlfn.XLOOKUP(A11,'steel Mint data'!A:A,'steel Mint data'!D:D,"",0) -> 40100 | F11: =_xlfn.XLOOKUP(A11,'steel Mint data'!A:A,'steel Mint data'!E:E,"",0) -> 37400 | I11: =_xlfn.XLOOKUP(A11,'steel Mint data'!A:A,'steel Mint data'!I:I,"",0) -> 40100 | K11: =_xlfn.XLOOKUP(A11,'steel Mint data'!A:A,'steel Mint data'!L:L,"",0) -> 42700 | P11: =_xlfn.XLOOKUP(A11,'steel Mint data'!A:A,'steel Mint data'!Q:Q,"",0) -> 37400 | Q11: =_xlfn.XLOOKUP(A11,'steel Mint data'!A:A,'steel Mint data'!R:R,"",0) -> 37200
A12: 45955 | B12: =_xlfn.XLOOKUP(A12,'steel Mint data'!A:A,'steel Mint data'!B:B,"",0) -> 41900 | E12: =_xlfn.XLOOKUP(A12,'steel Mint data'!A:A,'steel Mint data'!D:D,"",0) -> 40200 | F12: =_xlfn.XLOOKUP(A12,'steel Mint data'!A:A,'steel Mint data'!E:E,"",0) -> 37500 | I12: =_xlfn.XLOOKUP(A12,'steel Mint data'!A:A,'steel Mint data'!I:I,"",0) -> 40300 | K12: =_xlfn.XLOOKUP(A12,'steel Mint data'!A:A,'steel Mint data'!L:L,"",0) -> 42700 | P12: =_xlfn.XLOOKUP(A12,'steel Mint data'!A:A,'steel Mint data'!Q:Q,"",0) -> 37400 | Q12: =_xlfn.XLOOKUP(A12,'steel Mint data'!A:A,'steel Mint data'!R:R,"",0) -> 37200
A13: 45956 | B13: =_xlfn.XLOOKUP(A13,'steel Mint data'!A:A,'steel Mint data'!B:B,"",0) -> H | E13: =_xlfn.XLOOKUP(A13,'steel Mint data'!A:A,'steel Mint data'!D:D,"",0) -> H | F13: =_xlfn.XLOOKUP(A13,'steel Mint data'!A:A,'steel Mint data'!E:E,"",0) -> H | I13: =_xlfn.XLOOKUP(A13,'steel Mint data'!A:A,'steel Mint data'!I:I,"",0) -> H | K13: =_xlfn.XLOOKUP(A13,'steel Mint data'!A:A,'steel Mint data'!L:L,"",0) -> H | P13: =_xlfn.XLOOKUP(A13,'steel Mint data'!A:A,'steel Mint data'!Q:Q,"",0) -> H | Q13: =_xlfn.XLOOKUP(A13,'steel Mint data'!A:A,'steel Mint data'!R:R,"",0) -> H
A14: 45957 | B14: =_xlfn.XLOOKUP(A14,'steel Mint data'!A:A,'steel Mint data'!B:B,"",0) -> 41900 | E14: =_xlfn.XLOOKUP(A14,'steel Mint data'!A:A,'steel Mint data'!D:D,"",0) -> 40300 | F14: =_xlfn.XLOOKUP(A14,'steel Mint data'!A:A,'steel Mint data'!E:E,"",0) -> 37400 | I14: =_xlfn.XLOOKUP(A14,'steel Mint data'!A:A,'steel Mint data'!I:I,"",0) -> 40100 | K14: =_xlfn.XLOOKUP(A14,'steel Mint data'!A:A,'steel Mint data'!L:L,"",0) -> 42700 | P14: =_xlfn.XLOOKUP(A14,'steel Mint data'!A:A,'steel Mint data'!Q:Q,"",0) -> 37300 | Q14: =_xlfn.XLOOKUP(A14,'steel Mint data'!A:A,'steel Mint data'!R:R,"",0) -> 37200 | S14: =800*43100+3000*41900 -> 160180000
A15: 45958 | B15: =_xlfn.XLOOKUP(A15,'steel Mint data'!A:A,'steel Mint data'!B:B,"",0) -> 41900 | E15: =_xlfn.XLOOKUP(A15,'steel Mint data'!A:A,'steel Mint data'!D:D,"",0) -> 40200 | F15: =_xlfn.XLOOKUP(A15,'steel Mint data'!A:A,'steel Mint data'!E:E,"",0) -> 37300 | I15: =_xlfn.XLOOKUP(A15,'steel Mint data'!A:A,'steel Mint data'!I:I,"",0) -> 39900 | K15: =_xlfn.XLOOKUP(A15,'steel Mint data'!A:A,'steel Mint data'!L:L,"",0) -> 42500 | P15: =_xlfn.XLOOKUP(A15,'steel Mint data'!A:A,'steel Mint data'!Q:Q,"",0) -> 37200 | Q15: =_xlfn.XLOOKUP(A15,'steel Mint data'!A:A,'steel Mint data'!R:R,"",0) -> 37200 | S15: =S14/3800 -> 42152.632
A16: 45959 | B16: =_xlfn.XLOOKUP(A16,'steel Mint data'!A:A,'steel Mint data'!B:B,"",0) -> 42000 | E16: =_xlfn.XLOOKUP(A16,'steel Mint data'!A:A,'steel Mint data'!D:D,"",0) -> 40100 | F16: =_xlfn.XLOOKUP(A16,'steel Mint data'!A:A,'steel Mint data'!E:E,"",0) -> 37600 | I16: =_xlfn.XLOOKUP(A16,'steel Mint data'!A:A,'steel Mint data'!I:I,"",0) -> 40100 | K16: =_xlfn.XLOOKUP(A16,'steel Mint data'!A:A,'steel Mint data'!L:L,"",0) -> 42600 | P16: =_xlfn.XLOOKUP(A16,'steel Mint data'!A:A,'steel Mint data'!Q:Q,"",0) -> 37400 | Q16: =_xlfn.XLOOKUP(A16,'steel Mint data'!A:A,'steel Mint data'!R:R,"",0) -> 37300
A17: 45960 | B17: =_xlfn.XLOOKUP(A17,'steel Mint data'!A:A,'steel Mint data'!B:B,"",0) -> 42000 | E17: =_xlfn.XLOOKUP(A17,'steel Mint data'!A:A,'steel Mint data'!D:D,"",0) -> 40600 | F17: =_xlfn.XLOOKUP(A17,'steel Mint data'!A:A,'steel Mint data'!E:E,"",0) -> 37700 | I17: =_xlfn.XLOOKUP(A17,'steel Mint data'!A:A,'steel Mint data'!I:I,"",0) -> 40300 | K17: =_xlfn.XLOOKUP(A17,'steel Mint data'!A:A,'steel Mint data'!L:L,"",0) -> 42900 | P17: =_xlfn.XLOOKUP(A17,'steel Mint data'!A:A,'steel Mint data'!Q:Q,"",0) -> 37500 | Q17: =_xlfn.XLOOKUP(A17,'steel Mint data'!A:A,'steel Mint data'!R:R,"",0) -> 37500
A18: 45961 | B18: =_xlfn.XLOOKUP(A18,'steel Mint data'!A:A,'steel Mint data'!B:B,"",0) -> 42300 | E18: =_xlfn.XLOOKUP(A18,'steel Mint data'!A:A,'steel Mint data'!D:D,"",0) -> 41500 | F18: =_xlfn.XLOOKUP(A18,'steel Mint data'!A:A,'steel Mint data'!E:E,"",0) -> 38000 | I18: =_xlfn.XLOOKUP(A18,'steel Mint data'!A:A,'steel Mint data'!I:I,"",0) -> 40700 | K18: =_xlfn.XLOOKUP(A18,'steel Mint data'!A:A,'steel Mint data'!L:L,"",0) -> 43000 | P18: =_xlfn.XLOOKUP(A18,'steel Mint data'!A:A,'steel Mint data'!Q:Q,"",0) -> 38200 | Q18: =_xlfn.XLOOKUP(A18,'steel Mint data'!A:A,'steel Mint data'!R:R,"",0) -> 38400
B19: =SUM(B3:B18) -> 420300 | E19: =SUM(E3:E18) -> 445900 | F19: =SUM(F3:F18) -> 413500 | I19: =SUM(I3:I18) -> 442600 | K19: =SUM(K3:K18) -> 471600 | P19: =SUM(P3:P18) -> 413300 | Q19: =SUM(Q3:Q18) -> 413800
B20: Amba Shakti (NCR) | C20: API (Raipur) | D20: Aditya Industries (Mandi) | E20: Shree Ganesh (Rourkela) | F20: SKA Raipur | G20: Amba Gwalior | H20: Rajasthan | I20: Gujarat | J20: Bardhman | M20: =40100+H22+H23 -> 41170
A21: Avg Price - Divided by no of days steel mint price is available | B21: =E19/O21 -> 40536.364 | C21: =P19/O21 -> 37572.727 | D21: =K19/O21 -> 42872.727 | E21: =Q19/O21 -> 37618.182 | F21: =C21 -> 37572.727 | G21: =B21-800 -> 39736.364 | H21: =I19/O21 -> 40236.364 | I21: =B19/(O21-1) -> 42030 | J21: =F19/O21 -> 37590.909 | O21: =COUNT(P3:P18) -> 11
A22: BIS | B22: 1200 | C22: 2150 | D22: 400 | E22: 2200 | F22: 1800 | G22: 1200 | H22: 800 | I22: 0 | J22: 2000 | N22: =46050-2500-1000-G24 -> 1413.6364 | R22: =42800-G24 -> 1663.6364
A23: Loading Charges | B23: 200 | C23: 265 | D23: 250 | E23: 275 | F23: 275 | G23: 200 | H23: 270 | I23: 200 | J23: 270 | M23: =45500-1000-1000-G24 -> 2363.6364 | O23: =44750-600-1000-G24 -> 2013.6364
A24: Actual PO Price (base dia): A | B24: =SUM(B21:B23) -> 41936.364 | C24: =SUM(C21:C23) -> 39987.727 | D24: =SUM(D21:D23) -> 43522.727 | E24: =SUM(E21:E23) -> 40093.182 | F24: =SUM(F21:F23) -> 39647.727 | G24: =SUM(G21:G23) -> 41136.364 | H24: =SUM(H21:H23) -> 41306.364 | I24: =SUM(I21:I23) -> 42230 | J24: =SUM(J21:J23) -> 39860.909 | K24: =45380-800 -> 44580 | L24: =44000-D24-800 -> -322.72727 | N24: =45500-1500-1000-G24 -> 1863.6364
A25: Notional PO: B | B25: 45100 | C25: 42315 | D25: 46150 | F25: 41975 | G25: 44300 | I25: 44300 | J25: 42470 | K25: =D24+800 -> 44322.727 | M25: =44000-1000-G24 -> 1863.6364 | O25: =44000-G24-1000 -> 1863.6364 | P25: =46500-1350-1000-G24 -> 3013.6364
A26: Change (A-B) | B26: =B24-B25 -> -3163.6364 | C26: =C24-C25 -> -2327.2727 | D26: =D24-D25 -> -2627.2727 | E26: =E24-E25 -> 40093.182 | F26: =F24-F25 -> -2327.2727 | G26: =G24-G25 -> -3163.6364 | H26: =H24-H25 -> 41306.364 | I26: =I24-I25 -> -2070 | J26: =J24-J25 -> -2609.0909 | K26: =44000-800-D24 -> -322.72727 | N26: =43400-2500-F24 -> 1252.2727 | P26: 75 | Q26: 36
B27: =B25-2500 -> 42600 | G27: =G25-2500 -> 41800 | L27: =44000-2600-1000-F24 -> 752.27273 | M27: =44000-3000-F24 -> 1352.2727 | O27: =45300-900-1000-G24 -> 2263.6364 | P27: =44000-1000-G24 -> 1863.6364 | Q27: =44000-800-D24 -> -322.72727 | R27: =40540+1400 -> 41940
A28: Current PL | B28: 48300 | C28: 45550 | D28: 48800 | E28: 45550 | F28: 45550 | G28: 47500 | H28: 47800 | I28: 48300 | S28: =44100*1.18 -> 52038
A29: Current ex plant NR | B29: =B28-500-(200+300+300)-250-400 -> 46350 | C29: =C28-500-(200+300+300)-250-400 -> 43600 | D29: =D28-500-(200+300+300)-250-400 -> 46850 | E29: =E28-500-(200+300+300)-250-400 -> 43600 | F29: =F28-500-(200+300+300)-250-400 -> 43600 | G29: =G28-500-(200+300+300)-250-400 -> 45550 | H29: =H28-500-(200+300+300)-250-400 -> 45850 | I29: =I28-500-(200+300+300)-250-400 -> 46350 | L29: =44000-1200-B24 -> 863.63636 | M29: =44000-1000-G24 -> 1863.6364 | N29: =44800-900-1000-G24 -> 1763.6364 | P29: =44800-1000-900-G24 -> 1763.6364 | Q29: =(Q27*Q26+P27*P26)/(P26+Q26) -> 1154.5455 | S29: =350000/860 -> 406.97674
A30: Current GM: C | B30: =B29-B24 -> 4413.6364 | C30: =C29-C24 -> 3612.2727 | D30: =D29-D24 -> 3327.2727 | E30: =E29-E24 -> 3506.8182 | F30: =F29-F24 -> 3952.2727 | G30: =G29-G24 -> 4413.6364 | H30: =H29-H24 -> 4543.6364 | I30: =I29-I24 -> 4120 | N30: =45400-1750-1000-G24 -> 1513.6364
M31: =45050-1050-800-D24 -> -322.72727 | O31: =43400-2000-F24 -> 1752.2727
B32: =B24+900+500 -> 43336.364
M33: =43800-3000-F24 -> 1152.2727 | N33: =44000-2300-1000-F24 -> 1052.2727 | XFD33: Asking Price Deliverd
XFD34: 43500
A35: Plant | B35: Jul H1 notional | XFD35: 44000
A36: Sikandarabad | B36: 46000 | XFD36: 43500
A37: API, Raipur | B37: 42615 | C37: =B37+1250 -> 43865 | R37: Raunak Infra | S37: Approved Qty from SKA Plant | T37: Invoiced qty from Gwalior | U37: Planned to Inoviced from API | XFD37: 44000
A38: SKA, Raipur | B38: 42275 | C38: =B38+1000 -> 43275 | R38: Qty (MT) | S38: 815 | T38: 207 | U38: =S38-T38 -> 608 | XFD38: 43000
A39: Kala Amb | B39: 46450 | C39: =B39+800 -> 47250 | R39: Approval FOR Price | S39: 46000 | T39: 46000 | U39: 46000 | XFD39: 43500
A40: Gwalior | B40: 45200 | C40: =B40+1000 -> 46200 | R40: Freight | S40: 3300 | T40: 1450 | U40: 3350 | XFD40: 44000
A41: Jaipur | B41: 44470 | R41: Grade -550D | S41: 1000 | T41: 1000 | U41: 1250 | XFD41: 45000
A42: Roukeral | B42: 43675 | R42: Ex-works Price | S42: =S39-S40-S41 -> 41700 | T42: =T39-T40-T41 -> 43550 | U42: =U39-U40-U41 -> 41400 | XFD42: 43500
A43: Gujarat | B43: =44500-1000 -> 43500 | C43: =B43+1000 -> 44500 | R43: Adjusted margin as on 4th Aug'25 | S43: =S42-F24 -> 2052.2727 | T43: =T42-G24 -> 2413.6364 | U43: =U42-C24 -> 1412.2727 | XFD43: 44000
R44: Wt. Margin (Rs/MT) | T44: =SUMPRODUCT(T43:U43,T38:U38)/SUM(T38:U38) -> 1666.6068 | XFD44: 44000
XFD45: 44000
XFD46: 41000

Sheet Nov H1
B1: Fe 500
A2: Region / Date | B2: Ex-Ahmedabad | C2: Ex-Bangalore | D2: Ex-Chennai | E2: Ex-Delhi/NCR | F2: Ex-Durgapur | G2: Ex-Goa | H2: Ex-Hyderabad | I2: Ex-Jaipur | J2: Ex-Jalna | K2: Ex-Mandi Gobindgarh | L2: Ex-Mumbai | M2: Ex-Muzaffarnagar | N2: Ex-Patna | O2: Ex-Raigarh | P2: Ex-Raipur | Q2: Ex-Rourkela
A3: 45962 | B3: =_xlfn.XLOOKUP(A3,'steel Mint data'!A:A,'steel Mint data'!B:B,"",0) -> 42300 | E3: =_xlfn.XLOOKUP(A3,'steel Mint data'!A:A,'steel Mint data'!D:D,"",0) -> 41500 | F3: =_xlfn.XLOOKUP(A3,'steel Mint data'!A:A,'steel Mint data'!E:E,"",0) -> 38000 | I3: =_xlfn.XLOOKUP(A3,'steel Mint data'!A:A,'steel Mint data'!I:I,"",0) -> 40900 | K3: =_xlfn.XLOOKUP(A3,'steel Mint data'!A:A,'steel Mint data'!L:L,"",0) -> 43300 | P3: =_xlfn.XLOOKUP(A3,'steel Mint data'!A:A,'steel Mint data'!Q:Q,"",0) -> 38500 | Q3: =_xlfn.XLOOKUP(A3,'steel Mint data'!A:A,'steel Mint data'!R:R,"",0) -> 38400
A4: 45963 | B4: =_xlfn.XLOOKUP(A4,'steel Mint data'!A:A,'steel Mint data'!B:B,"",0) -> H | E4: =_xlfn.XLOOKUP(A4,'steel Mint data'!A:A,'steel Mint data'!D:D,"",0) -> H | F4: =_xlfn.XLOOKUP(A4,'steel Mint data'!A:A,'steel Mint data'!E:E,"",0) -> H | I4: =_xlfn.XLOOKUP(A4,'steel Mint data'!A:A,'steel Mint data'!I:I,"",0) -> H | K4: =_xlfn.XLOOKUP(A4,'steel Mint data'!A:A,'steel Mint data'!L:L,"",0) -> H | P4: =_xlfn.XLOOKUP(A4,'steel Mint data'!A:A,'steel Mint data'!Q:Q,"",0) -> H | Q4: =_xlfn.XLOOKUP(A4,'steel Mint data'!A:A,'steel Mint data'!R:R,"",0) -> H
A5: 45964 | B5: =_xlfn.XLOOKUP(A5,'steel Mint data'!A:A,'steel Mint data'!B:B,"",0) -> 42300 | E5: =_xlfn.XLOOKUP(A5,'steel Mint data'!A:A,'steel Mint data'!D:D,"",0) -> 41200 | F5: =_xlfn.XLOOKUP(A5,'steel Mint data'!A:A,'steel Mint data'!E:E,"",0) -> 37800 | I5: =_xlfn.XLOOKUP(A5,'steel Mint data'!A:A,'steel Mint data'!I:I,"",0) -> 40700 | K5: =_xlfn.XLOOKUP(A5,'steel Mint data'!A:A,'steel Mint data'!L:L,"",0) -> 43100 | P5: =_xlfn.XLOOKUP(A5,'steel Mint data'!A:A,'steel Mint data'!Q:Q,"",0) -> 38200 | Q5: =_xlfn.XLOOKUP(A5,'steel Mint data'!A:A,'steel Mint data'!R:R,"",0) -> 38200
A6: 45965 | B6: =_xlfn.XLOOKUP(A6,'steel Mint data'!A:A,'steel Mint data'!B:B,"",0) -> 42300 | E6: =_xlfn.XLOOKUP(A6,'steel Mint data'!A:A,'steel Mint data'!D:D,"",0) -> 41400 | F6: =_xlfn.XLOOKUP(A6,'steel Mint data'!A:A,'steel Mint data'!E:E,"",0) -> 38000 | I6: =_xlfn.XLOOKUP(A6,'steel Mint data'!A:A,'steel Mint data'!I:I,"",0) -> 40800 | K6: =_xlfn.XLOOKUP(A6,'steel Mint data'!A:A,'steel Mint data'!L:L,"",0) -> 43300 | P6: =_xlfn.XLOOKUP(A6,'steel Mint data'!A:A,'steel Mint data'!Q:Q,"",0) -> 38200 | Q6: =_xlfn.XLOOKUP(A6,'steel Mint data'!A:A,'steel Mint data'!R:R,"",0) -> 38200
A7: 45966 | B7: =_xlfn.XLOOKUP(A7,'steel Mint data'!A:A,'steel Mint data'!B:B,"",0) -> 42300 | E7: =_xlfn.XLOOKUP(A7,'steel Mint data'!A:A,'steel Mint data'!D:D,"",0) -> 41400 | F7: =_xlfn.XLOOKUP(A7,'steel Mint data'!A:A,'steel Mint data'!E:E,"",0) -> 37800 | I7: =_xlfn.XLOOKUP(A7,'steel Mint data'!A:A,'steel Mint data'!I:I,"",0) -> 40700 | K7: =_xlfn.XLOOKUP(A7,'steel Mint data'!A:A,'steel Mint data'!L:L,"",0) -> 43300 | P7: =_xlfn.XLOOKUP(A7,'steel Mint data'!A:A,'steel Mint data'!Q:Q,"",0) -> 38000 | Q7: =_xlfn.XLOOKUP(A7,'steel Mint data'!A:A,'steel Mint data'!R:R,"",0) -> 38200
A8: 45967 | B8: =_xlfn.XLOOKUP(A8,'steel Mint data'!A:A,'steel Mint data'!B:B,"",0) -> 42200 | E8: =_xlfn.XLOOKUP(A8,'steel Mint data'!A:A,'steel Mint data'!D:D,"",0) -> 41400 | F8: =_xlfn.XLOOKUP(A8,'steel Mint data'!A:A,'steel Mint data'!E:E,"",0) -> 37800 | I8: =_xlfn.XLOOKUP(A8,'steel Mint data'!A:A,'steel Mint data'!I:I,"",0) -> 40800 | K8: =_xlfn.XLOOKUP(A8,'steel Mint data'!A:A,'steel Mint data'!L:L,"",0) -> 43200 | P8: =_xlfn.XLOOKUP(A8,'steel Mint data'!A:A,'steel Mint data'!Q:Q,"",0) -> 37800 | Q8: =_xlfn.XLOOKUP(A8,'steel Mint data'!A:A,'steel Mint data'!R:R,"",0) -> 38200
A9: 45968 | B9: =_xlfn.XLOOKUP(A9,'steel Mint data'!A:A,'steel Mint data'!B:B,"",0) -> 42000 | E9: =_xlfn.XLOOKUP(A9,'steel Mint data'!A:A,'steel Mint data'!D:D,"",0) -> 41300 | F9: =_xlfn.XLOOKUP(A9,'steel Mint data'!A:A,'steel Mint data'!E:E,"",0) -> 37800 | I9: =_xlfn.XLOOKUP(A9,'steel Mint data'!A:A,'steel Mint data'!I:I,"",0) -> 40700 | K9: =_xlfn.XLOOKUP(A9,'steel Mint data'!A:A,'steel Mint data'!L:L,"",0) -> 43200 | P9: =_xlfn.XLOOKUP(A9,'steel Mint data'!A:A,'steel Mint data'!Q:Q,"",0) -> 37600 | Q9: =_xlfn.XLOOKUP(A9,'steel Mint data'!A:A,'steel Mint data'!R:R,"",0) -> 38000
A10: 45969 | B10: =_xlfn.XLOOKUP(A10,'steel Mint data'!A:A,'steel Mint data'!B:B,"",0) -> 42000 | E10: =_xlfn.XLOOKUP(A10,'steel Mint data'!A:A,'steel Mint data'!D:D,"",0) -> 41200 | F10: =_xlfn.XLOOKUP(A10,'steel Mint data'!A:A,'steel Mint data'!E:E,"",0) -> 37700 | I10: =_xlfn.XLOOKUP(A10,'steel Mint data'!A:A,'steel Mint data'!I:I,"",0) -> 40500 | K10: =_xlfn.XLOOKUP(A10,'steel Mint data'!A:A,'steel Mint data'!L:L,"",0) -> 43100 | P10: =_xlfn.XLOOKUP(A10,'steel Mint data'!A:A,'steel Mint data'!Q:Q,"",0) -> 37600 | Q10: =_xlfn.XLOOKUP(A10,'steel Mint data'!A:A,'steel Mint data'!R:R,"",0) -> 38000
A11: 45970 | B11: =_xlfn.XLOOKUP(A11,'steel Mint data'!A:A,'steel Mint data'!B:B,"",0) -> H | E11: =_xlfn.XLOOKUP(A11,'steel Mint data'!A:A,'steel Mint data'!D:D,"",0) -> H | F11: =_xlfn.XLOOKUP(A11,'steel Mint data'!A:A,'steel Mint data'!E:E,"",0) -> H | I11: =_xlfn.XLOOKUP(A11,'steel Mint data'!A:A,'steel Mint data'!I:I,"",0) -> H | K11: =_xlfn.XLOOKUP(A11,'steel Mint data'!A:A,'steel Mint data'!L:L,"",0) -> H | P11: =_xlfn.XLOOKUP(A11,'steel Mint data'!A:A,'steel Mint data'!Q:Q,"",0) -> H | Q11: =_xlfn.XLOOKUP(A11,'steel Mint data'!A:A,'steel Mint data'!R:R,"",0) -> H
A12: 45971 | B12: =_xlfn.XLOOKUP(A12,'steel Mint data'!A:A,'steel Mint data'!B:B,"",0) -> 41900 | E12: =_xlfn.XLOOKUP(A12,'steel Mint data'!A:A,'steel Mint data'!D:D,"",0) -> 41000 | F12: =_xlfn.XLOOKUP(A12,'steel Mint data'!A:A,'steel Mint data'!E:E,"",0) -> 37800 | I12: =_xlfn.XLOOKUP(A12,'steel Mint data'!A:A,'steel Mint data'!I:I,"",0) -> 40500 | K12: =_xlfn.XLOOKUP(A12,'steel Mint data'!A:A,'steel Mint data'!L:L,"",0) -> 43100 | P12: =_xlfn.XLOOKUP(A12,'steel Mint data'!A:A,'steel Mint data'!Q:Q,"",0) -> 37600 | Q12: =_xlfn.XLOOKUP(A12,'steel Mint data'!A:A,'steel Mint data'!R:R,"",0) -> 37800
A13: 45972 | B13: =_xlfn.XLOOKUP(A13,'steel Mint data'!A:A,'steel Mint data'!B:B,"",0) -> 41900 | E13: =_xlfn.XLOOKUP(A13,'steel Mint data'!A:A,'steel Mint data'!D:D,"",0) -> 41500 | F13: =_xlfn.XLOOKUP(A13,'steel Mint data'!A:A,'steel Mint data'!E:E,"",0) -> 38100 | I13: =_xlfn.XLOOKUP(A13,'steel Mint data'!A:A,'steel Mint data'!I:I,"",0) -> 40600 | K13: =_xlfn.XLOOKUP(A13,'steel Mint data'!A:A,'steel Mint data'!L:L,"",0) -> 43400 | P13: =_xlfn.XLOOKUP(A13,'steel Mint data'!A:A,'steel Mint data'!Q:Q,"",0) -> 37800 | Q13: =_xlfn.XLOOKUP(A13,'steel Mint data'!A:A,'steel Mint data'!R:R,"",0) -> 38000
A14: 45973 | B14: =_xlfn.XLOOKUP(A14,'steel Mint data'!A:A,'steel Mint data'!B:B,"",0) -> 41900 | E14: =_xlfn.XLOOKUP(A14,'steel Mint data'!A:A,'steel Mint data'!D:D,"",0) -> 41400 | F14: =_xlfn.XLOOKUP(A14,'steel Mint data'!A:A,'steel Mint data'!E:E,"",0) -> 38000 | I14: =_xlfn.XLOOKUP(A14,'steel Mint data'!A:A,'steel Mint data'!I:I,"",0) -> 40600 | K14: =_xlfn.XLOOKUP(A14,'steel Mint data'!A:A,'steel Mint data'!L:L,"",0) -> 43500 | P14: =_xlfn.XLOOKUP(A14,'steel Mint data'!A:A,'steel Mint data'!Q:Q,"",0) -> 37700 | Q14: =_xlfn.XLOOKUP(A14,'steel Mint data'!A:A,'steel Mint data'!R:R,"",0) -> 38000
... A16: 45975 | B16: =_xlfn.XLOOKUP(A16,'steel Mint data'!A:A,'steel Mint data'!B:B,"",0) -> 42300 | E16: =_xlfn.XLOOKUP(A16,'steel Mint data'!A:A,'steel Mint data'!D:D,"",0) -> 41800 | F16: =_xlfn.XLOOKUP(A16,'steel Mint data'!A:A,'steel Mint data'!E:E,"",0) -> 38000 | I16: =_xlfn.XLOOKUP(A16,'steel Mint data'!A:A,'steel Mint data'!I:I,"",0) -> 41000 | K16: =_xlfn.XLOOKUP(A16,'steel Mint data'!A:A,'steel Mint data'!L:L,"",0) -> 43700 | P16: =_xlfn.XLOOKUP(A16,'steel Mint data'!A:A,'steel Mint data'!Q:Q,"",0) -> 38100 | Q16: =_xlfn.XLOOKUP(A16,'steel Mint data'!A:A,'steel Mint data'!R:R,"",0) -> 38400
A17: 45976
A18: 45977
B19: =SUM(B3:B18) -> 505600 | E19: =SUM(E3:E18) -> 496700 | F19: =SUM(F3:F18) -> 454900 | I19: =SUM(I3:I18) -> 488700 | K19: =SUM(K3:K18) -> 519800 | P19: =SUM(P3:P18) -> 455100 | Q19: =SUM(Q3:Q18) -> 457600
B20: Amba Shakti (NCR) | C20: API (Raipur) | D20: Aditya Industries (Mandi) | E20: Shree Ganesh (Rourkela) | F20: SKA Raipur | G20: Amba Gwalior 43700 | H20: Rajasthan | I20: Gujarat | J20: Bardhman | M20: =40100+H22+H23 -> 41170
A21: Avg Price - Divided by no of days steel mint price is available | B21: =E19/O21 -> 41391.667 | C21: =P19/O21 -> 37925 | D21: =K19/O21 -> 43316.667 | E21: =Q19/O21 -> 38133.333 | F21: =C21 -> 37925 | G21: =B21-800 -> 40591.667 | H21: =I19/O21 -> 40725 | I21: =B19/(O21) -> 42133.333 | J21: =F19/O21 -> 37908.333 | O21: =COUNT(P3:P18) -> 12
A22: BIS | B22: 1200 | C22: 2150 | D22: 400 | E22: 2200 | F22: 1800 | G22: 1200 | H22: 800 | I22: 0 | J22: 2000 | K22: =F24+3500 -> 43500 | R22: =42800-G24 -> 808.33333
A23: Loading Charges | B23: 200 | C23: 265 | D23: 250 | E23: 275 | F23: 275 | G23: 200 | H23: 270 | I23: 200 | J23: 270 | K23: =G24+1700 -> 43691.667 | M23: =45500-1225-D24 -> 308.33333 | N23: =45500-1225 -> 44275 | P23: =42400-1700-F24 -> 700
A24: Actual PO Price (base dia): A | B24: =SUM(B21:B23) -> 42791.667 | C24: =SUM(C21:C23) -> 40340 | D24: =SUM(D21:D23) -> 43966.667 | E24: =SUM(E21:E23) -> 40608.333 | F24: =SUM(F21:F23) -> 40000 | G24: =SUM(G21:G23) -> 41991.667 | H24: =SUM(H21:H23) -> 41795 | I24: =SUM(I21:I23) -> 42333.333 | J24: =SUM(J21:J23) -> 40178.333 | L24: =44500-B24-900 -> 808.33333 | M24: =44500-4000-F24 -> 500
A25: Notional PO: B | B25: 45100 | C25: 42315 | D25: 46150 | F25: 41975 | G25: 44300 | I25: 44300 | J25: 42470 | K25: =45000-3800-F24 -> 1200 | L25: =41700-F24 -> 1700 | M25: =43400-525-F24 -> 2875 | N25: =41700-F24 -> 1700 | P25: =43550-900-B24 -> -141.66667
A26: Change (A-B) | B26: =B24-B25 -> -2308.3333 | C26: =C24-C25 -> -1975 | D26: =D24-D25 -> -2183.3333 | E26: =E24-E25 -> 40608.333 | F26: =F24-F25 -> -1975 | G26: =G24-G25 -> -2308.3333 | H26: =H24-H25 -> 41795 | I26: =I24-I25 -> -1966.6667 | J26: =J24-J25 -> -2291.6667 | L26: =43500-2100 -> 41400 | O26: =45000-3150-F24 -> 1850 | Q26: =44000-2900-F24 -> 1100 | R26: =44500-3500-F24 -> 1000
B27: =B25-2500 -> 42600 | G27: =G25-2500 -> 41800 | M27: =43800-1000-G24 -> 808.33333 | N27: =45000-1300-1000-G24 -> 708.33333 | P27: =44000-4000-F24 -> 0 | Q27: =46250-2400-1000-G24 -> 858.33333
A28: Current PL | B28: 48300 | C28: 45550 | D28: 48800 | E28: 45550 | F28: 45550 | G28: 47500 | H28: 47800 | I28: 48300 | L28: =40500+3600 -> 44100
A29: Current ex plant NR | B29: =B28-500-(200+300+300)-250-400 -> 46350 | C29: =C28-500-(200+300+300)-250-400 -> 43600 | D29: =D28-500-(200+300+300)-250-400 -> 46850 | E29: =E28-500-(200+300+300)-250-400 -> 43600 | F29: =F28-500-(200+300+300)-250-400 -> 43600 | G29: =G28-500-(200+300+300)-250-400 -> 45550 | H29: =H28-500-(200+300+300)-250-400 -> 45850 | I29: =I28-500-(200+300+300)-250-400 -> 46350 | K29: =44900-3800-F24 -> 1100 | M29: =43000-500-1000-F24 -> 1500 | N29: =43500-800-B24 -> -91.666667 | O29: =43500-2700-F24 -> 800 | Q29: =44500-3500-F24 -> 1000
A30: Current GM: C | B30: =B29-B24 -> 3558.3333 | C30: =C29-C24 -> 3260 | D30: =D29-D24 -> 2883.3333 | E30: =E29-E24 -> 2991.6667 | F30: =F29-F24 -> 3600 | G30: =G29-G24 -> 3558.3333 | H30: =H29-H24 -> 4055 | I30: =I29-I24 -> 4016.6667 | L30: =45000-3500-F24 -> 1500 | N30: =44800-1000-1000-I24 -> 466.66667 | P30: =44700-1600-B24 -> 308.33333 | Q30: =44700-3800-F24 -> 900
M31: =44700-2700-1000-F24 -> 1000 | O31: =45000-1300-1000-G24 -> 708.33333
A32: Fe 550 | B32: 43250 | C32: 41500 | D32: 44250 | G32: 42750 | L32: =44800+3500+600 -> 48900 | M32: =42000-1000-F24 -> 1000 | Q32: =45850-1600-D24 -> 283.33333
A33: LRF | C33: =44300-750 -> 43550 | D33: =C33-2200-C24 -> 1010 | G33: 44000 | I33: 44000 | J33: =45550+600 -> 46150 | N33: =43700+1950 -> 45650 | P33: =44500-1000-B24 -> 708.33333 | XFD33: Asking Price Deliverd
C34: =44300-2200-C24 -> 1760 | J34: =J33-4000-I24-1000 -> -1183.3333 | XFD34: 43500
A35: Margin | B35: =B32-B24-1000 -> -541.66667 | C35: =C32-C24-700 -> 460 | D35: =D32-D24-500 -> -216.66667 | G35: =G32-G24-1000 -> -241.66667 | I35: =I33-I24-500-1000 -> 166.66667 | O35: =43750-2200-F24 -> 1550 | XFD35: 44000
E36: =43200-1700-C24 -> 1160 | XFD36: 43500
D37: =45500-1225-D24 -> 308.33333 | R37: Raunak Infra | S37: Approved Qty from SKA Plant | T37: Invoiced qty from Gwalior | U37: Planned to Inoviced from API | XFD37: 44000
C38: =45550-1600-D24 -> -16.666667 | D38: =45550-1800-D24 -> -216.66667 | R38: Qty (MT) | S38: 815 | T38: 207 | U38: =S38-T38 -> 608 | XFD38: 43000
R39: Approval FOR Price | S39: 46000 | T39: 46000 | U39: 46000 | XFD39: 43500
A40: Plant | B40: Jul H1 notional | G40: =45550+600-4000-I24 -> -183.33333 | R40: Freight | S40: 3300 | T40: 1450 | U40: 3350 | XFD40: 44000
A41: Sikandarabad | B41: 46000 | R41: Grade -550D | S41: 1000 | T41: 1000 | U41: 1250 | XFD41: 45000
A42: API, Raipur | B42: 42615 | C42: =B42+1250 -> 43865 | R42: Ex-works Price | S42: =S39-S40-S41 -> 41700 | T42: =T39-T40-T41 -> 43550 | U42: =U39-U40-U41 -> 41400 | XFD42: 43500
A43: SKA, Raipur | B43: 42275 | C43: =B43+1000 -> 43275 | G43: =45550-1600-D24 -> -16.666667 | R43: Adjusted margin as on 4th Aug'25 | S43: =S42-F24 -> 1700 | T43: =T42-G24 -> 1558.3333 | U43: =U42-C24 -> 1060 | XFD43: 44000
A44: Kala Amb | B44: 46450 | C44: =B44+800 -> 47250 | R44: Wt. Margin (Rs/MT) | T44: =SUMPRODUCT(T43:U43,T38:U38)/SUM(T38:U38) -> 1186.5706 | XFD44: 44000
A45: Gwalior | B45: 45200 | C45: =B45+1000 -> 46200 | XFD45: 44000
A46: Jaipur | B46: 44470 | XFD46: 41000
A47: Roukeral | B47: 43675
A48: Gujarat | B48: =44500-1000 -> 43500 | C48: =B48+1000 -> 44500
B51: Amba Shakti (NCR) | C51: API (Raipur) | D51: Aditya Industries (Mandi) | E51: Shree Ganesh (Rourkela) | F51: SKA Raipur | G51: Amba Gwalior 43700 | H51: Rajasthan | I51: Gujarat | J51: Bardhman
A52: Fe 550 | B52: 43250 | C52: 41000 | D52: 44250 | E52: 40600 | F52: 40750 | G52: 42750 | I52: 42500
A53: Fe 550D | G53: 43700 | I53: 43500
A55: Margin | B55: =B52-B24 -> 458.33333 | C55: =C52-C24 -> 660 | D55: =D52-D24 -> 283.33333 | E55: =E52-E24 -> -8.3333333 | F55: =F52-F24 -> 750 | G55: =G52-G24 -> 758.33333 | H55: =H52-H24 -> -41795 | I55: =I52-I24 -> 166.66667 | J55: =J52-J24 -> -40178.333

Sheet Nov H2
B1: Fe 500
A2: Region / Date | B2: Ex-Ahmedabad | C2: Ex-Bangalore | D2: Ex-Chennai | E2: Ex-Delhi/NCR | F2: Ex-Durgapur | G2: Ex-Goa | H2: Ex-Hyderabad | I2: Ex-Jaipur | J2: Ex-Jalna | K2: Ex-Mandi Gobindgarh | L2: Ex-Mumbai | M2: Ex-Muzaffarnagar | N2: Ex-Patna | O2: Ex-Raigarh | P2: Ex-Raipur | Q2: Ex-Rourkela
A3: 45977 | B3: =_xlfn.XLOOKUP(A3,'steel Mint data'!A:A,'steel Mint data'!B:B,"",0) -> H | E3: =_xlfn.XLOOKUP(A3,'steel Mint data'!A:A,'steel Mint data'!D:D,"",0) -> H | F3: =_xlfn.XLOOKUP(A3,'steel Mint data'!A:A,'steel Mint data'!E:E,"",0) -> H | I3: =_xlfn.XLOOKUP(A3,'steel Mint data'!A:A,'steel Mint data'!I:I,"",0) -> H | K3: =_xlfn.XLOOKUP(A3,'steel Mint data'!A:A,'steel Mint data'!L:L,"",0) -> H | P3: =_xlfn.XLOOKUP(A3,'steel Mint data'!A:A,'steel Mint data'!Q:Q,"",0) -> H | Q3: =_xlfn.XLOOKUP(A3,'steel Mint data'!A:A,'steel Mint data'!R:R,"",0) -> H
A4: 45978 | B4: =_xlfn.XLOOKUP(A4,'steel Mint data'!A:A,'steel Mint data'!B:B,"",0) -> 42500 | E4: =_xlfn.XLOOKUP(A4,'steel Mint data'!A:A,'steel Mint data'!D:D,"",0) -> 42300 | F4: =_xlfn.XLOOKUP(A4,'steel Mint data'!A:A,'steel Mint data'!E:E,"",0) -> 38600 | I4: =_xlfn.XLOOKUP(A4,'steel Mint data'!A:A,'steel Mint data'!I:I,"",0) -> 41600 | K4: =_xlfn.XLOOKUP(A4,'steel Mint data'!A:A,'steel Mint data'!L:L,"",0) -> 44100 | P4: =_xlfn.XLOOKUP(A4,'steel Mint data'!A:A,'steel Mint data'!Q:Q,"",0) -> 38500 | Q4: =_xlfn.XLOOKUP(A4,'steel Mint data'!A:A,'steel Mint data'!R:R,"",0) -> 38800
A5: 45979 | B5: =_xlfn.XLOOKUP(A5,'steel Mint data'!A:A,'steel Mint data'!B:B,"",0) -> 42500 | E5: =_xlfn.XLOOKUP(A5,'steel Mint data'!A:A,'steel Mint data'!D:D,"",0) -> 42100 | F5: =_xlfn.XLOOKUP(A5,'steel Mint data'!A:A,'steel Mint data'!E:E,"",0) -> 38600 | I5: =_xlfn.XLOOKUP(A5,'steel Mint data'!A:A,'steel Mint data'!I:I,"",0) -> 41500 | K5: =_xlfn.XLOOKUP(A5,'steel Mint data'!A:A,'steel Mint data'!L:L,"",0) -> 44200 | P5: =_xlfn.XLOOKUP(A5,'steel Mint data'!A:A,'steel Mint data'!Q:Q,"",0) -> 38500 | Q5: =_xlfn.XLOOKUP(A5,'steel Mint data'!A:A,'steel Mint data'!R:R,"",0) -> 38700
A6: 45980 | B6: =_xlfn.XLOOKUP(A6,'steel Mint data'!A:A,'steel Mint data'!B:B,"",0) -> 42500 | E6: =_xlfn.XLOOKUP(A6,'steel Mint data'!A:A,'steel Mint data'!D:D,"",0) -> 42000 | F6: =_xlfn.XLOOKUP(A6,'steel Mint data'!A:A,'steel Mint data'!E:E,"",0) -> 38500 | I6: =_xlfn.XLOOKUP(A6,'steel Mint data'!A:A,'steel Mint data'!I:I,"",0) -> 41500 | K6: =_xlfn.XLOOKUP(A6,'steel Mint data'!A:A,'steel Mint data'!L:L,"",0) -> 44000 | P6: =_xlfn.XLOOKUP(A6,'steel Mint data'!A:A,'steel Mint data'!Q:Q,"",0) -> 38400 | Q6: =_xlfn.XLOOKUP(A6,'steel Mint data'!A:A,'steel Mint data'!R:R,"",0) -> 38700
A7: 45981 | B7: =_xlfn.XLOOKUP(A7,'steel Mint data'!A:A,'steel Mint data'!B:B,"",0) -> 42500 | E7: =_xlfn.XLOOKUP(A7,'steel Mint data'!A:A,'steel Mint data'!D:D,"",0) -> 42100 | F7: =_xlfn.XLOOKUP(A7,'steel Mint data'!A:A,'steel Mint data'!E:E,"",0) -> 38900 | I7: =_xlfn.XLOOKUP(A7,'steel Mint data'!A:A,'steel Mint data'!I:I,"",0) -> 41700 | K7: =_xlfn.XLOOKUP(A7,'steel Mint data'!A:A,'steel Mint data'!L:L,"",0) -> 44400 | P7: =_xlfn.XLOOKUP(A7,'steel Mint data'!A:A,'steel Mint data'!Q:Q,"",0) -> 38400 | Q7: =_xlfn.XLOOKUP(A7,'steel Mint data'!A:A,'steel Mint data'!R:R,"",0) -> 38700
A8: 45982 | B8: =_xlfn.XLOOKUP(A8,'steel Mint data'!A:A,'steel Mint data'!B:B,"",0) -> 42700 | E8: =_xlfn.XLOOKUP(A8,'steel Mint data'!A:A,'steel Mint data'!D:D,"",0) -> 42100 | F8: =_xlfn.XLOOKUP(A8,'steel Mint data'!A:A,'steel Mint data'!E:E,"",0) -> 38800 | I8: =_xlfn.XLOOKUP(A8,'steel Mint data'!A:A,'steel Mint data'!I:I,"",0) -> 41500 | K8: =_xlfn.XLOOKUP(A8,'steel Mint data'!A:A,'steel Mint data'!L:L,"",0) -> 44400 | P8: =_xlfn.XLOOKUP(A8,'steel Mint data'!A:A,'steel Mint data'!Q:Q,"",0) -> 38400 | Q8: =_xlfn.XLOOKUP(A8,'steel Mint data'!A:A,'steel Mint data'!R:R,"",0) -> 38700
A9: 45983 | B9: =_xlfn.XLOOKUP(A9,'steel Mint data'!A:A,'steel Mint data'!B:B,"",0) -> 42700 | E9: =_xlfn.XLOOKUP(A9,'steel Mint data'!A:A,'steel Mint data'!D:D,"",0) -> 42200 | F9: =_xlfn.XLOOKUP(A9,'steel Mint data'!A:A,'steel Mint data'!E:E,"",0) -> 38800 | I9: =_xlfn.XLOOKUP(A9,'steel Mint data'!A:A,'steel Mint data'!I:I,"",0) -> 41400 | K9: =_xlfn.XLOOKUP(A9,'steel Mint data'!A:A,'steel Mint data'!L:L,"",0) -> 44400 | P9: =_xlfn.XLOOKUP(A9,'steel Mint data'!A:A,'steel Mint data'!Q:Q,"",0) -> 38300 | Q9: =_xlfn.XLOOKUP(A9,'steel Mint data'!A:A,'steel Mint data'!R:R,"",0) -> 38500
A10: 45984 | B10: =_xlfn.XLOOKUP(A10,'steel Mint data'!A:A,'steel Mint data'!B:B,"",0) -> H | E10: =_xlfn.XLOOKUP(A10,'steel Mint data'!A:A,'steel Mint data'!D:D,"",0) -> H | F10: =_xlfn.XLOOKUP(A10,'steel Mint data'!A:A,'steel Mint data'!E:E,"",0) -> H | I10: =_xlfn.XLOOKUP(A10,'steel Mint data'!A:A,'steel Mint data'!I:I,"",0) -> H | K10: =_xlfn.XLOOKUP(A10,'steel Mint data'!A:A,'steel Mint data'!L:L,"",0) -> H | P10: =_xlfn.XLOOKUP(A10,'steel Mint data'!A:A,'steel Mint data'!Q:Q,"",0) -> H | Q10: =_xlfn.XLOOKUP(A10,'steel Mint data'!A:A,'steel Mint data'!R:R,"",0) -> H
